Workbook

Sheet задание
A1: № | B1: Условия акции - все задания выполнить с использованием формул, для каждого критерия создать отдельный столбец в котором указать, удовлетворяет ли строка отчета проверяемому критерию, остальные пункты графики и сводные таблицы делать на отдельных листах
A2: 1 | B2: дата отправки смс должна была быть в период 01.10 по 14.10 | C2: лист "выгрузка -- копия (2)"
A3: 3 | B3: у комплекта обязательно должна быть регистрация (дата регистрации) | C3: лист "выгрузка -- копия (2)"
A4: 4 | B4: дилер должен быть в списке дилеров (номер ЛС дилера должен быть со списка на листе "дилеры участники") | C4: лист "выгрузка -- копия (2)"
A5: 5 | B5: тарифный план должен быть в списке тарифных планов (лист "ставки тарифы") | C5: лист "выгрузка -- копия (2)"
A6: 6 | B6: канал дилера, чей комплект отправляется, должен быть среди каналов (стоять згачение 1), в которых отправленный тп бонусируется (см. лист ставки тарифы) | C6: лист "выгрузка -- копия (2)"
A7: 7 | B7: проверить отправленные номера комплектов на задвоения, если один и тот же номер отправлен несколько раз, то исключаются все комплекты кроме того, у которого дата отправки смс была ближе к дате активации (как до, так и после) | C7: на листе "Задание 7". Методика: 1) Создаём столбец с модулем разности даты активации и даты отправки смс. 2) Сортируем этот столбец по убыванию. 3) Сортируем столбец с номером комплекта по возрастанию. При этом повторяющиеся значения находятся рядом, при этом таблица всё ещё отсортирована по убыванию модуля разности. 4) Удаляем дубликаты по столбцу с номером комплекта, и из-за применённых сортировок остаются строки и наименьшим модулем разности.
A8: 8 | B8: произвести расчет вознаграждения для каждого отправленного смс с учетом суммы стартового баланса и дополнительного платежа (см. таблицу ставки и тарифы), смс должны удовлетварять всем предыдущим условиям | C8: лист "выгрузка -- копия (2)"
A9: 9 | B9: построить сводную таблицу в которой было бы видно, какому участнику (по его номеру) начисляется какое суммарное вознаграждение (упорядочить от наибольшего вознаграждения к меньшему) | C9: лист "Задание 9"
A10: 10 | B10: сгруппировать Тарифный планы по группам (Smart, Ultra, Супер МТС) | C10: лист "выгрузка -- копия (2)", столбец 10 -- группа тарифа
A11: 11 | B11: проанализировать смс, котрые не прошли по указанным критериям, сделать предположение, какой критерий(условие) можно добавить/отменить/изменить, чтобы больше комплектов попадали под бонусирование. | C11: Больше всего "срезается" из-за малого количества дилеров-участников, можно подключить больше дилеров к программе
A12: 12 | B12: вывести диаграмму из которой видно, какую долю среди уникальных блокированных абонентов занимает регион среди всех уникальных блокированных абонентов | C12: лист "Задание 12"
A13: 13 | B13: по блокированным определить в какой месяц от даты активации произошла блокировка | C13: лист "Задание 13". Надеюсь, правильно понял формулировку

Sheet ставки тарифы
C1: пороговые значения: | D1: 100 | E1: 200 | F1: 300
A2: Название ТП комплекта | B2: Локальный | C2: Непрофильный | D2: 0 | E2: 2 | F2: 3
A3: Smart (МАСС) (SCP) | B3: 1 | C3: 1 | D3: 0 | E3: 0 | F3: 120
A4: Smart 052013 (МАСС) (SCP) | B4: 1 | C4: 1 | D4: 0 | E4: 0 | F4: 120
A5: Smart 102014 (МАСС) (SCP) | B5: 1 | C5: 1 | D5: 0 | E5: 0 | F5: 120
A6: Smart mini (МАСС) (SCP) | B6: 1 | C6: 1 | D6: 70 | E6: 110 | F6: 110
A7: Smart mini 102014 (МАСС) (SCP) | B7: 1 | C7: 1 | D7: 70 | E7: 110 | F7: 110
A8: Smart mini 112013 (МАСС) (SCP) | B8: 1 | C8: 1 | D8: 70 | E8: 110 | F8: 110
A9: Smart Nonstop (МАСС) (SCP) | B9: 1 | C9: 1 | D9: 0 | E9: 0 | F9: 200
A10: Smart Top (МАСС) (SCP) | B10: 1 | C10: 1 | D10: 0 | E10: 0 | F10: 200
A11: Smart+ (МАСС) (SCP) | B11: 1 | C11: 1 | D11: 0 | E11: 0 | F11: 200
A12: Smart+ 102014 (МАСС) (SCP) | B12: 1 | C12: 1 | D12: 0 | E12: 0 | F12: 200
A13: Smart+ на год (МАСС) (SCP) | B13: 1 | C13: 1 | D13: 0 | E13: 0 | F13: 200
A14: Ultra (КОРП) (SS) | B14: 1 | C14: 1 | D14: 0 | E14: 0 | F14: 220
... A19: МТС Коннект-4 (МАСС) (SCP) | B19: 1 | C19: 1 | D19: 0 | E19: 100 | F19: 170
A20: Супер МТС (МАСС) (SCP) | C20: 1 | D20: 70 | E20: 70 | F20: 70
A21: Супер МТС 042014 (МАСС) (SCP) | C21: 1 | D21: 70 | E21: 70 | F21: 70
A22: Супер МТС 0513 (МАСС) (SCP) | C22: 1 | D22: 70 | E22: 70 | F22: 70
A23: Супер МТС 082013 (МАСС) (SCP) | C23: 1 | D23: 70 | E23: 70 | F23: 70
A24: Супер МТС 092014 (МАСС) (SCP) | C24: 1 | D24: 70 | E24: 70 | F24: 70
A25: Супер МТС 2012 (МАСС) (SCP) | C25: 1 | D25: 70 | E25: 70 | F25: 70
A26: Супер МТС 2013 (МАСС) (SCP) | C26: 1 | D26: 70 | E26: 70 | F26: 70
A27: Супер МТС. Область (МАСС) (SCP) | C27: 1 | D27: 70 | E27: 70 | F27: 70
A28: Супер МТС. Область 072014 (МАСС) (SCP) | C28: 1 | D28: 70 | E28: 70 | F28: 70
A29: Супер МТС_2011 (МАСС) (SCP) | C29: 1 | D29: 70 | E29: 70 | F29: 70

Sheet дилеры участники
A1: Дилеры участники
A2: 79956
A3: 64616
A4: 57078
A5: 66498

Sheet выгрузка 
A1: Дата отправки смс | B1: Номер отправителя | C1: Номер комплекта | D1: Дата активации | E1: Дата регистрации | F1: ЛС дилера | G1: Канал продажи | H1: ТП комплекта текущий | I1: ТП комплекта текущий2 | J1: Первоначальный баланс проданного комплекта | K1: Размер дополнительного платежа | L1: Сумма дополнительного платежа и стартового баланса | M1: статус комплекта | N1: дата блокировки
A2: 41583.542 | B2: 910467 | C2: 8500837 | D2: 41583.542 | E2: 41593.845 | F2: 79956 | G2: Непрофильный | H2: Тверь - Smart mini (МАСС) (SCP) | I2: Тверь - Smart mini (МАСС) (SCP) | J2: 30 | K2: 200 | L2: 230 | M2: Блокирован | N2: 41971
A3: 41558.712 | B3: 916012 | C3: 8511801 | D3: 41558.712 | F3: 73902 | G3: Непрофильный | H3: Тверь - Супер МТС (МАСС) (SCP) | I3: Тверь - Супер МТС (МАСС) (SCP) | J3: 30 | K3: 195 | L3: 225 | M3: Блокирован | N3: 41812
A4: 41555.831 | B4: 916692 | C4: 8550792 | D4: 41555.831 | F4: 73902 | G4: Непрофильный | H4: Тверь - Супер МТС (МАСС) (SCP) | I4: Тверь - Супер МТС (МАСС) (SCP) | J4: 30 | K4: 0 | L4: 30 | M4: Блокирован | N4: 41692
A5: 41557.684 | B5: 910441 | C5: 8514402 | D5: 41557.685 | F5: 73902 | G5: Непрофильный | H5: Тверь - МТС Коннект-4 (МАСС) (SCP) | I5: Тверь - МТС Коннект-4 (МАСС) (SCP) | J5: 949 | K5: 90.01 | L5: 1039.01 | M5: Блокирован | N5: 41803
A6: 41552.713 | B6: 919995 | C6: 1753744 | D6: 41552.712 | E6: 41552.716 | F6: 64626 | G6: Непрофильный | H6: Тверь - Smart mini (МАСС) (SCP) | I6: Тверь - Smart mini (МАСС) (SCP) | J6: 220 | K6: 0 | L6: 220 | M6: Активен
A7: 41560.465 | B7: 916496 | C7: 1755631 | D7: 41560.465 | F7: 64626 | G7: Непрофильный | H7: Тверь - МТС Коннект-4 (МАСС) (SCP) | I7: Тверь - МТС Коннект-4 (МАСС) (SCP) | J7: 30 | K7: 378 | L7: 408 | M7: Блокирован | N7: 41649
A8: 41559.574 | B8: 916496 | C8: 8503066 | D8: 41559.573 | E8: 41560.836 | F8: 64626 | G8: Непрофильный | H8: Тверь - МТС Коннект-4 (МАСС) (SCP) | I8: Тверь - МТС Коннект-4 (МАСС) (SCP) | J8: 30 | K8: 283.5 | L8: 313.5 | M8: Блокирован | N8: 41874
A9: 41561.285 | B9: 963978 | C9: 8520327 | D9: 41561.286 | F9: 64626 | G9: Непрофильный | H9: Тверь - Smart mini (МАСС) (SCP) | I9: Тверь - Smart mini (МАСС) (SCP) | J9: 30 | K9: 250 | L9: 280 | M9: Блокирован | N9: 41794
A10: 41560.411 | B10: 916496 | C10: 8520383 | D10: 41560.411 | F10: 64626 | G10: Непрофильный | H10: Тверь - МТС Коннект-4 (МАСС) (SCP) | I10: Тверь - МТС Коннект-4 (МАСС) (SCP) | J10: 1749 | K10: 0 | L10: 1749 | M10: Блокирован | N10: 41776
A11: 41554.326 | B11: 916496 | C11: 8503724 | D11: 41554.325 | E11: 41555.868 | F11: 64626 | G11: Непрофильный | H11: Тверь - МТС Коннект-4 (МАСС) (SCP) | I11: Тверь - МТС Коннект-4 (МАСС) (SCP) | J11: 30 | K11: 191 | L11: 221 | M11: Блокирован | N11: 41919
A12: 41560.824 | B12: 910467 | C12: 8500835 | D12: 41560.825 | F12: 79956 | G12: Непрофильный | H12: Тверь - Smart mini (МАСС) (SCP) | I12: Тверь - Smart mini (МАСС) (SCP) | J12: 30 | K12: 200 | L12: 230 | M12: Блокирован | N12: 41963
A13: 41551.599 | B13: 910450 | C13: 1996282 | D13: 41551.6 | F13: 64616 | G13: Непрофильный | H13: Тверь - Супер МТС (МАСС) (SCP) | I13: Тверь - Супер МТС (МАСС) (SCP) | J13: 30 | K13: 200 | L13: 230 | M13: Блокирован | N13: 41725
A14: 41561.664 | B14: 916566 | C14: 8527611 | D14: 41561.665 | F14: 64616 | G14: Непрофильный | H14: Тверь - Smart mini (МАСС) (SCP) | I14: Тверь - Smart mini (МАСС) (SCP) | J14: 30 | K14: 230 | L14: 260 | M14: Активен
A15: 41560.633 | B15: 910466 | C15: 8503673 | D15: 41560.634 | F15: 79956 | G15: Непрофильный | H15: Тверь - Smart mini (МАСС) (SCP) | I15: Тверь - Smart mini (МАСС) (SCP) | J15: 220 | K15: 0 | L15: 220 | M15: Блокирован | N15: 41844
A16: 41551.535 | B16: 910475 | C16: 8555316 | D16: 41551.534 | E16: 41556.434 | F16: 64626 | G16: Непрофильный | H16: Тверь - Smart mini (МАСС) (SCP) | I16: Тверь - Smart mini (МАСС) (SCP) | J16: 220 | K16: 0 | L16: 220 | M16: Блокирован | N16: 41969
A17: 41559.503 | B17: 915327 | C17: 1996837 | D17: 41559.505 | F17: 73902 | G17: Непрофильный | H17: Тверь - Супер МТС (МАСС) (SCP) | I17: Тверь - Супер МТС (МАСС) (SCP) | J17: 30 | K17: 1235 | L17: 1265 | M17: Блокирован | N17: 41890
A18: 41557.755 | B18: 917505 | C18: 1753781 | D18: 41557.754 | E18: 41558.78 | F18: 64626 | G18: Непрофильный | H18: Тверь - Smart mini (МАСС) (SCP) | I18: Тверь - Smart mini (МАСС) (SCP) | J18: 220 | K18: 0 | L18: 220 | M18: Активен
A19: 41555.665 | B19: 916692 | C19: 1753350 | D19: 41555.663 | F19: 73902 | G19: Непрофильный | H19: Тверь - Smart (МАСС) (SCP) | I19: Тверь - Smart (МАСС) (SCP) | J19: 30 | K19: 485 | L19: 515 | M19: Активен
A20: 41550.568 | B20: 916496 | C20: 8514427 | D20: 41550.567 | E20: 41560.808 | F20: 64626 | G20: Непрофильный | H20: Тверь - МТС Коннект-4 (МАСС) (SCP) | I20: Тверь - МТС Коннект-4 (МАСС) (SCP) | J20: 949 | K20: 0 | L20: 949 | M20: Блокирован | N20: 41815
A21: 41558.709 | B21: 910475 | C21: 8555317 | D21: 41558.707 | E21: 41560.99 | F21: 64626 | G21: Непрофильный | H21: Тверь - Smart mini (МАСС) (SCP) | I21: Тверь - Smart mini (МАСС) (SCP) | J21: 220 | K21: 0 | L21: 220 | M21: Блокирован | N21: 41955
A22: 41556.744 | B22: 916322 | C22: 1753092 | D22: 41556.746 | F22: 79956 | G22: Непрофильный | H22: Тверь - Smart mini (МАСС) (SCP) | I22: Тверь - Smart mini (МАСС) (SCP) | J22: 220 | K22: 0 | L22: 220 | M22: Активен
A23: 41556.441 | B23: 916496 | C23: 8503715 | D23: 41556.44 | E23: 41560.843 | F23: 64626 | G23: Непрофильный | H23: Тверь - МТС Коннект-4 (МАСС) (SCP) | I23: Тверь - МТС Коннект-4 (МАСС) (SCP) | J23: 30 | K23: 425.25 | L23: 455.25 | M23: Блокирован | N23: 41931
A24: 41551.605 | B24: 910441 | C24: 8561014 | D24: 41551.604 | E24: 41556.66 | F24: 73902 | G24: Непрофильный | H24: Тверь - МТС Коннект-4 (МАСС) (SCP) | I24: Тверь - МТС Коннект-4 (МАСС) (SCP) | J24: 30 | K24: 700 | L24: 730 | M24: Блокирован | N24: 41739
A25: 41553.706 | B25: 910487 | C25: 8563780 | D25: 41553.708 | F25: 73902 | G25: Непрофильный | H25: Тверь - Smart (МАСС) (SCP) | I25: Тверь - Smart (МАСС) (SCP) | J25: 470 | K25: 100 | L25: 570 | M25: Блокирован | N25: 41923
A26: 41558.766 | B26: 917505 | C26: 8524888 | D26: 41558.763 | E26: 41558.773 | F26: 64626 | G26: Непрофильный | H26: Тверь - МТС Коннект-4 (МАСС) (SCP) | I26: Тверь - МТС Коннект-4 (МАСС) (SCP) | J26: 401 | K26: 0 | L26: 401 | M26: Активен
A27: 41550.73 | B27: 916191 | C27: 8554807 | D27: 41550.732 | F27: 64616 | G27: Непрофильный | H27: Тверь - Smart (МАСС) (SCP) | I27: Тверь - Smart (МАСС) (SCP) | J27: 30 | K27: 700 | L27: 730 | M27: Блокирован | N27: 41718
A28: 41560.546 | B28: 919100 | C28: 8562412 | D28: 41560.544 | F28: 79956 | G28: Непрофильный | H28: Тверь - Супер МТС (МАСС) (SCP) | I28: Тверь - Супер МТС (МАСС) (SCP) | J28: 30 | K28: 188 | L28: 218 | M28: Блокирован | N28: 41783
A29: 41555.665 | B29: 916692 | C29: 1753359 | D29: 41555.663 | F29: 73902 | G29: Непрофильный | H29: Тверь - Smart (МАСС) (SCP) | I29: Тверь - Smart (МАСС) (SCP) | J29: 30 | K29: 485 | L29: 515 | M29: Активен
A30: 41554.443 | B30: 916425 | C30: 1999892 | D30: 41554.44 | F30: 79956 | G30: Непрофильный | H30: Тверь - Smart mini (МАСС) (SCP) | I30: Тверь - Smart mini (МАСС) (SCP) | J30: 220 | K30: 195.2 | L30: 415.2 | M30: Блокирован | N30: 42001
A31: 41548.566 | B31: 916510 | C31: 8502926 | D31: 41548.564 | E31: 41554.672 | F31: 73902 | G31: Непрофильный | H31: Тверь - Супер МТС. Область (МАСС) (SCP) | I31: Тверь - Супер МТС. Область (МАСС) (SCP) | J31: 30 | K31: 0 | L31: 30 | M31: Блокирован | N31: 41780
A32: 41548.7 | B32: 915323 | C32: 8503672 | D32: 41548.698 | E32: 41556.5 | F32: 64626 | G32: Непрофильный | H32: Тверь - Smart mini (МАСС) (SCP) | I32: Тверь - Smart mini (МАСС) (SCP) | J32: 20 | K32: 640 | L32: 660 | M32: Блокирован | N32: 41645
A33: 41556.465 | B33: 910459 | C33: 1755511 | D33: 41556.462 | E33: 41560.944 | F33: 64626 | G33: Непрофильный | H33: Тверь - Супер МТС (МАСС) (SCP) | I33: Тверь - Супер МТС (МАСС) (SCP) | J33: 30 | K33: 800 | L33: 830 | M33: Блокирован | N33: 41734
A34: 41551.561 | B34: 910475 | C34: 8555316 | D34: 41551.558 | E34: 41556.434 | F34: 64626 | G34: Непрофильный | H34: Тверь - Smart mini (МАСС) (SCP) | I34: Тверь - Smart mini (МАСС) (SCP) | J34: 220 | K34: 0 | L34: 220 | M34: Блокирован | N34: 41969
A35: 41561.735 | B35: 916542 | C35: 8500887 | D35: 41561.738 | F35: 79956 | G35: Непрофильный | H35: Тверь - Smart mini (МАСС) (SCP) | I35: Тверь - Smart mini (МАСС) (SCP) | J35: 30 | K35: 561.12 | L35: 591.12 | M35: Блокирован | N35: 41951
A36: 41554.609 | B36: 985351 | C36: 8500120 | D36: 41554.612 | E36: 41556.419 | F36: 79956 | G36: Непрофильный | H36: Тверь - Smart (МАСС) (SCP) | I36: Тверь - Smart (МАСС) (SCP) | J36: 470 | K36: 0 | L36: 470 | M36: Блокирован | N36: 41763
A37: 41553.702 | B37: 917505 | C37: 1753770 | D37: 41553.699 | E37: 41553.9 | F37: 64626 | G37: Непрофильный | H37: Тверь - Smart mini (МАСС) (SCP) | I37: Тверь - Smart mini (МАСС) (SCP) | J37: 220 | K37: 0 | L37: 220 | M37: Активен
A38: 41583.834 | B38: 910486 | C38: 8527896 | D38: 41583.83 | E38: 41585.695 | F38: 79956 | G38: Непрофильный | H38: Тверь - МТС Коннект-4 (МАСС) (SCP) | I38: Тверь - МТС Коннект-4 (МАСС) (SCP) | J38: 30 | K38: 752 | L38: 782 | M38: Активен
A39: 41559.818 | B39: 910488 | C39: 1750460 | D39: 41559.821 | E39: 41560.404 | F39: 64626 | G39: Непрофильный | H39: Тверь - Smart mini (МАСС) (SCP) | I39: Тверь - Smart mini (МАСС) (SCP) | J39: 220 | K39: 0 | L39: 220 | M39: Активен
A40: 41561.934 | B40: 915000 | C40: 8562212 | D40: 41561.93 | F40: 79956 | G40: Непрофильный | H40: Тверь - Smart mini (МАСС) (SCP) | I40: Тверь - Smart mini (МАСС) (SCP) | J40: 270 | K40: 0 | L40: 270 | M40: Блокирован | N40: 41822
A41: 41556.876 | B41: 919996 | C41: 1698592 | D41: 41556.88 | E41: 41560.938 | F41: 64626 | G41: Непрофильный | H41: Тверь - Супер МТС. Область (МАСС) (SCP) | I41: Тверь - Супер МТС. Область (МАСС) (SCP) | J41: 30 | K41: 110 | L41: 140 | M41: Активен
A42: 41557.81 | B42: 916366 | C42: 1750481 | D42: 41557.813 | F42: 73902 | G42: Непрофильный | H42: Тверь - Smart mini (МАСС) (SCP) | I42: Тверь - Smart mini (МАСС) (SCP) | J42: 30 | K42: 194 | L42: 224 | M42: Активен
A43: 41557.768 | B43: 985358 | C43: 8520666 | D43: 41557.764 | F43: 64616 | G43: Непрофильный | H43: Тверь - Smart mini (МАСС) (SCP) | I43: Тверь - Smart mini (МАСС) (SCP) | J43: 30 | K43: 237.5 | L43: 267.5 | M43: Блокирован | N43: 41662
A44: 41553.753 | B44: 916512 | C44: 8540117 | D44: 41553.748 | E44: 41556.554 | F44: 64616 | G44: Непрофильный | H44: Тверь - Smart mini (МАСС) (SCP) | I44: Тверь - Smart mini (МАСС) (SCP) | J44: 30 | K44: 294.01 | L44: 324.01 | M44: Активен
A45: 41560.75 | B45: 916523 | C45: 8550255 | D45: 41560.746 | F45: 64616 | G45: Непрофильный | H45: Тверь - Супер МТС (МАСС) (SCP) | I45: Тверь - Супер МТС (МАСС) (SCP) | J45: 50 | K45: 0 | L45: 50 | M45: Блокирован | N45: 41852
A46: 41553.566 | B46: 919100 | C46: 1699873 | D46: 41553.561 | E46: 41556.526 | F46: 64626 | G46: Непрофильный | H46: Тверь - Супер МТС (МАСС) (SCP) | I46: Тверь - Супер МТС (МАСС) (SCP) | J46: 30 | K46: 0 | L46: 30 | M46: Активен
A47: 41583.698 | B47: 916149 | C47: 8500307 | D47: 41583.702 | F47: 64616 | G47: Непрофильный | H47: Тверь - Супер МТС (МАСС) (SCP) | I47: Тверь - Супер МТС (МАСС) (SCP) | J47: 30 | K47: 0 | L47: 30 | M47: Блокирован | N47: 41951
A48: 41555.431 | B48: 916525 | C48: 8528041 | D48: 41555.427 | E48: 41557.737 | F48: 79956 | G48: Непрофильный | H48: Тверь - МТС Коннект-4 (МАСС) (SCP) | I48: Тверь - МТС Коннект-4 (МАСС) (SCP) | J48: 30 | K48: 611 | L48: 641 | M48: Активен
A49: 41555.711 | B49: 910488 | C49: 8550145 | D49: 41555.707 | E49: 41555.707 | F49: 64626 | G49: Непрофильный | H49: Тверь - Супер МТС (МАСС) (SCP) | I49: Тверь - Супер МТС (МАСС) (SCP) | J49: 50 | K49: 200 | L49: 250 | M49: Блокирован | N49: 41770
A50: 41553.762 | B50: 910486 | C50: 8528047 | D50: 41553.757 | E50: 41556.655 | F50: 79956 | G50: Непрофильный | H50: Тверь - МТС Коннект-4 (МАСС) (SCP) | I50: Тверь - МТС Коннект-4 (МАСС) (SCP) | J50: 30 | K50: 676.8 | L50: 706.8 | M50: Активен
A51: 41548.744 | B51: 916111 | C51: 8547459 | D51: 41548.739 | E51: 41552.475 | F51: 64628 | G51: Непрофильный | H51: Тверь - Супер МТС. Область (МАСС) (SCP) | I51: Тверь - Супер МТС. Область (МАСС) (SCP) | J51: 30 | K51: 0 | L51: 30 | M51: Активен
A52: 41557.631 | B52: 916496 | C52: 8503724 | D52: 41557.625 | E52: 41560.844 | F52: 64626 | G52: Непрофильный | H52: Тверь - МТС Коннект-4 (МАСС) (SCP) | I52: Тверь - МТС Коннект-4 (МАСС) (SCP) | J52: 30 | K52: 432 | L52: 462 | M52: Блокирован | N52: 41919
A53: 41550.812 | B53: 985333 | C53: 8550504 | D53: 41550.817 | E53: 41556.54 | F53: 64616 | G53: Непрофильный | H53: Тверь - Smart (МАСС) (SCP) | I53: Тверь - Smart (МАСС) (SCP) | J53: 30 | K53: 500 | L53: 530 | M53: Блокирован | N53: 41752
A54: 41550.632 | B54: 985820 | C54: 8524868 | D54: 41550.627 | E54: 41550.684 | F54: 64626 | G54: Непрофильный | H54: Тверь - МТС Коннект-4 (МАСС) (SCP) | I54: Тверь - МТС Коннект-4 (МАСС) (SCP) | J54: 401 | K54: 824.5 | L54: 1225.5 | M54: Активен
A55: 41560.84 | B55: 910480 | C55: 8550143 | D55: 41560.835 | E55: 41560.843 | F55: 64626 | G55: Непрофильный | H55: Тверь - Супер МТС (МАСС) (SCP) | I55: Тверь - Супер МТС (МАСС) (SCP) | J55: 50 | K55: 0 | L55: 50 | M55: Блокирован | N55: 41732
A56: 41554.534 | B56: 916496 | C56: 8520383 | D56: 41554.529 | E56: 41560.808 | F56: 64626 | G56: Непрофильный | H56: Тверь - МТС Коннект-4 (МАСС) (SCP) | I56: Тверь - МТС Коннект-4 (МАСС) (SCP) | J56: 1749 | K56: 0 | L56: 1749 | M56: Блокирован | N56: 41776
A57: 41557.763 | B57: 910452 | C57: 8500121 | D57: 41557.758 | F57: 79956 | G57: Непрофильный | H57: Тверь - Smart (МАСС) (SCP) | I57: Тверь - Smart (МАСС) (SCP) | J57: 470 | K57: 200 | L57: 670 | M57: Блокирован | N57: 41747
A58: 41553.408 | B58: 915323 | C58: 8550432 | D58: 41553.402 | E58: 41555.97 | F58: 64626 | G58: Непрофильный | H58: Тверь - Супер МТС. Область (МАСС) (SCP) | I58: Тверь - Супер МТС. Область (МАСС) (SCP) | J58: 30 | K58: 0 | L58: 30 | M58: Блокирован | N58: 41650
A59: 41593.603 | B59: 916692 | C59: 8502914 | D59: 41593.597 | F59: 73902 | G59: Непрофильный | H59: Тверь - Супер МТС. Область (МАСС) (SCP) | I59: Тверь - Супер МТС. Область (МАСС) (SCP) | J59: 30 | K59: 100 | L59: 130 | M59: Блокирован | N59: 41949
A60: 41550.699 | B60: 910441 | C60: 8545571 | D60: 41550.693 | E60: 41556.659 | F60: 73902 | G60: Непрофильный | H60: Тверь - МТС Коннект-4 (МАСС) (SCP) | I60: Тверь - МТС Коннект-4 (МАСС) (SCP) | J60: 401 | K60: 0 | L60: 401 | M60: Активен
A61: 41558.594 | B61: 916180 | C61: 8503339 | D61: 41558.6 | F61: 64616 | G61: Непрофильный | H61: Тверь - МТС Коннект-4 (МАСС) (SCP) | I61: Тверь - МТС Коннект-4 (МАСС) (SCP) | J61: 30 | K61: 728.8 | L61: 758.8 | M61: Блокирован | N61: 41828
A62: 41562.762 | B62: 985351 | C62: 8563786 | D62: 41562.769 | F62: 73902 | G62: Непрофильный | H62: Тверь - Smart (МАСС) (SCP) | I62: Тверь - Smart (МАСС) (SCP) | J62: 470 | K62: 0 | L62: 470 | M62: Блокирован | N62: 41953
A63: 41548.48 | B63: 910481 | C63: 8500121 | D63: 41548.486 | E63: 41554.529 | F63: 79956 | G63: Непрофильный | H63: Тверь - Smart (МАСС) (SCP) | I63: Тверь - Smart (МАСС) (SCP) | J63: 470 | K63: 96.2 | L63: 566.2 | M63: Блокирован | N63: 41747
A64: 41593.669 | B64: 916510 | C64: 1698170 | D64: 41593.676 | F64: 73902 | G64: Непрофильный | H64: Тверь - Супер МТС (МАСС) (SCP) | I64: Тверь - Супер МТС (МАСС) (SCP) | J64: 1 | K64: 88 | L64: 89 | M64: Активен
A65: 41558.714 | B65: 910457 | C65: 8500121 | D65: 41558.721 | E65: 41560.557 | F65: 79956 | G65: Непрофильный | H65: Тверь - Smart (МАСС) (SCP) | I65: Тверь - Smart (МАСС) (SCP) | J65: 470 | K65: 0 | L65: 470 | M65: Блокирован | N65: 41747
A66: 41583.474 | B66: 915000 | C66: 1977491 | D66: 41583.481 | E66: 41591.434 | F66: 79956 | G66: Непрофильный | H66: Тверь - Супер МТС (МАСС) (SCP) | I66: Тверь - Супер МТС (МАСС) (SCP) | J66: 30 | K66: 0 | L66: 30 | M66: Блокирован | N66: 41906
A67: 41556.748 | B67: 916366 | C67: 8502571 | D67: 41556.74 | F67: 73902 | G67: Непрофильный | H67: Тверь - Твоя страна (МАСС) (SCP) | I67: Тверь - Твоя страна (МАСС) (SCP) | J67: 30 | K67: 0 | L67: 30 | M67: Блокирован | N67: 41776
A68: 41553.543 | B68: 910475 | C68: 8520666 | D68: 41553.536 | F68: 64616 | G68: Непрофильный | H68: Тверь - Smart mini (МАСС) (SCP) | I68: Тверь - Smart mini (МАСС) (SCP) | J68: 30 | K68: 285 | L68: 315 | M68: Блокирован | N68: 41662
A69: 41559.48 | B69: 916496 | C69: 1755646 | D69: 41559.488 | E69: 41560.847 | F69: 64626 | G69: Непрофильный | H69: Тверь - МТС Коннект-4 (МАСС) (SCP) | I69: Тверь - МТС Коннект-4 (МАСС) (SCP) | J69: 30 | K69: 96 | L69: 126 | M69: Блокирован | N69: 41839
A70: 41552.654 | B70: 910489 | C70: 8563770 | D70: 41552.661 | E70: 41559.424 | F70: 73902 | G70: Непрофильный | H70: Тверь - Smart (МАСС) (SCP) | I70: Тверь - Smart (МАСС) (SCP) | J70: 470 | K70: 0 | L70: 470 | M70: Блокирован | N70: 41860
A71: 41549.692 | B71: 916496 | C71: 8514428 | D71: 41549.685 | E71: 41560.808 | F71: 64626 | G71: Непрофильный | H71: Тверь - МТС Коннект-4 (МАСС) (SCP) | I71: Тверь - МТС Коннект-4 (МАСС) (SCP) | J71: 949 | K71: 0 | L71: 949 | M71: Блокирован | N71: 41845
A72: 41555.699 | B72: 915321 | C72: 8500122 | D72: 41555.706 | E72: 41555.709 | F72: 79956 | G72: Непрофильный | H72: Тверь - Smart (МАСС) (SCP) | I72: Тверь - Smart (МАСС) (SCP) | J72: 470 | K72: 0 | L72: 470 | M72: Блокирован | N72: 41952
A73: 41550.521 | B73: 916322 | C73: 8503735 | D73: 41550.513 | F73: 79956 | G73: Непрофильный | H73: Тверь - Smart mini (МАСС) (SCP) | I73: Тверь - Smart mini (МАСС) (SCP) | J73: 220 | K73: 180.04 | L73: 400.04 | M73: Блокирован | N73: 41800
A74: 41556.569 | B74: 910457 | C74: 8542775 | D74: 41556.561 | E74: 41560.815 | F74: 79956 | G74: Непрофильный | H74: Тверь - МТС Коннект-4 (МАСС) (SCP) | I74: Тверь - МТС Коннект-4 (МАСС) (SCP) | J74: 401 | K74: 0 | L74: 401 | M74: Активен
A75: 41549.653 | B75: 915321 | C75: 8500122 | D75: 41549.644 | E75: 41549.682 | F75: 79956 | G75: Непрофильный | H75: Тверь - Smart (МАСС) (SCP) | I75: Тверь - Smart (МАСС) (SCP) | J75: 470 | K75: 0 | L75: 470 | M75: Блокирован | N75: 41952
A76: 41559.826 | B76: 916580 | C76: 1753523 | D76: 41559.835 | F76: 64628 | G76: Непрофильный | H76: Тверь - RED Energy (МАСС) (SCP) | I76: Тверь - RED Energy (МАСС) (SCP) | J76: 220 | K76: 320.05 | L76: 540.05 | M76: Активен
A77: 41548.493 | B77: 910466 | C77: 8500716 | D77: 41548.502 | E77: 41558.002 | F77: 79956 | G77: Непрофильный | H77: Тверь - Smart mini (МАСС) (SCP) | I77: Тверь - Smart mini (МАСС) (SCP) | J77: 30 | K77: 200 | L77: 230 | M77: Блокирован | N77: 41650
A78: 41561.555 | B78: 985351 | C78: 1996772 | D78: 41561.546 | E78: 41561.554 | F78: 64626 | G78: Непрофильный | H78: Тверь - Супер МТС. Область (МАСС) (SCP) | I78: Тверь - Супер МТС. Область (МАСС) (SCP) | J78: 50 | K78: 250 | L78: 300 | M78: Блокирован | N78: 41725
A79: 41550.575 | B79: 985351 | C79: 8550145 | D79: 41550.566 | E79: 41550.571 | F79: 64626 | G79: Непрофильный | H79: Тверь - Супер МТС (МАСС) (SCP) | I79: Тверь - Супер МТС (МАСС) (SCP) | J79: 50 | K79: 100 | L79: 150 | M79: Блокирован | N79: 41770
A80: 41550.571 | B80: 916154 | C80: 8563781 | D80: 41550.58 | E80: 41560.726 | F80: 73902 | G80: Непрофильный | H80: Тверь - Smart (МАСС) (SCP) | I80: Тверь - Smart (МАСС) (SCP) | J80: 470 | K80: 495.1 | L80: 965.1 | M80: Блокирован | N80: 41671
A81: 41562.613 | B81: 985488 | C81: 8500886 | D81: 41562.603 | F81: 79956 | G81: Непрофильный | H81: Тверь - Smart mini (МАСС) (SCP) | I81: Тверь - Smart mini (МАСС) (SCP) | J81: 30 | K81: 235 | L81: 265 | M81: Блокирован | N81: 41808
A82: 41560.818 | B82: 910467 | C82: 8500836 | D82: 41560.809 | F82: 79956 | G82: Непрофильный | H82: Тверь - Smart mini (МАСС) (SCP) | I82: Тверь - Smart mini (МАСС) (SCP) | J82: 30 | K82: 200 | L82: 230 | M82: Блокирован | N82: 41642
A83: 41554.733 | B83: 985351 | C83: 8539478 | D83: 41554.723 | F83: 64616 | G83: Непрофильный | H83: Тверь - Smart mini (МАСС) (SCP) | I83: Тверь - Smart mini (МАСС) (SCP) | J83: 30 | K83: 422.51 | L83: 452.51 | M83: Активен
A84: 41550.631 | B84: 916154 | C84: 8543205 | D84: 41550.64 | E84: 41560.729 | F84: 73902 | G84: Непрофильный | H84: Тверь - Smart mini (МАСС) (SCP) | I84: Тверь - Smart mini (МАСС) (SCP) | J84: 220 | K84: 0 | L84: 220 | M84: Активен
A85: 41560.761 | B85: 910489 | C85: 8503680 | D85: 41560.751 | E85: 41560.845 | F85: 79956 | G85: Непрофильный | H85: Тверь - Smart mini (МАСС) (SCP) | I85: Тверь - Smart mini (МАСС) (SCP) | J85: 220 | K85: 0 | L85: 220 | M85: Блокирован | N85: 41949
A86: 41558.715 | B86: 910457 | C86: 8500121 | D86: 41558.705 | E86: 41561.695 | F86: 79956 | G86: Непрофильный | H86: Тверь - Smart (МАСС) (SCP) | I86: Тверь - Smart (МАСС) (SCP) | J86: 470 | K86: 95 | L86: 565 | M86: Блокирован | N86: 41747
A87: 41561.935 | B87: 910481 | C87: 8562212 | D87: 41561.924 | F87: 79956 | G87: Непрофильный | H87: Тверь - Smart mini (МАСС) (SCP) | I87: Тверь - Smart mini (МАСС) (SCP) | J87: 270 | K87: 0 | L87: 270 | M87: Блокирован | N87: 41822
A88: 41559.832 | B88: 910488 | C88: 1750460 | D88: 41559.821 | E88: 41560.404 | F88: 64626 | G88: Непрофильный | H88: Тверь - Smart mini (МАСС) (SCP) | I88: Тверь - Smart mini (МАСС) (SCP) | J88: 220 | K88: 0 | L88: 220 | M88: Активен
A89: 41561.935 | B89: 910452 | C89: 8562212 | D89: 41561.925 | F89: 79956 | G89: Непрофильный | H89: Тверь - Smart mini (МАСС) (SCP) | I89: Тверь - Smart mini (МАСС) (SCP) | J89: 270 | K89: 0 | L89: 270 | M89: Блокирован | N89: 41822
A90: 41557.872 | B90: 910488 | C90: 8500084 | D90: 41557.862 | E90: 41557.875 | F90: 64626 | G90: Непрофильный | H90: Тверь - Smart (МАСС) (SCP) | I90: Тверь - Smart (МАСС) (SCP) | J90: 470 | K90: 0 | L90: 470 | M90: Блокирован | N90: 41655
A91: 41561.602 | B91: 916496 | C91: 8503076 | D91: 41561.613 | F91: 64626 | G91: Непрофильный | H91: Тверь - МТС Коннект-4 (МАСС) (SCP) | I91: Тверь - МТС Коннект-4 (МАСС) (SCP) | J91: 30 | K91: 100 | L91: 130 | M91: Блокирован | N91: 41949
A92: 41552.774 | B92: 910436 | C92: 8550510 | D92: 41552.763 | E92: 41553.931 | F92: 73902 | G92: Непрофильный | H92: Тверь - Smart mini (МАСС) (SCP) | I92: Тверь - Smart mini (МАСС) (SCP) | J92: 220 | K92: 0 | L92: 220 | M92: Блокирован | N92: 41944
A93: 41559.634 | B93: 910486 | C93: 8562398 | D93: 41559.623 | E93: 41561.695 | F93: 79956 | G93: Непрофильный | H93: Тверь - МТС Коннект-4 (МАСС) (SCP) | I93: Тверь - МТС Коннект-4 (МАСС) (SCP) | J93: 949 | K93: 0 | L93: 949 | M93: Блокирован | N93: 41786
A94: 41555.553 | B94: 916692 | C94: 8550792 | D94: 41555.542 | F94: 73902 | G94: Непрофильный | H94: Тверь - Супер МТС (МАСС) (SCP) | I94: Тверь - Супер МТС (МАСС) (SCP) | J94: 30 | K94: 0 | L94: 30 | M94: Блокирован | N94: 41692
A95: 41593.63 | B95: 910481 | C95: 1999885 | D95: 41593.619 | F95: 79956 | G95: Непрофильный | H95: Тверь - Smart mini (МАСС) (SCP) | I95: Тверь - Smart mini (МАСС) (SCP) | J95: 220 | K95: 300 | L95: 520 | M95: Блокирован | N95: 41673
A96: 41560.411 | B96: 916366 | C96: 8533012 | D96: 41560.423 | F96: 73902 | G96: Непрофильный | H96: Тверь - Smart mini (МАСС) (SCP) | I96: Тверь - Smart mini (МАСС) (SCP) | J96: 30 | K96: 203.7 | L96: 233.7 | M96: Активен
A97: 41559.679 | B97: 916496 | C97: 8520383 | D97: 41559.667 | E97: 41560.808 | F97: 64626 | G97: Непрофильный | H97: Тверь - МТС Коннект-4 (МАСС) (SCP) | I97: Тверь - МТС Коннект-4 (МАСС) (SCP) | J97: 1749 | K97: 0 | L97: 1749 | M97: Блокирован | N97: 41776
A98: 41561.454 | B98: 915339 | C98: 1755151 | D98: 41561.442 | F98: 64626 | G98: Непрофильный | H98: Тверь - Супер МТС (МАСС) (SCP) | I98: Тверь - Супер МТС (МАСС) (SCP) | J98: 30 | K98: 0 | L98: 30 | M98: Активен
A99: 41549.673 | B99: 915317 | C99: 8500211 | D99: 41549.661 | E99: 41555.697 | F99: 73902 | G99: Непрофильный | H99: Тверь - Супер МТС (МАСС) (SCP) | I99: Тверь - Супер МТС (МАСС) (SCP) | J99: 30 | K99: 0 | L99: 30 | M99: Блокирован | N99: 41928
A100: 41549.755 | B100: 915276 | C100: 8543906 | D100: 41549.767 | E100: 41549.778 | F100: 79956 | G100: Непрофильный | H100: Тверь - Супер МТС (МАСС) (SCP) | I100: Тверь - Супер МТС (МАСС) (SCP) | J100: 30 | K100: 0 | L100: 30 | M100: Активен
...

Sheet выгрузка -- копия (2)
A1: Дата отправки смс | B1: Номер отправителя | C1: Номер комплекта | D1: Дата активации | E1: Месяц активации | F1: Дата регистрации | G1: ЛС дилера | H1: Канал продажи | I1: ТП комплекта текущий.1 | J1: ТП комплекта текущий.2 | K1: Первоначальный баланс проданного комплекта | L1: Размер дополнительного платежа | M1: Сумма дополнительного платежа и стартового баланса | N1: статус комплекта | O1: Дата блокировки | P1: ТП комплекта текущий без города (столбец создан с помощью Power Query) | Q1: Критерий 1 -- от 1 до 14 октября | R1: Критерий 3 -- дата регистрации | S1: Критерий 4 -- дилеры-участники | T1: Критерий 5 -- ТП из списка | U1: Критерий 6 -- бонус в канале | V1: 8 --Вознаграждение | W1: 10 --Группа тарифа | X1: 13 --Месяц блокировки от месяца подключения | Y1: Блокировка
A2: 41593.654 | B2: 915323 | C2: 1751529 | D2: 41593.716 | E2: =IF(выгрузка__22[[#This Row],[Дата активации]]<>"",MONTH(выгрузка__22[[#This Row],[Дата активации]]),0) -> 11 | G2: 64628 | H2: Непрофильный | I2: Тверь | J2: - Супер МТС (МАСС) (SCP) | K2: 30 | L2: 0 | M2: 30 | N2: Активен | P2: Супер МТС (МАСС) (SCP) | Q2: =IF(AND(DAY(выгрузка__22[[#This Row],[Дата отправки смс]])>=1,DAY(выгрузка__22[[#This Row],[Дата отправки смс]])<=14,MONTH(выгрузка__22[[#This Row],[Дата отправки смс]])=10),1,0) -> 0 | R2: =IF(выгрузка__22[[#This Row],[Дата регистрации]]="",0,1) -> 0 | S2: =IF(ISNA(VLOOKUP(выгрузка__22[[#This Row],[ЛС дилера]],'дилеры участники'!A:A,1,0)),0,1) -> 0 | T2: =IF(ISNA(VLOOKUP(выгрузка__22[[#This Row],[ТП комплекта текущий без города (столбец создан с помощью Power Query)]],Таблица3[Название ТП комплекта],1,0)),0,1) -> 1 | U2: =IF(ISNA(IF(выгрузка__22[[#This Row],[Канал продажи]]="Непрофильный",VLOOKUP(выгрузка__22[[#This Row],[ТП комплекта текущий без города (столбец создан с помощью Power Query)]],Таблица3[[Название ТП комплекта]:[Непрофильный]],3,0),VLOOKUP(выгрузка__22[[#This Row],[ТП комплекта текущий без города (столбец создан с помощью Power Query)]],Таблица3[[Название ТП комплекта]:[Непрофильный]],2,0)))=FALSE,1,0) -> 1 | V2: =IF(T2=1,IF(выгрузка__22[[#This Row],[Сумма дополнительного платежа и стартового баланса]]>300,VLOOKUP(выгрузка__22[[#This Row],[ТП комплекта текущий без города (столбец создан с помощью Power Query)]],Таблица3[],6,0),IF(выгрузка__22[[#This Row],[Сумма дополнительного платежа и стартового баланса]]>200,VLOOKUP(выгрузка__22[[#This Row],[ТП комплекта текущий без города (столбец создан с помощью Power Query)]],Таблица3[],5,0),IF(выгрузка__22[[#This Row],[Сумма дополнительного платежа и стартового баланса]]>100,VLOOKUP(выгрузка__22[[#This Row],[ТП комплекта текущий без города (столбец создан с помощью Power Query)]],Таблица3[],4,0),0))),0) -> 0 | W2: Супер МТС | X2: =IF(выгрузка__22[[#This Row],[Дата активации]]<>0,IF(выгрузка__22[[#This Row],[Дата блокировки]]<>"",CEILING((выгрузка__22[[#This Row],[Дата блокировки]]-выгрузка__22[[#This Row],[Дата активации]])/30,1),0),0) -> 0 | Y2: =IF(выгрузка__22[[#This Row],[Дата блокировки]]<>"",1,0) -> 0
A3: 41593.714 | B3: 916207 | C3: 1751479 | D3: 41593.7 | E3: =IF(выгрузка__22[[#This Row],[Дата активации]]<>"",MONTH(выгрузка__22[[#This Row],[Дата активации]]),0) -> 11 | G3: 64626 | H3: Непрофильный | I3: Тверь | J3: - Супер МТС (МАСС) (SCP) | K3: 30 | L3: 0 | M3: 30 | N3: Активен | P3: Супер МТС (МАСС) (SCP) | Q3: =IF(AND(DAY(выгрузка__22[[#This Row],[Дата отправки смс]])>=1,DAY(выгрузка__22[[#This Row],[Дата отправки смс]])<=14,MONTH(выгрузка__22[[#This Row],[Дата отправки смс]])=10),1,0) -> 0 | R3: =IF(выгрузка__22[[#This Row],[Дата регистрации]]="",0,1) -> 0 | S3: =IF(ISNA(VLOOKUP(выгрузка__22[[#This Row],[ЛС дилера]],'дилеры участники'!A:A,1,0)),0,1) -> 0 | T3: =IF(ISNA(VLOOKUP(выгрузка__22[[#This Row],[ТП комплекта текущий без города (столбец создан с помощью Power Query)]],Таблица3[Название ТП комплекта],1,0)),0,1) -> 1 | U3: =IF(ISNA(IF(выгрузка__22[[#This Row],[Канал продажи]]="Непрофильный",VLOOKUP(выгрузка__22[[#This Row],[ТП комплекта текущий без города (столбец создан с помощью Power Query)]],Таблица3[[Название ТП комплекта]:[Непрофильный]],3,0),VLOOKUP(выгрузка__22[[#This Row],[ТП комплекта текущий без города (столбец создан с помощью Power Query)]],Таблица3[[Название ТП комплекта]:[Непрофильный]],2,0)))=FALSE,1,0) -> 1 | V3: =IF(T3=1,IF(выгрузка__22[[#This Row],[Сумма дополнительного платежа и стартового баланса]]>300,VLOOKUP(выгрузка__22[[#This Row],[ТП комплекта текущий без города (столбец создан с помощью Power Query)]],Таблица3[],6,0),IF(выгрузка__22[[#This Row],[Сумма дополнительного платежа и стартового баланса]]>200,VLOOKUP(выгрузка__22[[#This Row],[ТП комплекта текущий без города (столбец создан с помощью Power Query)]],Таблица3[],5,0),IF(выгрузка__22[[#This Row],[Сумма дополнительного платежа и стартового баланса]]>100,VLOOKUP(выгрузка__22[[#This Row],[ТП комплекта текущий без города (столбец создан с помощью Power Query)]],Таблица3[],4,0),0))),0) -> 0 | W3: Супер МТС | X3: =IF(выгрузка__22[[#This Row],[Дата активации]]<>0,IF(выгрузка__22[[#This Row],[Дата блокировки]]<>"",CEILING((выгрузка__22[[#This Row],[Дата блокировки]]-выгрузка__22[[#This Row],[Дата активации]])/30,1),0),0) -> 0 | Y3: =IF(выгрузка__22[[#This Row],[Дата блокировки]]<>"",1,0) -> 0
A4: 41593.669 | B4: 916510 | C4: 1698170 | D4: 41593.676 | E4: =IF(выгрузка__22[[#This Row],[Дата активации]]<>"",MONTH(выгрузка__22[[#This Row],[Дата активации]]),0) -> 11 | G4: 73902 | H4: Непрофильный | I4: Тверь | J4: - Супер МТС (МАСС) (SCP) | K4: 1 | L4: 88 | M4: 89 | N4: Активен | P4: Супер МТС (МАСС) (SCP) | Q4: =IF(AND(DAY(выгрузка__22[[#This Row],[Дата отправки смс]])>=1,DAY(выгрузка__22[[#This Row],[Дата отправки смс]])<=14,MONTH(выгрузка__22[[#This Row],[Дата отправки смс]])=10),1,0) -> 0 | R4: =IF(выгрузка__22[[#This Row],[Дата регистрации]]="",0,1) -> 0 | S4: =IF(ISNA(VLOOKUP(выгрузка__22[[#This Row],[ЛС дилера]],'дилеры участники'!A:A,1,0)),0,1) -> 0 | T4: =IF(ISNA(VLOOKUP(выгрузка__22[[#This Row],[ТП комплекта текущий без города (столбец создан с помощью Power Query)]],Таблица3[Название ТП комплекта],1,0)),0,1) -> 1 | U4: =IF(ISNA(IF(выгрузка__22[[#This Row],[Канал продажи]]="Непрофильный",VLOOKUP(выгрузка__22[[#This Row],[ТП комплекта текущий без города (столбец создан с помощью Power Query)]],Таблица3[[Название ТП комплекта]:[Непрофильный]],3,0),VLOOKUP(выгрузка__22[[#This Row],[ТП комплекта текущий без города (столбец создан с помощью Power Query)]],Таблица3[[Название ТП комплекта]:[Непрофильный]],2,0)))=FALSE,1,0) -> 1 | V4: =IF(T4=1,IF(выгрузка__22[[#This Row],[Сумма дополнительного платежа и стартового баланса]]>300,VLOOKUP(выгрузка__22[[#This Row],[ТП комплекта текущий без города (столбец создан с помощью Power Query)]],Таблица3[],6,0),IF(выгрузка__22[[#This Row],[Сумма дополнительного платежа и стартового баланса]]>200,VLOOKUP(выгрузка__22[[#This Row],[ТП комплекта текущий без города (столбец создан с помощью Power Query)]],Таблица3[],5,0),IF(выгрузка__22[[#This Row],[Сумма дополнительного платежа и стартового баланса]]>100,VLOOKUP(выгрузка__22[[#This Row],[ТП комплекта текущий без города (столбец создан с помощью Power Query)]],Таблица3[],4,0),0))),0) -> 0 | W4: Супер МТС | X4: =IF(выгрузка__22[[#This Row],[Дата активации]]<>0,IF(выгрузка__22[[#This Row],[Дата блокировки]]<>"",CEILING((выгрузка__22[[#This Row],[Дата блокировки]]-выгрузка__22[[#This Row],[Дата активации]])/30,1),0),0) -> 0 | Y4: =IF(выгрузка__22[[#This Row],[Дата блокировки]]<>"",1,0) -> 0
A5: 41593.534 | B5: 916726 | C5: 8545217 | D5: 41593.586 | E5: =IF(выгрузка__22[[#This Row],[Дата активации]]<>"",MONTH(выгрузка__22[[#This Row],[Дата активации]]),0) -> 11 | G5: 64626 | H5: Непрофильный | I5: Тверь | J5: - Smart mini (МАСС) (SCP) | K5: 30 | L5: 190 | M5: 220 | N5: Активен | P5: Smart mini (МАСС) (SCP) | Q5: =IF(AND(DAY(выгрузка__22[[#This Row],[Дата отправки смс]])>=1,DAY(выгрузка__22[[#This Row],[Дата отправки смс]])<=14,MONTH(выгрузка__22[[#This Row],[Дата отправки смс]])=10),1,0) -> 0 | R5: =IF(выгрузка__22[[#This Row],[Дата регистрации]]="",0,1) -> 0 | S5: =IF(ISNA(VLOOKUP(выгрузка__22[[#This Row],[ЛС дилера]],'дилеры участники'!A:A,1,0)),0,1) -> 0 | T5: =IF(ISNA(VLOOKUP(выгрузка__22[[#This Row],[ТП комплекта текущий без города (столбец создан с помощью Power Query)]],Таблица3[Название ТП комплекта],1,0)),0,1) -> 1 | U5: =IF(ISNA(IF(выгрузка__22[[#This Row],[Канал продажи]]="Непрофильный",VLOOKUP(выгрузка__22[[#This Row],[ТП комплекта текущий без города (столбец создан с помощью Power Query)]],Таблица3[[Название ТП комплекта]:[Непрофильный]],3,0),VLOOKUP(выгрузка__22[[#This Row],[ТП комплекта текущий без города (столбец создан с помощью Power Query)]],Таблица3[[Название ТП комплекта]:[Непрофильный]],2,0)))=FALSE,1,0) -> 1 | V5: =IF(T5=1,IF(выгрузка__22[[#This Row],[Сумма дополнительного платежа и стартового баланса]]>300,VLOOKUP(выгрузка__22[[#This Row],[ТП комплекта текущий без города (столбец создан с помощью Power Query)]],Таблица3[],6,0),IF(выгрузка__22[[#This Row],[Сумма дополнительного платежа и стартового баланса]]>200,VLOOKUP(выгрузка__22[[#This Row],[ТП комплекта текущий без города (столбец создан с помощью Power Query)]],Таблица3[],5,0),IF(выгрузка__22[[#This Row],[Сумма дополнительного платежа и стартового баланса]]>100,VLOOKUP(выгрузка__22[[#This Row],[ТП комплекта текущий без города (столбец создан с помощью Power Query)]],Таблица3[],4,0),0))),0) -> 110 | W5: Smart mini | X5: =IF(выгрузка__22[[#This Row],[Дата активации]]<>0,IF(выгрузка__22[[#This Row],[Дата блокировки]]<>"",CEILING((выгрузка__22[[#This Row],[Дата блокировки]]-выгрузка__22[[#This Row],[Дата активации]])/30,1),0),0) -> 0 | Y5: =IF(выгрузка__22[[#This Row],[Дата блокировки]]<>"",1,0) -> 0
A6: 41593.654 | B6: 910488 | C6: 1750456 | D6: 41592.85 | E6: =IF(выгрузка__22[[#This Row],[Дата активации]]<>"",MONTH(выгрузка__22[[#This Row],[Дата активации]]),0) -> 11 | F6: 41592.837 | G6: 64626 | H6: Непрофильный | I6: Тверь | J6: - Smart mini (МАСС) (SCP) | K6: 220 | L6: 0 | M6: 220 | N6: Активен | P6: Smart mini (МАСС) (SCP) | Q6: =IF(AND(DAY(выгрузка__22[[#This Row],[Дата отправки смс]])>=1,DAY(выгрузка__22[[#This Row],[Дата отправки смс]])<=14,MONTH(выгрузка__22[[#This Row],[Дата отправки смс]])=10),1,0) -> 0 | R6: =IF(выгрузка__22[[#This Row],[Дата регистрации]]="",0,1) -> 1 | S6: =IF(ISNA(VLOOKUP(выгрузка__22[[#This Row],[ЛС дилера]],'дилеры участники'!A:A,1,0)),0,1) -> 0 | T6: =IF(ISNA(VLOOKUP(выгрузка__22[[#This Row],[ТП комплекта текущий без города (столбец создан с помощью Power Query)]],Таблица3[Название ТП комплекта],1,0)),0,1) -> 1 | U6: =IF(ISNA(IF(выгрузка__22[[#This Row],[Канал продажи]]="Непрофильный",VLOOKUP(выгрузка__22[[#This Row],[ТП комплекта текущий без города (столбец создан с помощью Power Query)]],Таблица3[[Название ТП комплекта]:[Непрофильный]],3,0),VLOOKUP(выгрузка__22[[#This Row],[ТП комплекта текущий без города (столбец создан с помощью Power Query)]],Таблица3[[Название ТП комплекта]:[Непрофильный]],2,0)))=FALSE,1,0) -> 1 | V6: =IF(T6=1,IF(выгрузка__22[[#This Row],[Сумма дополнительного платежа и стартового баланса]]>300,VLOOKUP(выгрузка__22[[#This Row],[ТП комплекта текущий без города (столбец создан с помощью Power Query)]],Таблица3[],6,0),IF(выгрузка__22[[#This Row],[Сумма дополнительного платежа и стартового баланса]]>200,VLOOKUP(выгрузка__22[[#This Row],[ТП комплекта текущий без города (столбец создан с помощью Power Query)]],Таблица3[],5,0),IF(выгрузка__22[[#This Row],[Сумма дополнительного платежа и стартового баланса]]>100,VLOOKUP(выгрузка__22[[#This Row],[ТП комплекта текущий без города (столбец создан с помощью Power Query)]],Таблица3[],4,0),0))),0) -> 110 | W6: Smart mini | X6: =IF(выгрузка__22[[#This Row],[Дата активации]]<>0,IF(выгрузка__22[[#This Row],[Дата блокировки]]<>"",CEILING((выгрузка__22[[#This Row],[Дата блокировки]]-выгрузка__22[[#This Row],[Дата активации]])/30,1),0),0) -> 0 | Y6: =IF(выгрузка__22[[#This Row],[Дата блокировки]]<>"",1,0) -> 0
A7: 41593.497 | B7: 910489 | C7: 8525534 | D7: 41591.638 | E7: =IF(выгрузка__22[[#This Row],[Дата активации]]<>"",MONTH(выгрузка__22[[#This Row],[Дата активации]]),0) -> 11 | G7: 64616 | H7: Непрофильный | I7: Тверь | J7: - Твоя страна (МАСС) (SCP) | K7: 30 | L7: 0 | M7: 30 | N7: Активен | P7: Твоя страна (МАСС) (SCP) | Q7: =IF(AND(DAY(выгрузка__22[[#This Row],[Дата отправки смс]])>=1,DAY(выгрузка__22[[#This Row],[Дата отправки смс]])<=14,MONTH(выгрузка__22[[#This Row],[Дата отправки смс]])=10),1,0) -> 0 | R7: =IF(выгрузка__22[[#This Row],[Дата регистрации]]="",0,1) -> 0 | S7: =IF(ISNA(VLOOKUP(выгрузка__22[[#This Row],[ЛС дилера]],'дилеры участники'!A:A,1,0)),0,1) -> 1 | T7: =IF(ISNA(VLOOKUP(выгрузка__22[[#This Row],[ТП комплекта текущий без города (столбец создан с помощью Power Query)]],Таблица3[Название ТП комплекта],1,0)),0,1) -> 0 | U7: =IF(ISNA(IF(выгрузка__22[[#This Row],[Канал продажи]]="Непрофильный",VLOOKUP(выгрузка__22[[#This Row],[ТП комплекта текущий без города (столбец создан с помощью Power Query)]],Таблица3[[Название ТП комплекта]:[Непрофильный]],3,0),VLOOKUP(выгрузка__22[[#This Row],[ТП комплекта текущий без города (столбец создан с помощью Power Query)]],Таблица3[[Название ТП комплекта]:[Непрофильный]],2,0)))=FALSE,1,0) -> 0 | V7: =IF(T7=1,IF(выгрузка__22[[#This Row],[Сумма дополнительного платежа и стартового баланса]]>300,VLOOKUP(выгрузка__22[[#This Row],[ТП комплекта текущий без города (столбец создан с помощью Power Query)]],Таблица3[],6,0),IF(выгрузка__22[[#This Row],[Сумма дополнительного платежа и стартового баланса]]>200,VLOOKUP(выгрузка__22[[#This Row],[ТП комплекта текущий без города (столбец создан с помощью Power Query)]],Таблица3[],5,0),IF(выгрузка__22[[#This Row],[Сумма дополнительного платежа и стартового баланса]]>100,VLOOKUP(выгрузка__22[[#This Row],[ТП комплекта текущий без города (столбец создан с помощью Power Query)]],Таблица3[],4,0),0))),0) -> 0 | W7: Твоя страна | X7: =IF(выгрузка__22[[#This Row],[Дата активации]]<>0,IF(выгрузка__22[[#This Row],[Дата блокировки]]<>"",CEILING((выгрузка__22[[#This Row],[Дата блокировки]]-выгрузка__22[[#This Row],[Дата активации]])/30,1),0),0) -> 0 | Y7: =IF(выгрузка__22[[#This Row],[Дата блокировки]]<>"",1,0) -> 0
A8: 41593.939 | B8: 910470 | C8: 8544488 | D8: 41590.755 | E8: =IF(выгрузка__22[[#This Row],[Дата активации]]<>"",MONTH(выгрузка__22[[#This Row],[Дата активации]]),0) -> 11 | G8: 64628 | H8: Непрофильный | I8: Тверь | J8: - Smart mini (МАСС) (SCP) | K8: 30 | L8: 200 | M8: 230 | N8: Активен | P8: Smart mini (МАСС) (SCP) | Q8: =IF(AND(DAY(выгрузка__22[[#This Row],[Дата отправки смс]])>=1,DAY(выгрузка__22[[#This Row],[Дата отправки смс]])<=14,MONTH(выгрузка__22[[#This Row],[Дата отправки смс]])=10),1,0) -> 0 | R8: =IF(выгрузка__22[[#This Row],[Дата регистрации]]="",0,1) -> 0 | S8: =IF(ISNA(VLOOKUP(выгрузка__22[[#This Row],[ЛС дилера]],'дилеры участники'!A:A,1,0)),0,1) -> 0 | T8: =IF(ISNA(VLOOKUP(выгрузка__22[[#This Row],[ТП комплекта текущий без города (столбец создан с помощью Power Query)]],Таблица3[Название ТП комплекта],1,0)),0,1) -> 1 | U8: =IF(ISNA(IF(выгрузка__22[[#This Row],[Канал продажи]]="Непрофильный",VLOOKUP(выгрузка__22[[#This Row],[ТП комплекта текущий без города (столбец создан с помощью Power Query)]],Таблица3[[Название ТП комплекта]:[Непрофильный]],3,0),VLOOKUP(выгрузка__22[[#This Row],[ТП комплекта текущий без города (столбец создан с помощью Power Query)]],Таблица3[[Название ТП комплекта]:[Непрофильный]],2,0)))=FALSE,1,0) -> 1 | V8: =IF(T8=1,IF(выгрузка__22[[#This Row],[Сумма дополнительного платежа и стартового баланса]]>300,VLOOKUP(выгрузка__22[[#This Row],[ТП комплекта текущий без города (столбец создан с помощью Power Query)]],Таблица3[],6,0),IF(выгрузка__22[[#This Row],[Сумма дополнительного платежа и стартового баланса]]>200,VLOOKUP(выгрузка__22[[#This Row],[ТП комплекта текущий без города (столбец создан с помощью Power Query)]],Таблица3[],5,0),IF(выгрузка__22[[#This Row],[Сумма дополнительного платежа и стартового баланса]]>100,VLOOKUP(выгрузка__22[[#This Row],[ТП комплекта текущий без города (столбец создан с помощью Power Query)]],Таблица3[],4,0),0))),0) -> 110 | W8: Smart mini | X8: =IF(выгрузка__22[[#This Row],[Дата активации]]<>0,IF(выгрузка__22[[#This Row],[Дата блокировки]]<>"",CEILING((выгрузка__22[[#This Row],[Дата блокировки]]-выгрузка__22[[#This Row],[Дата активации]])/30,1),0),0) -> 0 | Y8: =IF(выгрузка__22[[#This Row],[Дата блокировки]]<>"",1,0) -> 0
A9: 41593.927 | B9: 916531 | C9: 8544557 | D9: 41590.713 | E9: =IF(выгрузка__22[[#This Row],[Дата активации]]<>"",MONTH(выгрузка__22[[#This Row],[Дата активации]]),0) -> 11 | G9: 64628 | H9: Непрофильный | I9: Тверь | J9: - Smart mini (МАСС) (SCP) | K9: 30 | L9: 200 | M9: 230 | N9: Активен | P9: Smart mini (МАСС) (SCP) | Q9: =IF(AND(DAY(выгрузка__22[[#This Row],[Дата отправки смс]])>=1,DAY(выгрузка__22[[#This Row],[Дата отправки смс]])<=14,MONTH(выгрузка__22[[#This Row],[Дата отправки смс]])=10),1,0) -> 0 | R9: =IF(выгрузка__22[[#This Row],[Дата регистрации]]="",0,1) -> 0 | S9: =IF(ISNA(VLOOKUP(выгрузка__22[[#This Row],[ЛС дилера]],'дилеры участники'!A:A,1,0)),0,1) -> 0 | T9: =IF(ISNA(VLOOKUP(выгрузка__22[[#This Row],[ТП комплекта текущий без города (столбец создан с помощью Power Query)]],Таблица3[Название ТП комплекта],1,0)),0,1) -> 1 | U9: =IF(ISNA(IF(выгрузка__22[[#This Row],[Канал продажи]]="Непрофильный",VLOOKUP(выгрузка__22[[#This Row],[ТП комплекта текущий без города (столбец создан с помощью Power Query)]],Таблица3[[Название ТП комплекта]:[Непрофильный]],3,0),VLOOKUP(выгрузка__22[[#This Row],[ТП комплекта текущий без города (столбец создан с помощью Power Query)]],Таблица3[[Название ТП комплекта]:[Непрофильный]],2,0)))=FALSE,1,0) -> 1 | V9: =IF(T9=1,IF(выгрузка__22[[#This Row],[Сумма дополнительного платежа и стартового баланса]]>300,VLOOKUP(выгрузка__22[[#This Row],[ТП комплекта текущий без города (столбец создан с помощью Power Query)]],Таблица3[],6,0),IF(выгрузка__22[[#This Row],[Сумма дополнительного платежа и стартового баланса]]>200,VLOOKUP(выгрузка__22[[#This Row],[ТП комплекта текущий без города (столбец создан с помощью Power Query)]],Таблица3[],5,0),IF(выгрузка__22[[#This Row],[Сумма дополнительного платежа и стартового баланса]]>100,VLOOKUP(выгрузка__22[[#This Row],[ТП комплекта текущий без города (столбец создан с помощью Power Query)]],Таблица3[],4,0),0))),0) -> 110 | W9: Smart mini | X9: =IF(выгрузка__22[[#This Row],[Дата активации]]<>0,IF(выгрузка__22[[#This Row],[Дата блокировки]]<>"",CEILING((выгрузка__22[[#This Row],[Дата блокировки]]-выгрузка__22[[#This Row],[Дата активации]])/30,1),0),0) -> 0 | Y9: =IF(выгрузка__22[[#This Row],[Дата блокировки]]<>"",1,0) -> 0
A10: 41593.591 | B10: 916512 | C10: 1698576 | D10: 41589.987 | E10: =IF(выгрузка__22[[#This Row],[Дата активации]]<>"",MONTH(выгрузка__22[[#This Row],[Дата активации]]),0) -> 11 | F10: 41591.94 | G10: 64626 | H10: Непрофильный | I10: Тверь | J10: - Супер МТС. Область (МАСС) (SCP) | K10: 30 | L10: 0 | M10: 30 | N10: Активен | P10: Супер МТС. Область (МАСС) (SCP) | Q10: =IF(AND(DAY(выгрузка__22[[#This Row],[Дата отправки смс]])>=1,DAY(выгрузка__22[[#This Row],[Дата отправки смс]])<=14,MONTH(выгрузка__22[[#This Row],[Дата отправки смс]])=10),1,0) -> 0 | R10: =IF(выгрузка__22[[#This Row],[Дата регистрации]]="",0,1) -> 1 | S10: =IF(ISNA(VLOOKUP(выгрузка__22[[#This Row],[ЛС дилера]],'дилеры участники'!A:A,1,0)),0,1) -> 0 | T10: =IF(ISNA(VLOOKUP(выгрузка__22[[#This Row],[ТП комплекта текущий без города (столбец создан с помощью Power Query)]],Таблица3[Название ТП комплекта],1,0)),0,1) -> 1 | U10: =IF(ISNA(IF(выгрузка__22[[#This Row],[Канал продажи]]="Непрофильный",VLOOKUP(выгрузка__22[[#This Row],[ТП комплекта текущий без города (столбец создан с помощью Power Query)]],Таблица3[[Название ТП комплекта]:[Непрофильный]],3,0),VLOOKUP(выгрузка__22[[#This Row],[ТП комплекта текущий без города (столбец создан с помощью Power Query)]],Таблица3[[Название ТП комплекта]:[Непрофильный]],2,0)))=FALSE,1,0) -> 1 | V10: =IF(T10=1,IF(выгрузка__22[[#This Row],[Сумма дополнительного платежа и стартового баланса]]>300,VLOOKUP(выгрузка__22[[#This Row],[ТП комплекта текущий без города (столбец создан с помощью Power Query)]],Таблица3[],6,0),IF(выгрузка__22[[#This Row],[Сумма дополнительного платежа и стартового баланса]]>200,VLOOKUP(выгрузка__22[[#This Row],[ТП комплекта текущий без города (столбец создан с помощью Power Query)]],Таблица3[],5,0),IF(выгрузка__22[[#This Row],[Сумма дополнительного платежа и стартового баланса]]>100,VLOOKUP(выгрузка__22[[#This Row],[ТП комплекта текущий без города (столбец создан с помощью Power Query)]],Таблица3[],4,0),0))),0) -> 0 | W10: Супер МТС. Область | X10: =IF(выгрузка__22[[#This Row],[Дата активации]]<>0,IF(выгрузка__22[[#This Row],[Дата блокировки]]<>"",CEILING((выгрузка__22[[#This Row],[Дата блокировки]]-выгрузка__22[[#This Row],[Дата активации]])/30,1),0),0) -> 0 | Y10: =IF(выгрузка__22[[#This Row],[Дата блокировки]]<>"",1,0) -> 0
A11: 41593.502 | B11: 985210 | C11: 1754810 | D11: 41589.829 | E11: =IF(выгрузка__22[[#This Row],[Дата активации]]<>"",MONTH(выгрузка__22[[#This Row],[Дата активации]]),0) -> 11 | F11: 41591.846 | G11: 64626 | H11: Непрофильный | I11: Тверь | J11: - МТС Коннект-4 (МАСС) (SCP) | K11: 30 | L11: 0 | M11: 30 | N11: Активен | P11: МТС Коннект-4 (МАСС) (SCP) | Q11: =IF(AND(DAY(выгрузка__22[[#This Row],[Дата отправки смс]])>=1,DAY(выгрузка__22[[#This Row],[Дата отправки смс]])<=14,MONTH(выгрузка__22[[#This Row],[Дата отправки смс]])=10),1,0) -> 0 | R11: =IF(выгрузка__22[[#This Row],[Дата регистрации]]="",0,1) -> 1 | S11: =IF(ISNA(VLOOKUP(выгрузка__22[[#This Row],[ЛС дилера]],'дилеры участники'!A:A,1,0)),0,1) -> 0 | T11: =IF(ISNA(VLOOKUP(выгрузка__22[[#This Row],[ТП комплекта текущий без города (столбец создан с помощью Power Query)]],Таблица3[Название ТП комплекта],1,0)),0,1) -> 1 | U11: =IF(ISNA(IF(выгрузка__22[[#This Row],[Канал продажи]]="Непрофильный",VLOOKUP(выгрузка__22[[#This Row],[ТП комплекта текущий без города (столбец создан с помощью Power Query)]],Таблица3[[Название ТП комплекта]:[Непрофильный]],3,0),VLOOKUP(выгрузка__22[[#This Row],[ТП комплекта текущий без города (столбец создан с помощью Power Query)]],Таблица3[[Название ТП комплекта]:[Непрофильный]],2,0)))=FALSE,1,0) -> 1 | V11: =IF(T11=1,IF(выгрузка__22[[#This Row],[Сумма дополнительного платежа и стартового баланса]]>300,VLOOKUP(выгрузка__22[[#This Row],[ТП комплекта текущий без города (столбец создан с помощью Power Query)]],Таблица3[],6,0),IF(выгрузка__22[[#This Row],[Сумма дополнительного платежа и стартового баланса]]>200,VLOOKUP(выгрузка__22[[#This Row],[ТП комплекта текущий без города (столбец создан с помощью Power Query)]],Таблица3[],5,0),IF(выгрузка__22[[#This Row],[Сумма дополнительного платежа и стартового баланса]]>100,VLOOKUP(выгрузка__22[[#This Row],[ТП комплекта текущий без города (столбец создан с помощью Power Query)]],Таблица3[],4,0),0))),0) -> 0 | W11: МТС Коннект-4 | X11: =IF(выгрузка__22[[#This Row],[Дата активации]]<>0,IF(выгрузка__22[[#This Row],[Дата блокировки]]<>"",CEILING((выгрузка__22[[#This Row],[Дата блокировки]]-выгрузка__22[[#This Row],[Дата активации]])/30,1),0),0) -> 0 | Y11: =IF(выгрузка__22[[#This Row],[Дата блокировки]]<>"",1,0) -> 0
A12: 41593.588 | B12: 916512 | C12: 1697829 | D12: 41589.806 | E12: =IF(выгрузка__22[[#This Row],[Дата активации]]<>"",MONTH(выгрузка__22[[#This Row],[Дата активации]]),0) -> 11 | F12: 41591.855 | G12: 64626 | H12: Непрофильный | I12: Тверь | J12: - Супер МТС. Область (МАСС) (SCP) | K12: 30 | L12: 0 | M12: 30 | N12: Активен | P12: Супер МТС. Область (МАСС) (SCP) | Q12: =IF(AND(DAY(выгрузка__22[[#This Row],[Дата отправки смс]])>=1,DAY(выгрузка__22[[#This Row],[Дата отправки смс]])<=14,MONTH(выгрузка__22[[#This Row],[Дата отправки смс]])=10),1,0) -> 0 | R12: =IF(выгрузка__22[[#This Row],[Дата регистрации]]="",0,1) -> 1 | S12: =IF(ISNA(VLOOKUP(выгрузка__22[[#This Row],[ЛС дилера]],'дилеры участники'!A:A,1,0)),0,1) -> 0 | T12: =IF(ISNA(VLOOKUP(выгрузка__22[[#This Row],[ТП комплекта текущий без города (столбец создан с помощью Power Query)]],Таблица3[Название ТП комплекта],1,0)),0,1) -> 1 | U12: =IF(ISNA(IF(выгрузка__22[[#This Row],[Канал продажи]]="Непрофильный",VLOOKUP(выгрузка__22[[#This Row],[ТП комплекта текущий без города (столбец создан с помощью Power Query)]],Таблица3[[Название ТП комплекта]:[Непрофильный]],3,0),VLOOKUP(выгрузка__22[[#This Row],[ТП комплекта текущий без города (столбец создан с помощью Power Query)]],Таблица3[[Название ТП комплекта]:[Непрофильный]],2,0)))=FALSE,1,0) -> 1 | V12: =IF(T12=1,IF(выгрузка__22[[#This Row],[Сумма дополнительного платежа и стартового баланса]]>300,VLOOKUP(выгрузка__22[[#This Row],[ТП комплекта текущий без города (столбец создан с помощью Power Query)]],Таблица3[],6,0),IF(выгрузка__22[[#This Row],[Сумма дополнительного платежа и стартового баланса]]>200,VLOOKUP(выгрузка__22[[#This Row],[ТП комплекта текущий без города (столбец создан с помощью Power Query)]],Таблица3[],5,0),IF(выгрузка__22[[#This Row],[Сумма дополнительного платежа и стартового баланса]]>100,VLOOKUP(выгрузка__22[[#This Row],[ТП комплекта текущий без города (столбец создан с помощью Power Query)]],Таблица3[],4,0),0))),0) -> 0 | W12: Супер МТС. Область | X12: =IF(выгрузка__22[[#This Row],[Дата активации]]<>0,IF(выгрузка__22[[#This Row],[Дата блокировки]]<>"",CEILING((выгрузка__22[[#This Row],[Дата блокировки]]-выгрузка__22[[#This Row],[Дата активации]])/30,1),0),0) -> 0 | Y12: =IF(выгрузка__22[[#This Row],[Дата блокировки]]<>"",1,0) -> 0
A13: 41593.501 | B13: 985210 | C13: 8542892 | D13: 41589.767 | E13: =IF(выгрузка__22[[#This Row],[Дата активации]]<>"",MONTH(выгрузка__22[[#This Row],[Дата активации]]),0) -> 11 | F13: 41591.805 | G13: 64626 | H13: Непрофильный | I13: Тверь | J13: - МТС Коннект-4 (МАСС) (SCP) | K13: 401 | L13: 0 | M13: 401 | N13: Активен | P13: МТС Коннект-4 (МАСС) (SCP) | Q13: =IF(AND(DAY(выгрузка__22[[#This Row],[Дата отправки смс]])>=1,DAY(выгрузка__22[[#This Row],[Дата отправки смс]])<=14,MONTH(выгрузка__22[[#This Row],[Дата отправки смс]])=10),1,0) -> 0 | R13: =IF(выгрузка__22[[#This Row],[Дата регистрации]]="",0,1) -> 1 | S13: =IF(ISNA(VLOOKUP(выгрузка__22[[#This Row],[ЛС дилера]],'дилеры участники'!A:A,1,0)),0,1) -> 0 | T13: =IF(ISNA(VLOOKUP(выгрузка__22[[#This Row],[ТП комплекта текущий без города (столбец создан с помощью Power Query)]],Таблица3[Название ТП комплекта],1,0)),0,1) -> 1 | U13: =IF(ISNA(IF(выгрузка__22[[#This Row],[Канал продажи]]="Непрофильный",VLOOKUP(выгрузка__22[[#This Row],[ТП комплекта текущий без города (столбец создан с помощью Power Query)]],Таблица3[[Название ТП комплекта]:[Непрофильный]],3,0),VLOOKUP(выгрузка__22[[#This Row],[ТП комплекта текущий без города (столбец создан с помощью Power Query)]],Таблица3[[Название ТП комплекта]:[Непрофильный]],2,0)))=FALSE,1,0) -> 1 | V13: =IF(T13=1,IF(выгрузка__22[[#This Row],[Сумма дополнительного платежа и стартового баланса]]>300,VLOOKUP(выгрузка__22[[#This Row],[ТП комплекта текущий без города (столбец создан с помощью Power Query)]],Таблица3[],6,0),IF(выгрузка__22[[#This Row],[Сумма дополнительного платежа и стартового баланса]]>200,VLOOKUP(выгрузка__22[[#This Row],[ТП комплекта текущий без города (столбец создан с помощью Power Query)]],Таблица3[],5,0),IF(выгрузка__22[[#This Row],[Сумма дополнительного платежа и стартового баланса]]>100,VLOOKUP(выгрузка__22[[#This Row],[ТП комплекта текущий без города (столбец создан с помощью Power Query)]],Таблица3[],4,0),0))),0) -> 170 | W13: МТС Коннект-4 | X13: =IF(выгрузка__22[[#This Row],[Дата активации]]<>0,IF(выгрузка__22[[#This Row],[Дата блокировки]]<>"",CEILING((выгрузка__22[[#This Row],[Дата блокировки]]-выгрузка__22[[#This Row],[Дата активации]])/30,1),0),0) -> 0 | Y13: =IF(выгрузка__22[[#This Row],[Дата блокировки]]<>"",1,0) -> 0
A14: 41593.599 | B14: 916888 | C14: 1751205 | D14: 41589.757 | E14: =IF(выгрузка__22[[#This Row],[Дата активации]]<>"",MONTH(выгрузка__22[[#This Row],[Дата активации]]),0) -> 11 | F14: 41591.876 | G14: 64626 | H14: Непрофильный | I14: Тверь | J14: - Супер МТС. Область (МАСС) (SCP) | K14: 30 | L14: 0 | M14: 30 | N14: Активен | P14: Супер МТС. Область (МАСС) (SCP) | Q14: =IF(AND(DAY(выгрузка__22[[#This Row],[Дата отправки смс]])>=1,DAY(выгрузка__22[[#This Row],[Дата отправки смс]])<=14,MONTH(выгрузка__22[[#This Row],[Дата отправки смс]])=10),1,0) -> 0 | R14: =IF(выгрузка__22[[#This Row],[Дата регистрации]]="",0,1) -> 1 | S14: =IF(ISNA(VLOOKUP(выгрузка__22[[#This Row],[ЛС дилера]],'дилеры участники'!A:A,1,0)),0,1) -> 0 | T14: =IF(ISNA(VLOOKUP(выгрузка__22[[#This Row],[ТП комплекта текущий без города (столбец создан с помощью Power Query)]],Таблица3[Название ТП комплекта],1,0)),0,1) -> 1 | U14: =IF(ISNA(IF(выгрузка__22[[#This Row],[Канал продажи]]="Непрофильный",VLOOKUP(выгрузка__22[[#This Row],[ТП комплекта текущий без города (столбец создан с помощью Power Query)]],Таблица3[[Название ТП комплекта]:[Непрофильный]],3,0),VLOOKUP(выгрузка__22[[#This Row],[ТП комплекта текущий без города (столбец создан с помощью Power Query)]],Таблица3[[Название ТП комплекта]:[Непрофильный]],2,0)))=FALSE,1,0) -> 1 | V14: =IF(T14=1,IF(выгрузка__22[[#This Row],[Сумма дополнительного платежа и стартового баланса]]>300,VLOOKUP(выгрузка__22[[#This Row],[ТП комплекта текущий без города (столбец создан с помощью Power Query)]],Таблица3[],6,0),IF(выгрузка__22[[#This Row],[Сумма дополнительного платежа и стартового баланса]]>200,VLOOKUP(выгрузка__22[[#This Row],[ТП комплекта текущий без города (столбец создан с помощью Power Query)]],Таблица3[],5,0),IF(выгрузка__22[[#This Row],[Сумма дополнительного платежа и стартового баланса]]>100,VLOOKUP(выгрузка__22[[#This Row],[ТП комплекта текущий без города (столбец создан с помощью Power Query)]],Таблица3[],4,0),0))),0) -> 0 | W14: Супер МТС. Область | X14: =IF(выгрузка__22[[#This Row],[Дата активации]]<>0,IF(выгрузка__22[[#This Row],[Дата блокировки]]<>"",CEILING((выгрузка__22[[#This Row],[Дата блокировки]]-выгрузка__22[[#This Row],[Дата активации]])/30,1),0),0) -> 0 | Y14: =IF(выгрузка__22[[#This Row],[Дата блокировки]]<>"",1,0) -> 0
A15: 41593.598 | B15: 916888 | C15: 1698728 | D15: 41589.744 | E15: =IF(выгрузка__22[[#This Row],[Дата активации]]<>"",MONTH(выгрузка__22[[#This Row],[Дата активации]]),0) -> 11 | F15: 41591.94 | G15: 64626 | H15: Непрофильный | I15: Тверь | J15: - Супер МТС. Область (МАСС) (SCP) | K15: 30 | L15: 0 | M15: 30 | N15: Активен | P15: Супер МТС. Область (МАСС) (SCP) | Q15: =IF(AND(DAY(выгрузка__22[[#This Row],[Дата отправки смс]])>=1,DAY(выгрузка__22[[#This Row],[Дата отправки смс]])<=14,MONTH(выгрузка__22[[#This Row],[Дата отправки смс]])=10),1,0) -> 0 | R15: =IF(выгрузка__22[[#This Row],[Дата регистрации]]="",0,1) -> 1 | S15: =IF(ISNA(VLOOKUP(выгрузка__22[[#This Row],[ЛС дилера]],'дилеры участники'!A:A,1,0)),0,1) -> 0 | T15: =IF(ISNA(VLOOKUP(выгрузка__22[[#This Row],[ТП комплекта текущий без города (столбец создан с помощью Power Query)]],Таблица3[Название ТП комплекта],1,0)),0,1) -> 1 | U15: =IF(ISNA(IF(выгрузка__22[[#This Row],[Канал продажи]]="Непрофильный",VLOOKUP(выгрузка__22[[#This Row],[ТП комплекта текущий без города (столбец создан с помощью Power Query)]],Таблица3[[Название ТП комплекта]:[Непрофильный]],3,0),VLOOKUP(выгрузка__22[[#This Row],[ТП комплекта текущий без города (столбец создан с помощью Power Query)]],Таблица3[[Название ТП комплекта]:[Непрофильный]],2,0)))=FALSE,1,0) -> 1 | V15: =IF(T15=1,IF(выгрузка__22[[#This Row],[Сумма дополнительного платежа и стартового баланса]]>300,VLOOKUP(выгрузка__22[[#This Row],[ТП комплекта текущий без города (столбец создан с помощью Power Query)]],Таблица3[],6,0),IF(выгрузка__22[[#This Row],[Сумма дополнительного платежа и стартового баланса]]>200,VLOOKUP(выгрузка__22[[#This Row],[ТП комплекта текущий без города (столбец создан с помощью Power Query)]],Таблица3[],5,0),IF(выгрузка__22[[#This Row],[Сумма дополнительного платежа и стартового баланса]]>100,VLOOKUP(выгрузка__22[[#This Row],[ТП комплекта текущий без города (столбец создан с помощью Power Query)]],Таблица3[],4,0),0))),0) -> 0 | W15: Супер МТС. Область | X15: =IF(выгрузка__22[[#This Row],[Дата активации]]<>0,IF(выгрузка__22[[#This Row],[Дата блокировки]]<>"",CEILING((выгрузка__22[[#This Row],[Дата блокировки]]-выгрузка__22[[#This Row],[Дата активации]])/30,1),0),0) -> 0 | Y15: =IF(выгрузка__22[[#This Row],[Дата блокировки]]<>"",1,0) -> 0
A16: 41593.567 | B16: 916513 | C16: 1698739 | D16: 41589.545 | E16: =IF(выгрузка__22[[#This Row],[Дата активации]]<>"",MONTH(выгрузка__22[[#This Row],[Дата активации]]),0) -> 11 | F16: 41591.987 | G16: 64626 | H16: Непрофильный | I16: Тверь | J16: - Супер МТС (МАСС) (SCP) | K16: 1 | L16: 0 | M16: 1 | N16: Активен | P16: Супер МТС (МАСС) (SCP) | Q16: =IF(AND(DAY(выгрузка__22[[#This Row],[Дата отправки смс]])>=1,DAY(выгрузка__22[[#This Row],[Дата отправки смс]])<=14,MONTH(выгрузка__22[[#This Row],[Дата отправки смс]])=10),1,0) -> 0 | R16: =IF(выгрузка__22[[#This Row],[Дата регистрации]]="",0,1) -> 1 | S16: =IF(ISNA(VLOOKUP(выгрузка__22[[#This Row],[ЛС дилера]],'дилеры участники'!A:A,1,0)),0,1) -> 0 | T16: =IF(ISNA(VLOOKUP(выгрузка__22[[#This Row],[ТП комплекта текущий без города (столбец создан с помощью Power Query)]],Таблица3[Название ТП комплекта],1,0)),0,1) -> 1 | U16: =IF(ISNA(IF(выгрузка__22[[#This Row],[Канал продажи]]="Непрофильный",VLOOKUP(выгрузка__22[[#This Row],[ТП комплекта текущий без города (столбец создан с помощью Power Query)]],Таблица3[[Название ТП комплекта]:[Непрофильный]],3,0),VLOOKUP(выгрузка__22[[#This Row],[ТП комплекта текущий без города (столбец создан с помощью Power Query)]],Таблица3[[Название ТП комплекта]:[Непрофильный]],2,0)))=FALSE,1,0) -> 1 | V16: =IF(T16=1,IF(выгрузка__22[[#This Row],[Сумма дополнительного платежа и стартового баланса]]>300,VLOOKUP(выгрузка__22[[#This Row],[ТП комплекта текущий без города (столбец создан с помощью Power Query)]],Таблица3[],6,0),IF(выгрузка__22[[#This Row],[Сумма дополнительного платежа и стартового баланса]]>200,VLOOKUP(выгрузка__22[[#This Row],[ТП комплекта текущий без города (столбец создан с помощью Power Query)]],Таблица3[],5,0),IF(выгрузка__22[[#This Row],[Сумма дополнительного платежа и стартового баланса]]>100,VLOOKUP(выгрузка__22[[#This Row],[ТП комплекта текущий без города (столбец создан с помощью Power Query)]],Таблица3[],4,0),0))),0) -> 0 | W16: Супер МТС | X16: =IF(выгрузка__22[[#This Row],[Дата активации]]<>0,IF(выгрузка__22[[#This Row],[Дата блокировки]]<>"",CEILING((выгрузка__22[[#This Row],[Дата блокировки]]-выгрузка__22[[#This Row],[Дата активации]])/30,1),0),0) -> 0 | Y16: =IF(выгрузка__22[[#This Row],[Дата блокировки]]<>"",1,0) -> 0
A17: 41593.925 | B17: 916531 | C17: 1754677 | D17: 41589.319 | E17: =IF(выгрузка__22[[#This Row],[Дата активации]]<>"",MONTH(выгрузка__22[[#This Row],[Дата активации]]),0) -> 11 | G17: 64628 | H17: Непрофильный | I17: Тверь | J17: - Smart mini (МАСС) (SCP) | K17: 1 | L17: 200 | M17: 201 | N17: Активен | P17: Smart mini (МАСС) (SCP) | Q17: =IF(AND(DAY(выгрузка__22[[#This Row],[Дата отправки смс]])>=1,DAY(выгрузка__22[[#This Row],[Дата отправки смс]])<=14,MONTH(выгрузка__22[[#This Row],[Дата отправки смс]])=10),1,0) -> 0 | R17: =IF(выгрузка__22[[#This Row],[Дата регистрации]]="",0,1) -> 0 | S17: =IF(ISNA(VLOOKUP(выгрузка__22[[#This Row],[ЛС дилера]],'дилеры участники'!A:A,1,0)),0,1) -> 0 | T17: =IF(ISNA(VLOOKUP(выгрузка__22[[#This Row],[ТП комплекта текущий без города (столбец создан с помощью Power Query)]],Таблица3[Название ТП комплекта],1,0)),0,1) -> 1 | U17: =IF(ISNA(IF(выгрузка__22[[#This Row],[Канал продажи]]="Непрофильный",VLOOKUP(выгрузка__22[[#This Row],[ТП комплекта текущий без города (столбец создан с помощью Power Query)]],Таблица3[[Название ТП комплекта]:[Непрофильный]],3,0),VLOOKUP(выгрузка__22[[#This Row],[ТП комплекта текущий без города (столбец создан с помощью Power Query)]],Таблица3[[Название ТП комплекта]:[Непрофильный]],2,0)))=FALSE,1,0) -> 1 | V17: =IF(T17=1,IF(выгрузка__22[[#This Row],[Сумма дополнительного платежа и стартового баланса]]>300,VLOOKUP(выгрузка__22[[#This Row],[ТП комплекта текущий без города (столбец создан с помощью Power Query)]],Таблица3[],6,0),IF(выгрузка__22[[#This Row],[Сумма дополнительного платежа и стартового баланса]]>200,VLOOKUP(выгрузка__22[[#This Row],[ТП комплекта текущий без города (столбец создан с помощью Power Query)]],Таблица3[],5,0),IF(выгрузка__22[[#This Row],[Сумма дополнительного платежа и стартового баланса]]>100,VLOOKUP(выгрузка__22[[#This Row],[ТП комплекта текущий без города (столбец создан с помощью Power Query)]],Таблица3[],4,0),0))),0) -> 110 | W17: Smart mini | X17: =IF(выгрузка__22[[#This Row],[Дата активации]]<>0,IF(выгрузка__22[[#This Row],[Дата блокировки]]<>"",CEILING((выгрузка__22[[#This Row],[Дата блокировки]]-выгрузка__22[[#This Row],[Дата активации]])/30,1),0),0) -> 0 | Y17: =IF(выгрузка__22[[#This Row],[Дата блокировки]]<>"",1,0) -> 0
A18: 41593.591 | B18: 916512 | C18: 1698590 | D18: 41588.993 | E18: =IF(выгрузка__22[[#This Row],[Дата активации]]<>"",MONTH(выгрузка__22[[#This Row],[Дата активации]]),0) -> 11 | F18: 41591.939 | G18: 64626 | H18: Непрофильный | I18: Тверь | J18: - Супер МТС. Область (МАСС) (SCP) | K18: 30 | L18: 0 | M18: 30 | N18: Активен | P18: Супер МТС. Область (МАСС) (SCP) | Q18: =IF(AND(DAY(выгрузка__22[[#This Row],[Дата отправки смс]])>=1,DAY(выгрузка__22[[#This Row],[Дата отправки смс]])<=14,MONTH(выгрузка__22[[#This Row],[Дата отправки смс]])=10),1,0) -> 0 | R18: =IF(выгрузка__22[[#This Row],[Дата регистрации]]="",0,1) -> 1 | S18: =IF(ISNA(VLOOKUP(выгрузка__22[[#This Row],[ЛС дилера]],'дилеры участники'!A:A,1,0)),0,1) -> 0 | T18: =IF(ISNA(VLOOKUP(выгрузка__22[[#This Row],[ТП комплекта текущий без города (столбец создан с помощью Power Query)]],Таблица3[Название ТП комплекта],1,0)),0,1) -> 1 | U18: =IF(ISNA(IF(выгрузка__22[[#This Row],[Канал продажи]]="Непрофильный",VLOOKUP(выгрузка__22[[#This Row],[ТП комплекта текущий без города (столбец создан с помощью Power Query)]],Таблица3[[Название ТП комплекта]:[Непрофильный]],3,0),VLOOKUP(выгрузка__22[[#This Row],[ТП комплекта текущий без города (столбец создан с помощью Power Query)]],Таблица3[[Название ТП комплекта]:[Непрофильный]],2,0)))=FALSE,1,0) -> 1 | V18: =IF(T18=1,IF(выгрузка__22[[#This Row],[Сумма дополнительного платежа и стартового баланса]]>300,VLOOKUP(выгрузка__22[[#This Row],[ТП комплекта текущий без города (столбец создан с помощью Power Query)]],Таблица3[],6,0),IF(выгрузка__22[[#This Row],[Сумма дополнительного платежа и стартового баланса]]>200,VLOOKUP(выгрузка__22[[#This Row],[ТП комплекта текущий без города (столбец создан с помощью Power Query)]],Таблица3[],5,0),IF(выгрузка__22[[#This Row],[Сумма дополнительного платежа и стартового баланса]]>100,VLOOKUP(выгрузка__22[[#This Row],[ТП комплекта текущий без города (столбец создан с помощью Power Query)]],Таблица3[],4,0),0))),0) -> 0 | W18: Супер МТС. Область | X18: =IF(выгрузка__22[[#This Row],[Дата активации]]<>0,IF(выгрузка__22[[#This Row],[Дата блокировки]]<>"",CEILING((выгрузка__22[[#This Row],[Дата блокировки]]-выгрузка__22[[#This Row],[Дата активации]])/30,1),0),0) -> 0 | Y18: =IF(выгрузка__22[[#This Row],[Дата блокировки]]<>"",1,0) -> 0
A19: 41593.596 | B19: 916888 | C19: 1698667 | D19: 41588.898 | E19: =IF(выгрузка__22[[#This Row],[Дата активации]]<>"",MONTH(выгрузка__22[[#This Row],[Дата активации]]),0) -> 11 | F19: 41591.939 | G19: 64626 | H19: Непрофильный | I19: Тверь | J19: - Супер МТС. Область (МАСС) (SCP) | K19: 30 | L19: 0 | M19: 30 | N19: Активен | P19: Супер МТС. Область (МАСС) (SCP) | Q19: =IF(AND(DAY(выгрузка__22[[#This Row],[Дата отправки смс]])>=1,DAY(выгрузка__22[[#This Row],[Дата отправки смс]])<=14,MONTH(выгрузка__22[[#This Row],[Дата отправки смс]])=10),1,0) -> 0 | R19: =IF(выгрузка__22[[#This Row],[Дата регистрации]]="",0,1) -> 1 | S19: =IF(ISNA(VLOOKUP(выгрузка__22[[#This Row],[ЛС дилера]],'дилеры участники'!A:A,1,0)),0,1) -> 0 | T19: =IF(ISNA(VLOOKUP(выгрузка__22[[#This Row],[ТП комплекта текущий без города (столбец создан с помощью Power Query)]],Таблица3[Название ТП комплекта],1,0)),0,1) -> 1 | U19: =IF(ISNA(IF(выгрузка__22[[#This Row],[Канал продажи]]="Непрофильный",VLOOKUP(выгрузка__22[[#This Row],[ТП комплекта текущий без города (столбец создан с помощью Power Query)]],Таблица3[[Название ТП комплекта]:[Непрофильный]],3,0),VLOOKUP(выгрузка__22[[#This Row],[ТП комплекта текущий без города (столбец создан с помощью Power Query)]],Таблица3[[Название ТП комплекта]:[Непрофильный]],2,0)))=FALSE,1,0) -> 1 | V19: =IF(T19=1,IF(выгрузка__22[[#This Row],[Сумма дополнительного платежа и стартового баланса]]>300,VLOOKUP(выгрузка__22[[#This Row],[ТП комплекта текущий без города (столбец создан с помощью Power Query)]],Таблица3[],6,0),IF(выгрузка__22[[#This Row],[Сумма дополнительного платежа и стартового баланса]]>200,VLOOKUP(выгрузка__22[[#This Row],[ТП комплекта текущий без города (столбец создан с помощью Power Query)]],Таблица3[],5,0),IF(выгрузка__22[[#This Row],[Сумма дополнительного платежа и стартового баланса]]>100,VLOOKUP(выгрузка__22[[#This Row],[ТП комплекта текущий без города (столбец создан с помощью Power Query)]],Таблица3[],4,0),0))),0) -> 0 | W19: Супер МТС. Область | X19: =IF(выгрузка__22[[#This Row],[Дата активации]]<>0,IF(выгрузка__22[[#This Row],[Дата блокировки]]<>"",CEILING((выгрузка__22[[#This Row],[Дата блокировки]]-выгрузка__22[[#This Row],[Дата активации]])/30,1),0),0) -> 0 | Y19: =IF(выгрузка__22[[#This Row],[Дата блокировки]]<>"",1,0) -> 0
A20: 41588.724 | B20: 919100 | C20: 8528599 | D20: 41588.868 | E20: =IF(выгрузка__22[[#This Row],[Дата активации]]<>"",MONTH(выгрузка__22[[#This Row],[Дата активации]]),0) -> 11 | G20: 79956 | H20: Непрофильный | I20: Тверь | J20: - Супер МТС (МАСС) (SCP) | K20: 30 | L20: 0 | M20: 30 | N20: Активен | P20: Супер МТС (МАСС) (SCP) | Q20: =IF(AND(DAY(выгрузка__22[[#This Row],[Дата отправки смс]])>=1,DAY(выгрузка__22[[#This Row],[Дата отправки смс]])<=14,MONTH(выгрузка__22[[#This Row],[Дата отправки смс]])=10),1,0) -> 0 | R20: =IF(выгрузка__22[[#This Row],[Дата регистрации]]="",0,1) -> 0 | S20: =IF(ISNA(VLOOKUP(выгрузка__22[[#This Row],[ЛС дилера]],'дилеры участники'!A:A,1,0)),0,1) -> 1 | T20: =IF(ISNA(VLOOKUP(выгрузка__22[[#This Row],[ТП комплекта текущий без города (столбец создан с помощью Power Query)]],Таблица3[Название ТП комплекта],1,0)),0,1) -> 1 | U20: =IF(ISNA(IF(выгрузка__22[[#This Row],[Канал продажи]]="Непрофильный",VLOOKUP(выгрузка__22[[#This Row],[ТП комплекта текущий без города (столбец создан с помощью Power Query)]],Таблица3[[Название ТП комплекта]:[Непрофильный]],3,0),VLOOKUP(выгрузка__22[[#This Row],[ТП комплекта текущий без города (столбец создан с помощью Power Query)]],Таблица3[[Название ТП комплекта]:[Непрофильный]],2,0)))=FALSE,1,0) -> 1 | V20: =IF(T20=1,IF(выгрузка__22[[#This Row],[Сумма дополнительного платежа и стартового баланса]]>300,VLOOKUP(выгрузка__22[[#This Row],[ТП комплекта текущий без города (столбец создан с помощью Power Query)]],Таблица3[],6,0),IF(выгрузка__22[[#This Row],[Сумма дополнительного платежа и стартового баланса]]>200,VLOOKUP(выгрузка__22[[#This Row],[ТП комплекта текущий без города (столбец создан с помощью Power Query)]],Таблица3[],5,0),IF(выгрузка__22[[#This Row],[Сумма дополнительного платежа и стартового баланса]]>100,VLOOKUP(выгрузка__22[[#This Row],[ТП комплекта текущий без города (столбец создан с помощью Power Query)]],Таблица3[],4,0),0))),0) -> 0 | W20: Супер МТС | X20: =IF(выгрузка__22[[#This Row],[Дата активации]]<>0,IF(выгрузка__22[[#This Row],[Дата блокировки]]<>"",CEILING((выгрузка__22[[#This Row],[Дата блокировки]]-выгрузка__22[[#This Row],[Дата активации]])/30,1),0),0) -> 0 | Y20: =IF(выгрузка__22[[#This Row],[Дата блокировки]]<>"",1,0) -> 0
A21: 41593.59 | B21: 916512 | C21: 1698543 | D21: 41588.749 | E21: =IF(выгрузка__22[[#This Row],[Дата активации]]<>"",MONTH(выгрузка__22[[#This Row],[Дата активации]]),0) -> 11 | F21: 41591.939 | G21: 64626 | H21: Непрофильный | I21: Тверь | J21: - Супер МТС. Область (МАСС) (SCP) | K21: 30 | L21: 0 | M21: 30 | N21: Активен | P21: Супер МТС. Область (МАСС) (SCP) | Q21: =IF(AND(DAY(выгрузка__22[[#This Row],[Дата отправки смс]])>=1,DAY(выгрузка__22[[#This Row],[Дата отправки смс]])<=14,MONTH(выгрузка__22[[#This Row],[Дата отправки смс]])=10),1,0) -> 0 | R21: =IF(выгрузка__22[[#This Row],[Дата регистрации]]="",0,1) -> 1 | S21: =IF(ISNA(VLOOKUP(выгрузка__22[[#This Row],[ЛС дилера]],'дилеры участники'!A:A,1,0)),0,1) -> 0 | T21: =IF(ISNA(VLOOKUP(выгрузка__22[[#This Row],[ТП комплекта текущий без города (столбец создан с помощью Power Query)]],Таблица3[Название ТП комплекта],1,0)),0,1) -> 1 | U21: =IF(ISNA(IF(выгрузка__22[[#This Row],[Канал продажи]]="Непрофильный",VLOOKUP(выгрузка__22[[#This Row],[ТП комплекта текущий без города (столбец создан с помощью Power Query)]],Таблица3[[Название ТП комплекта]:[Непрофильный]],3,0),VLOOKUP(выгрузка__22[[#This Row],[ТП комплекта текущий без города (столбец создан с помощью Power Query)]],Таблица3[[Название ТП комплекта]:[Непрофильный]],2,0)))=FALSE,1,0) -> 1 | V21: =IF(T21=1,IF(выгрузка__22[[#This Row],[Сумма дополнительного платежа и стартового баланса]]>300,VLOOKUP(выгрузка__22[[#This Row],[ТП комплекта текущий без города (столбец создан с помощью Power Query)]],Таблица3[],6,0),IF(выгрузка__22[[#This Row],[Сумма дополнительного платежа и стартового баланса]]>200,VLOOKUP(выгрузка__22[[#This Row],[ТП комплекта текущий без города (столбец создан с помощью Power Query)]],Таблица3[],5,0),IF(выгрузка__22[[#This Row],[Сумма дополнительного платежа и стартового баланса]]>100,VLOOKUP(выгрузка__22[[#This Row],[ТП комплекта текущий без города (столбец создан с помощью Power Query)]],Таблица3[],4,0),0))),0) -> 0 | W21: Супер МТС. Область | X21: =IF(выгрузка__22[[#This Row],[Дата активации]]<>0,IF(выгрузка__22[[#This Row],[Дата блокировки]]<>"",CEILING((выгрузка__22[[#This Row],[Дата блокировки]]-выгрузка__22[[#This Row],[Дата активации]])/30,1),0),0) -> 0 | Y21: =IF(выгрузка__22[[#This Row],[Дата блокировки]]<>"",1,0) -> 0
A22: 41583.641 | B22: 985333 | C22: 8522342 | D22: 41588.697 | E22: =IF(выгрузка__22[[#This Row],[Дата активации]]<>"",MONTH(выгрузка__22[[#This Row],[Дата активации]]),0) -> 11 | F22: 41593.508 | G22: 64616 | H22: Непрофильный | I22: Тверь | J22: - Smart mini (МАСС) (SCP) | K22: 30 | L22: 500 | M22: 530 | N22: Активен | P22: Smart mini (МАСС) (SCP) | Q22: =IF(AND(DAY(выгрузка__22[[#This Row],[Дата отправки смс]])>=1,DAY(выгрузка__22[[#This Row],[Дата отправки смс]])<=14,MONTH(выгрузка__22[[#This Row],[Дата отправки смс]])=10),1,0) -> 0 | R22: =IF(выгрузка__22[[#This Row],[Дата регистрации]]="",0,1) -> 1 | S22: =IF(ISNA(VLOOKUP(выгрузка__22[[#This Row],[ЛС дилера]],'дилеры участники'!A:A,1,0)),0,1) -> 1 | T22: =IF(ISNA(VLOOKUP(выгрузка__22[[#This Row],[ТП комплекта текущий без города (столбец создан с помощью Power Query)]],Таблица3[Название ТП комплекта],1,0)),0,1) -> 1 | U22: =IF(ISNA(IF(выгрузка__22[[#This Row],[Канал продажи]]="Непрофильный",VLOOKUP(выгрузка__22[[#This Row],[ТП комплекта текущий без города (столбец создан с помощью Power Query)]],Таблица3[[Название ТП комплекта]:[Непрофильный]],3,0),VLOOKUP(выгрузка__22[[#This Row],[ТП комплекта текущий без города (столбец создан с помощью Power Query)]],Таблица3[[Название ТП комплекта]:[Непрофильный]],2,0)))=FALSE,1,0) -> 1 | V22: =IF(T22=1,IF(выгрузка__22[[#This Row],[Сумма дополнительного платежа и стартового баланса]]>300,VLOOKUP(выгрузка__22[[#This Row],[ТП комплекта текущий без города (столбец создан с помощью Power Query)]],Таблица3[],6,0),IF(выгрузка__22[[#This Row],[Сумма дополнительного платежа и стартового баланса]]>200,VLOOKUP(выгрузка__22[[#This Row],[ТП комплекта текущий без города (столбец создан с помощью Power Query)]],Таблица3[],5,0),IF(выгрузка__22[[#This Row],[Сумма дополнительного платежа и стартового баланса]]>100,VLOOKUP(выгрузка__22[[#This Row],[ТП комплекта текущий без города (столбец создан с помощью Power Query)]],Таблица3[],4,0),0))),0) -> 110 | W22: Smart mini | X22: =IF(выгрузка__22[[#This Row],[Дата активации]]<>0,IF(выгрузка__22[[#This Row],[Дата блокировки]]<>"",CEILING((выгрузка__22[[#This Row],[Дата блокировки]]-выгрузка__22[[#This Row],[Дата активации]])/30,1),0),0) -> 0 | Y22: =IF(выгрузка__22[[#This Row],[Дата блокировки]]<>"",1,0) -> 0
A23: 41593.501 | B23: 985210 | C23: 8524926 | D23: 41588.572 | E23: =IF(выгрузка__22[[#This Row],[Дата активации]]<>"",MONTH(выгрузка__22[[#This Row],[Дата активации]]),0) -> 11 | G23: 64626 | H23: Непрофильный | I23: Тверь | J23: - МТС Коннект-4 (МАСС) (SCP) | K23: 401 | L23: 100 | M23: 501 | N23: Активен | P23: МТС Коннект-4 (МАСС) (SCP) | Q23: =IF(AND(DAY(выгрузка__22[[#This Row],[Дата отправки смс]])>=1,DAY(выгрузка__22[[#This Row],[Дата отправки смс]])<=14,MONTH(выгрузка__22[[#This Row],[Дата отправки смс]])=10),1,0) -> 0 | R23: =IF(выгрузка__22[[#This Row],[Дата регистрации]]="",0,1) -> 0 | S23: =IF(ISNA(VLOOKUP(выгрузка__22[[#This Row],[ЛС дилера]],'дилеры участники'!A:A,1,0)),0,1) -> 0 | T23: =IF(ISNA(VLOOKUP(выгрузка__22[[#This Row],[ТП комплекта текущий без города (столбец создан с помощью Power Query)]],Таблица3[Название ТП комплекта],1,0)),0,1) -> 1 | U23: =IF(ISNA(IF(выгрузка__22[[#This Row],[Канал продажи]]="Непрофильный",VLOOKUP(выгрузка__22[[#This Row],[ТП комплекта текущий без города (столбец создан с помощью Power Query)]],Таблица3[[Название ТП комплекта]:[Непрофильный]],3,0),VLOOKUP(выгрузка__22[[#This Row],[ТП комплекта текущий без города (столбец создан с помощью Power Query)]],Таблица3[[Название ТП комплекта]:[Непрофильный]],2,0)))=FALSE,1,0) -> 1 | V23: =IF(T23=1,IF(выгрузка__22[[#This Row],[Сумма дополнительного платежа и стартового баланса]]>300,VLOOKUP(выгрузка__22[[#This Row],[ТП комплекта текущий без города (столбец создан с помощью Power Query)]],Таблица3[],6,0),IF(выгрузка__22[[#This Row],[Сумма дополнительного платежа и стартового баланса]]>200,VLOOKUP(выгрузка__22[[#This Row],[ТП комплекта текущий без города (столбец создан с помощью Power Query)]],Таблица3[],5,0),IF(выгрузка__22[[#This Row],[Сумма дополнительного платежа и стартового баланса]]>100,VLOOKUP(выгрузка__22[[#This Row],[ТП комплекта текущий без города (столбец создан с помощью Power Query)]],Таблица3[],4,0),0))),0) -> 170 | W23: МТС Коннект-4 | X23: =IF(выгрузка__22[[#This Row],[Дата активации]]<>0,IF(выгрузка__22[[#This Row],[Дата блокировки]]<>"",CEILING((выгрузка__22[[#This Row],[Дата блокировки]]-выгрузка__22[[#This Row],[Дата активации]])/30,1),0),0) -> 0 | Y23: =IF(выгрузка__22[[#This Row],[Дата блокировки]]<>"",1,0) -> 0
A24: 41593.596 | B24: 916888 | C24: 1698653 | D24: 41588.539 | E24: =IF(выгрузка__22[[#This Row],[Дата активации]]<>"",MONTH(выгрузка__22[[#This Row],[Дата активации]]),0) -> 11 | F24: 41591.939 | G24: 64626 | H24: Непрофильный | I24: Тверь | J24: - Супер МТС. Область (МАСС) (SCP) | K24: 30 | L24: 92.01 | M24: 122.01 | N24: Активен | P24: Супер МТС. Область (МАСС) (SCP) | Q24: =IF(AND(DAY(выгрузка__22[[#This Row],[Дата отправки смс]])>=1,DAY(выгрузка__22[[#This Row],[Дата отправки смс]])<=14,MONTH(выгрузка__22[[#This Row],[Дата отправки смс]])=10),1,0) -> 0 | R24: =IF(выгрузка__22[[#This Row],[Дата регистрации]]="",0,1) -> 1 | S24: =IF(ISNA(VLOOKUP(выгрузка__22[[#This Row],[ЛС дилера]],'дилеры участники'!A:A,1,0)),0,1) -> 0 | T24: =IF(ISNA(VLOOKUP(выгрузка__22[[#This Row],[ТП комплекта текущий без города (столбец создан с помощью Power Query)]],Таблица3[Название ТП комплекта],1,0)),0,1) -> 1 | U24: =IF(ISNA(IF(выгрузка__22[[#This Row],[Канал продажи]]="Непрофильный",VLOOKUP(выгрузка__22[[#This Row],[ТП комплекта текущий без города (столбец создан с помощью Power Query)]],Таблица3[[Название ТП комплекта]:[Непрофильный]],3,0),VLOOKUP(выгрузка__22[[#This Row],[ТП комплекта текущий без города (столбец создан с помощью Power Query)]],Таблица3[[Название ТП комплекта]:[Непрофильный]],2,0)))=FALSE,1,0) -> 1 | V24: =IF(T24=1,IF(выгрузка__22[[#This Row],[Сумма дополнительного платежа и стартового баланса]]>300,VLOOKUP(выгрузка__22[[#This Row],[ТП комплекта текущий без города (столбец создан с помощью Power Query)]],Таблица3[],6,0),IF(выгрузка__22[[#This Row],[Сумма дополнительного платежа и стартового баланса]]>200,VLOOKUP(выгрузка__22[[#This Row],[ТП комплекта текущий без города (столбец создан с помощью Power Query)]],Таблица3[],5,0),IF(выгрузка__22[[#This Row],[Сумма дополнительного платежа и стартового баланса]]>100,VLOOKUP(выгрузка__22[[#This Row],[ТП комплекта текущий без города (столбец создан с помощью Power Query)]],Таблица3[],4,0),0))),0) -> 70 | W24: Супер МТС. Область | X24: =IF(выгрузка__22[[#This Row],[Дата активации]]<>0,IF(выгрузка__22[[#This Row],[Дата блокировки]]<>"",CEILING((выгрузка__22[[#This Row],[Дата блокировки]]-выгрузка__22[[#This Row],[Дата активации]])/30,1),0),0) -> 0 | Y24: =IF(выгрузка__22[[#This Row],[Дата блокировки]]<>"",1,0) -> 0
A25: 41588.523 | B25: 916183 | C25: 8539482 | D25: 41588.535 | E25: =IF(выгрузка__22[[#This Row],[Дата активации]]<>"",MONTH(выгрузка__22[[#This Row],[Дата активации]]),0) -> 11 | G25: 64616 | H25: Непрофильный | I25: Тверь | J25: - Smart mini (МАСС) (SCP) | K25: 30 | L25: 242.5 | M25: 272.5 | N25: Активен | P25: Smart mini (МАСС) (SCP) | Q25: =IF(AND(DAY(выгрузка__22[[#This Row],[Дата отправки смс]])>=1,DAY(выгрузка__22[[#This Row],[Дата отправки смс]])<=14,MONTH(выгрузка__22[[#This Row],[Дата отправки смс]])=10),1,0) -> 0 | R25: =IF(выгрузка__22[[#This Row],[Дата регистрации]]="",0,1) -> 0 | S25: =IF(ISNA(VLOOKUP(выгрузка__22[[#This Row],[ЛС дилера]],'дилеры участники'!A:A,1,0)),0,1) -> 1 | T25: =IF(ISNA(VLOOKUP(выгрузка__22[[#This Row],[ТП комплекта текущий без города (столбец создан с помощью Power Query)]],Таблица3[Название ТП комплекта],1,0)),0,1) -> 1 | U25: =IF(ISNA(IF(выгрузка__22[[#This Row],[Канал продажи]]="Непрофильный",VLOOKUP(выгрузка__22[[#This Row],[ТП комплекта текущий без города (столбец создан с помощью Power Query)]],Таблица3[[Название ТП комплекта]:[Непрофильный]],3,0),VLOOKUP(выгрузка__22[[#This Row],[ТП комплекта текущий без города (столбец создан с помощью Power Query)]],Таблица3[[Название ТП комплекта]:[Непрофильный]],2,0)))=FALSE,1,0) -> 1 | V25: =IF(T25=1,IF(выгрузка__22[[#This Row],[Сумма дополнительного платежа и стартового баланса]]>300,VLOOKUP(выгрузка__22[[#This Row],[ТП комплекта текущий без города (столбец создан с помощью Power Query)]],Таблица3[],6,0),IF(выгрузка__22[[#This Row],[Сумма дополнительного платежа и стартового баланса]]>200,VLOOKUP(выгрузка__22[[#This Row],[ТП комплекта текущий без города (столбец создан с помощью Power Query)]],Таблица3[],5,0),IF(выгрузка__22[[#This Row],[Сумма дополнительного платежа и стартового баланса]]>100,VLOOKUP(выгрузка__22[[#This Row],[ТП комплекта текущий без города (столбец создан с помощью Power Query)]],Таблица3[],4,0),0))),0) -> 110 | W25: Smart mini | X25: =IF(выгрузка__22[[#This Row],[Дата активации]]<>0,IF(выгрузка__22[[#This Row],[Дата блокировки]]<>"",CEILING((выгрузка__22[[#This Row],[Дата блокировки]]-выгрузка__22[[#This Row],[Дата активации]])/30,1),0),0) -> 0 | Y25: =IF(выгрузка__22[[#This Row],[Дата блокировки]]<>"",1,0) -> 0
A26: 41588.57 | B26: 910437 | C26: 8547015 | D26: 41587.921 | E26: =IF(выгрузка__22[[#This Row],[Дата активации]]<>"",MONTH(выгрузка__22[[#This Row],[Дата активации]]),0) -> 11 | G26: 73902 | H26: Непрофильный | I26: Тверь | J26: - Smart mini (МАСС) (SCP) | K26: 220 | L26: 0 | M26: 220 | N26: Активен | P26: Smart mini (МАСС) (SCP) | Q26: =IF(AND(DAY(выгрузка__22[[#This Row],[Дата отправки смс]])>=1,DAY(выгрузка__22[[#This Row],[Дата отправки смс]])<=14,MONTH(выгрузка__22[[#This Row],[Дата отправки смс]])=10),1,0) -> 0 | R26: =IF(выгрузка__22[[#This Row],[Дата регистрации]]="",0,1) -> 0 | S26: =IF(ISNA(VLOOKUP(выгрузка__22[[#This Row],[ЛС дилера]],'дилеры участники'!A:A,1,0)),0,1) -> 0 | T26: =IF(ISNA(VLOOKUP(выгрузка__22[[#This Row],[ТП комплекта текущий без города (столбец создан с помощью Power Query)]],Таблица3[Название ТП комплекта],1,0)),0,1) -> 1 | U26: =IF(ISNA(IF(выгрузка__22[[#This Row],[Канал продажи]]="Непрофильный",VLOOKUP(выгрузка__22[[#This Row],[ТП комплекта текущий без города (столбец создан с помощью Power Query)]],Таблица3[[Название ТП комплекта]:[Непрофильный]],3,0),VLOOKUP(выгрузка__22[[#This Row],[ТП комплекта текущий без города (столбец создан с помощью Power Query)]],Таблица3[[Название ТП комплекта]:[Непрофильный]],2,0)))=FALSE,1,0) -> 1 | V26: =IF(T26=1,IF(выгрузка__22[[#This Row],[Сумма дополнительного платежа и стартового баланса]]>300,VLOOKUP(выгрузка__22[[#This Row],[ТП комплекта текущий без города (столбец создан с помощью Power Query)]],Таблица3[],6,0),IF(выгрузка__22[[#This Row],[Сумма дополнительного платежа и стартового баланса]]>200,VLOOKUP(выгрузка__22[[#This Row],[ТП комплекта текущий без города (столбец создан с помощью Power Query)]],Таблица3[],5,0),IF(выгрузка__22[[#This Row],[Сумма дополнительного платежа и стартового баланса]]>100,VLOOKUP(выгрузка__22[[#This Row],[ТП комплекта текущий без города (столбец создан с помощью Power Query)]],Таблица3[],4,0),0))),0) -> 110 | W26: Smart mini | X26: =IF(выгрузка__22[[#This Row],[Дата активации]]<>0,IF(выгрузка__22[[#This Row],[Дата блокировки]]<>"",CEILING((выгрузка__22[[#This Row],[Дата блокировки]]-выгрузка__22[[#This Row],[Дата активации]])/30,1),0),0) -> 0 | Y26: =IF(выгрузка__22[[#This Row],[Дата блокировки]]<>"",1,0) -> 0
A27: 41593.596 | B27: 916888 | C27: 1698658 | D27: 41587.9 | E27: =IF(выгрузка__22[[#This Row],[Дата активации]]<>"",MONTH(выгрузка__22[[#This Row],[Дата активации]]),0) -> 11 | F27: 41591.939 | G27: 64626 | H27: Непрофильный | I27: Тверь | J27: - Супер МТС. Область (МАСС) (SCP) | K27: 30 | L27: 0 | M27: 30 | N27: Активен | P27: Супер МТС. Область (МАСС) (SCP) | Q27: =IF(AND(DAY(выгрузка__22[[#This Row],[Дата отправки смс]])>=1,DAY(выгрузка__22[[#This Row],[Дата отправки смс]])<=14,MONTH(выгрузка__22[[#This Row],[Дата отправки смс]])=10),1,0) -> 0 | R27: =IF(выгрузка__22[[#This Row],[Дата регистрации]]="",0,1) -> 1 | S27: =IF(ISNA(VLOOKUP(выгрузка__22[[#This Row],[ЛС дилера]],'дилеры участники'!A:A,1,0)),0,1) -> 0 | T27: =IF(ISNA(VLOOKUP(выгрузка__22[[#This Row],[ТП комплекта текущий без города (столбец создан с помощью Power Query)]],Таблица3[Название ТП комплекта],1,0)),0,1) -> 1 | U27: =IF(ISNA(IF(выгрузка__22[[#This Row],[Канал продажи]]="Непрофильный",VLOOKUP(выгрузка__22[[#This Row],[ТП комплекта текущий без города (столбец создан с помощью Power Query)]],Таблица3[[Название ТП комплекта]:[Непрофильный]],3,0),VLOOKUP(выгрузка__22[[#This Row],[ТП комплекта текущий без города (столбец создан с помощью Power Query)]],Таблица3[[Название ТП комплекта]:[Непрофильный]],2,0)))=FALSE,1,0) -> 1 | V27: =IF(T27=1,IF(выгрузка__22[[#This Row],[Сумма дополнительного платежа и стартового баланса]]>300,VLOOKUP(выгрузка__22[[#This Row],[ТП комплекта текущий без города (столбец создан с помощью Power Query)]],Таблица3[],6,0),IF(выгрузка__22[[#This Row],[Сумма дополнительного платежа и стартового баланса]]>200,VLOOKUP(выгрузка__22[[#This Row],[ТП комплекта текущий без города (столбец создан с помощью Power Query)]],Таблица3[],5,0),IF(выгрузка__22[[#This Row],[Сумма дополнительного платежа и стартового баланса]]>100,VLOOKUP(выгрузка__22[[#This Row],[ТП комплекта текущий без города (столбец создан с помощью Power Query)]],Таблица3[],4,0),0))),0) -> 0 | W27: Супер МТС. Область | X27: =IF(выгрузка__22[[#This Row],[Дата активации]]<>0,IF(выгрузка__22[[#This Row],[Дата блокировки]]<>"",CEILING((выгрузка__22[[#This Row],[Дата блокировки]]-выгрузка__22[[#This Row],[Дата активации]])/30,1),0),0) -> 0 | Y27: =IF(выгрузка__22[[#This Row],[Дата блокировки]]<>"",1,0) -> 0
A28: 41593.592 | B28: 916512 | C28: 1698595 | D28: 41587.863 | E28: =IF(выгрузка__22[[#This Row],[Дата активации]]<>"",MONTH(выгрузка__22[[#This Row],[Дата активации]]),0) -> 11 | F28: 41591.938 | G28: 64626 | H28: Непрофильный | I28: Тверь | J28: - Супер МТС. Область (МАСС) (SCP) | K28: 30 | L28: 0 | M28: 30 | N28: Активен | P28: Супер МТС. Область (МАСС) (SCP) | Q28: =IF(AND(DAY(выгрузка__22[[#This Row],[Дата отправки смс]])>=1,DAY(выгрузка__22[[#This Row],[Дата отправки смс]])<=14,MONTH(выгрузка__22[[#This Row],[Дата отправки смс]])=10),1,0) -> 0 | R28: =IF(выгрузка__22[[#This Row],[Дата регистрации]]="",0,1) -> 1 | S28: =IF(ISNA(VLOOKUP(выгрузка__22[[#This Row],[ЛС дилера]],'дилеры участники'!A:A,1,0)),0,1) -> 0 | T28: =IF(ISNA(VLOOKUP(выгрузка__22[[#This Row],[ТП комплекта текущий без города (столбец создан с помощью Power Query)]],Таблица3[Название ТП комплекта],1,0)),0,1) -> 1 | U28: =IF(ISNA(IF(выгрузка__22[[#This Row],[Канал продажи]]="Непрофильный",VLOOKUP(выгрузка__22[[#This Row],[ТП комплекта текущий без города (столбец создан с помощью Power Query)]],Таблица3[[Название ТП комплекта]:[Непрофильный]],3,0),VLOOKUP(выгрузка__22[[#This Row],[ТП комплекта текущий без города (столбец создан с помощью Power Query)]],Таблица3[[Название ТП комплекта]:[Непрофильный]],2,0)))=FALSE,1,0) -> 1 | V28: =IF(T28=1,IF(выгрузка__22[[#This Row],[Сумма дополнительного платежа и стартового баланса]]>300,VLOOKUP(выгрузка__22[[#This Row],[ТП комплекта текущий без города (столбец создан с помощью Power Query)]],Таблица3[],6,0),IF(выгрузка__22[[#This Row],[Сумма дополнительного платежа и стартового баланса]]>200,VLOOKUP(выгрузка__22[[#This Row],[ТП комплекта текущий без города (столбец создан с помощью Power Query)]],Таблица3[],5,0),IF(выгрузка__22[[#This Row],[Сумма дополнительного платежа и стартового баланса]]>100,VLOOKUP(выгрузка__22[[#This Row],[ТП комплекта текущий без города (столбец создан с помощью Power Query)]],Таблица3[],4,0),0))),0) -> 0 | W28: Супер МТС. Область | X28: =IF(выгрузка__22[[#This Row],[Дата активации]]<>0,IF(выгрузка__22[[#This Row],[Дата блокировки]]<>"",CEILING((выгрузка__22[[#This Row],[Дата блокировки]]-выгрузка__22[[#This Row],[Дата активации]])/30,1),0),0) -> 0 | Y28: =IF(выгрузка__22[[#This Row],[Дата блокировки]]<>"",1,0) -> 0
A29: 41593.599 | B29: 916888 | C29: 1752159 | D29: 41587.862 | E29: =IF(выгрузка__22[[#This Row],[Дата активации]]<>"",MONTH(выгрузка__22[[#This Row],[Дата активации]]),0) -> 11 | F29: 41592.001 | G29: 64626 | H29: Непрофильный | I29: Тверь | J29: - Супер МТС. Область (МАСС) (SCP) | K29: 30 | L29: 0 | M29: 30 | N29: Активен | P29: Супер МТС. Область (МАСС) (SCP) | Q29: =IF(AND(DAY(выгрузка__22[[#This Row],[Дата отправки смс]])>=1,DAY(выгрузка__22[[#This Row],[Дата отправки смс]])<=14,MONTH(выгрузка__22[[#This Row],[Дата отправки смс]])=10),1,0) -> 0 | R29: =IF(выгрузка__22[[#This Row],[Дата регистрации]]="",0,1) -> 1 | S29: =IF(ISNA(VLOOKUP(выгрузка__22[[#This Row],[ЛС дилера]],'дилеры участники'!A:A,1,0)),0,1) -> 0 | T29: =IF(ISNA(VLOOKUP(выгрузка__22[[#This Row],[ТП комплекта текущий без города (столбец создан с помощью Power Query)]],Таблица3[Название ТП комплекта],1,0)),0,1) -> 1 | U29: =IF(ISNA(IF(выгрузка__22[[#This Row],[Канал продажи]]="Непрофильный",VLOOKUP(выгрузка__22[[#This Row],[ТП комплекта текущий без города (столбец создан с помощью Power Query)]],Таблица3[[Название ТП комплекта]:[Непрофильный]],3,0),VLOOKUP(выгрузка__22[[#This Row],[ТП комплекта текущий без города (столбец создан с помощью Power Query)]],Таблица3[[Название ТП комплекта]:[Непрофильный]],2,0)))=FALSE,1,0) -> 1 | V29: =IF(T29=1,IF(выгрузка__22[[#This Row],[Сумма дополнительного платежа и стартового баланса]]>300,VLOOKUP(выгрузка__22[[#This Row],[ТП комплекта текущий без города (столбец создан с помощью Power Query)]],Таблица3[],6,0),IF(выгрузка__22[[#This Row],[Сумма дополнительного платежа и стартового баланса]]>200,VLOOKUP(выгрузка__22[[#This Row],[ТП комплекта текущий без города (столбец создан с помощью Power Query)]],Таблица3[],5,0),IF(выгрузка__22[[#This Row],[Сумма дополнительного платежа и стартового баланса]]>100,VLOOKUP(выгрузка__22[[#This Row],[ТП комплекта текущий без города (столбец создан с помощью Power Query)]],Таблица3[],4,0),0))),0) -> 0 | W29: Супер МТС. Область | X29: =IF(выгрузка__22[[#This Row],[Дата активации]]<>0,IF(выгрузка__22[[#This Row],[Дата блокировки]]<>"",CEILING((выгрузка__22[[#This Row],[Дата блокировки]]-выгрузка__22[[#This Row],[Дата активации]])/30,1),0),0) -> 0 | Y29: =IF(выгрузка__22[[#This Row],[Дата блокировки]]<>"",1,0) -> 0
A30: 41593.502 | B30: 985210 | C30: 1754777 | D30: 41587.626 | E30: =IF(выгрузка__22[[#This Row],[Дата активации]]<>"",MONTH(выгрузка__22[[#This Row],[Дата активации]]),0) -> 11 | F30: 41591.844 | G30: 64626 | H30: Непрофильный | I30: Тверь | J30: - МТС Коннект-4 (МАСС) (SCP) | K30: 30 | L30: 0 | M30: 30 | N30: Активен | P30: МТС Коннект-4 (МАСС) (SCP) | Q30: =IF(AND(DAY(выгрузка__22[[#This Row],[Дата отправки смс]])>=1,DAY(выгрузка__22[[#This Row],[Дата отправки смс]])<=14,MONTH(выгрузка__22[[#This Row],[Дата отправки смс]])=10),1,0) -> 0 | R30: =IF(выгрузка__22[[#This Row],[Дата регистрации]]="",0,1) -> 1 | S30: =IF(ISNA(VLOOKUP(выгрузка__22[[#This Row],[ЛС дилера]],'дилеры участники'!A:A,1,0)),0,1) -> 0 | T30: =IF(ISNA(VLOOKUP(выгрузка__22[[#This Row],[ТП комплекта текущий без города (столбец создан с помощью Power Query)]],Таблица3[Название ТП комплекта],1,0)),0,1) -> 1 | U30: =IF(ISNA(IF(выгрузка__22[[#This Row],[Канал продажи]]="Непрофильный",VLOOKUP(выгрузка__22[[#This Row],[ТП комплекта текущий без города (столбец создан с помощью Power Query)]],Таблица3[[Название ТП комплекта]:[Непрофильный]],3,0),VLOOKUP(выгрузка__22[[#This Row],[ТП комплекта текущий без города (столбец создан с помощью Power Query)]],Таблица3[[Название ТП комплекта]:[Непрофильный]],2,0)))=FALSE,1,0) -> 1 | V30: =IF(T30=1,IF(выгрузка__22[[#This Row],[Сумма дополнительного платежа и стартового баланса]]>300,VLOOKUP(выгрузка__22[[#This Row],[ТП комплекта текущий без города (столбец создан с помощью Power Query)]],Таблица3[],6,0),IF(выгрузка__22[[#This Row],[Сумма дополнительного платежа и стартового баланса]]>200,VLOOKUP(выгрузка__22[[#This Row],[ТП комплекта текущий без города (столбец создан с помощью Power Query)]],Таблица3[],5,0),IF(выгрузка__22[[#This Row],[Сумма дополнительного платежа и стартового баланса]]>100,VLOOKUP(выгрузка__22[[#This Row],[ТП комплекта текущий без города (столбец создан с помощью Power Query)]],Таблица3[],4,0),0))),0) -> 0 | W30: МТС Коннект-4 | X30: =IF(выгрузка__22[[#This Row],[Дата активации]]<>0,IF(выгрузка__22[[#This Row],[Дата блокировки]]<>"",CEILING((выгрузка__22[[#This Row],[Дата блокировки]]-выгрузка__22[[#This Row],[Дата активации]])/30,1),0),0) -> 0 | Y30: =IF(выгрузка__22[[#This Row],[Дата блокировки]]<>"",1,0) -> 0
A31: 41593.599 | B31: 916888 | C31: 1750221 | D31: 41587.575 | E31: =IF(выгрузка__22[[#This Row],[Дата активации]]<>"",MONTH(выгрузка__22[[#This Row],[Дата активации]]),0) -> 11 | F31: 41591.869 | G31: 64626 | H31: Непрофильный | I31: Тверь | J31: - Супер МТС. Область (МАСС) (SCP) | K31: 30 | L31: 0 | M31: 30 | N31: Активен | P31: Супер МТС. Область (МАСС) (SCP) | Q31: =IF(AND(DAY(выгрузка__22[[#This Row],[Дата отправки смс]])>=1,DAY(выгрузка__22[[#This Row],[Дата отправки смс]])<=14,MONTH(выгрузка__22[[#This Row],[Дата отправки смс]])=10),1,0) -> 0 | R31: =IF(выгрузка__22[[#This Row],[Дата регистрации]]="",0,1) -> 1 | S31: =IF(ISNA(VLOOKUP(выгрузка__22[[#This Row],[ЛС дилера]],'дилеры участники'!A:A,1,0)),0,1) -> 0 | T31: =IF(ISNA(VLOOKUP(выгрузка__22[[#This Row],[ТП комплекта текущий без города (столбец создан с помощью Power Query)]],Таблица3[Название ТП комплекта],1,0)),0,1) -> 1 | U31: =IF(ISNA(IF(выгрузка__22[[#This Row],[Канал продажи]]="Непрофильный",VLOOKUP(выгрузка__22[[#This Row],[ТП комплекта текущий без города (столбец создан с помощью Power Query)]],Таблица3[[Название ТП комплекта]:[Непрофильный]],3,0),VLOOKUP(выгрузка__22[[#This Row],[ТП комплекта текущий без города (столбец создан с помощью Power Query)]],Таблица3[[Название ТП комплекта]:[Непрофильный]],2,0)))=FALSE,1,0) -> 1 | V31: =IF(T31=1,IF(выгрузка__22[[#This Row],[Сумма дополнительного платежа и стартового баланса]]>300,VLOOKUP(выгрузка__22[[#This Row],[ТП комплекта текущий без города (столбец создан с помощью Power Query)]],Таблица3[],6,0),IF(выгрузка__22[[#This Row],[Сумма дополнительного платежа и стартового баланса]]>200,VLOOKUP(выгрузка__22[[#This Row],[ТП комплекта текущий без города (столбец создан с помощью Power Query)]],Таблица3[],5,0),IF(выгрузка__22[[#This Row],[Сумма дополнительного платежа и стартового баланса]]>100,VLOOKUP(выгрузка__22[[#This Row],[ТП комплекта текущий без города (столбец создан с помощью Power Query)]],Таблица3[],4,0),0))),0) -> 0 | W31: Супер МТС. Область | X31: =IF(выгрузка__22[[#This Row],[Дата активации]]<>0,IF(выгрузка__22[[#This Row],[Дата блокировки]]<>"",CEILING((выгрузка__22[[#This Row],[Дата блокировки]]-выгрузка__22[[#This Row],[Дата активации]])/30,1),0),0) -> 0 | Y31: =IF(выгрузка__22[[#This Row],[Дата блокировки]]<>"",1,0) -> 0
A32: 41593.599 | B32: 916888 | C32: 1750220 | D32: 41587.549 | E32: =IF(выгрузка__22[[#This Row],[Дата активации]]<>"",MONTH(выгрузка__22[[#This Row],[Дата активации]]),0) -> 11 | F32: 41591.869 | G32: 64626 | H32: Непрофильный | I32: Тверь | J32: - Супер МТС. Область (МАСС) (SCP) | K32: 30 | L32: 0 | M32: 30 | N32: Активен | P32: Супер МТС. Область (МАСС) (SCP) | Q32: =IF(AND(DAY(выгрузка__22[[#This Row],[Дата отправки смс]])>=1,DAY(выгрузка__22[[#This Row],[Дата отправки смс]])<=14,MONTH(выгрузка__22[[#This Row],[Дата отправки смс]])=10),1,0) -> 0 | R32: =IF(выгрузка__22[[#This Row],[Дата регистрации]]="",0,1) -> 1 | S32: =IF(ISNA(VLOOKUP(выгрузка__22[[#This Row],[ЛС дилера]],'дилеры участники'!A:A,1,0)),0,1) -> 0 | T32: =IF(ISNA(VLOOKUP(выгрузка__22[[#This Row],[ТП комплекта текущий без города (столбец создан с помощью Power Query)]],Таблица3[Название ТП комплекта],1,0)),0,1) -> 1 | U32: =IF(ISNA(IF(выгрузка__22[[#This Row],[Канал продажи]]="Непрофильный",VLOOKUP(выгрузка__22[[#This Row],[ТП комплекта текущий без города (столбец создан с помощью Power Query)]],Таблица3[[Название ТП комплекта]:[Непрофильный]],3,0),VLOOKUP(выгрузка__22[[#This Row],[ТП комплекта текущий без города (столбец создан с помощью Power Query)]],Таблица3[[Название ТП комплекта]:[Непрофильный]],2,0)))=FALSE,1,0) -> 1 | V32: =IF(T32=1,IF(выгрузка__22[[#This Row],[Сумма дополнительного платежа и стартового баланса]]>300,VLOOKUP(выгрузка__22[[#This Row],[ТП комплекта текущий без города (столбец создан с помощью Power Query)]],Таблица3[],6,0),IF(выгрузка__22[[#This Row],[Сумма дополнительного платежа и стартового баланса]]>200,VLOOKUP(выгрузка__22[[#This Row],[ТП комплекта текущий без города (столбец создан с помощью Power Query)]],Таблица3[],5,0),IF(выгрузка__22[[#This Row],[Сумма дополнительного платежа и стартового баланса]]>100,VLOOKUP(выгрузка__22[[#This Row],[ТП комплекта текущий без города (столбец создан с помощью Power Query)]],Таблица3[],4,0),0))),0) -> 0 | W32: Супер МТС. Область | X32: =IF(выгрузка__22[[#This Row],[Дата активации]]<>0,IF(выгрузка__22[[#This Row],[Дата блокировки]]<>"",CEILING((выгрузка__22[[#This Row],[Дата блокировки]]-выгрузка__22[[#This Row],[Дата активации]])/30,1),0),0) -> 0 | Y32: =IF(выгрузка__22[[#This Row],[Дата блокировки]]<>"",1,0) -> 0
A33: 41593.596 | B33: 916888 | C33: 1698662 | D33: 41587.53 | E33: =IF(выгрузка__22[[#This Row],[Дата активации]]<>"",MONTH(выгрузка__22[[#This Row],[Дата активации]]),0) -> 11 | F33: 41591.938 | G33: 64626 | H33: Непрофильный | I33: Тверь | J33: - Супер МТС. Область (МАСС) (SCP) | K33: 30 | L33: 0 | M33: 30 | N33: Активен | P33: Супер МТС. Область (МАСС) (SCP) | Q33: =IF(AND(DAY(выгрузка__22[[#This Row],[Дата отправки смс]])>=1,DAY(выгрузка__22[[#This Row],[Дата отправки смс]])<=14,MONTH(выгрузка__22[[#This Row],[Дата отправки смс]])=10),1,0) -> 0 | R33: =IF(выгрузка__22[[#This Row],[Дата регистрации]]="",0,1) -> 1 | S33: =IF(ISNA(VLOOKUP(выгрузка__22[[#This Row],[ЛС дилера]],'дилеры участники'!A:A,1,0)),0,1) -> 0 | T33: =IF(ISNA(VLOOKUP(выгрузка__22[[#This Row],[ТП комплекта текущий без города (столбец создан с помощью Power Query)]],Таблица3[Название ТП комплекта],1,0)),0,1) -> 1 | U33: =IF(ISNA(IF(выгрузка__22[[#This Row],[Канал продажи]]="Непрофильный",VLOOKUP(выгрузка__22[[#This Row],[ТП комплекта текущий без города (столбец создан с помощью Power Query)]],Таблица3[[Название ТП комплекта]:[Непрофильный]],3,0),VLOOKUP(выгрузка__22[[#This Row],[ТП комплекта текущий без города (столбец создан с помощью Power Query)]],Таблица3[[Название ТП комплекта]:[Непрофильный]],2,0)))=FALSE,1,0) -> 1 | V33: =IF(T33=1,IF(выгрузка__22[[#This Row],[Сумма дополнительного платежа и стартового баланса]]>300,VLOOKUP(выгрузка__22[[#This Row],[ТП комплекта текущий без города (столбец создан с помощью Power Query)]],Таблица3[],6,0),IF(выгрузка__22[[#This Row],[Сумма дополнительного платежа и стартового баланса]]>200,VLOOKUP(выгрузка__22[[#This Row],[ТП комплекта текущий без города (столбец создан с помощью Power Query)]],Таблица3[],5,0),IF(выгрузка__22[[#This Row],[Сумма дополнительного платежа и стартового баланса]]>100,VLOOKUP(выгрузка__22[[#This Row],[ТП комплекта текущий без города (столбец создан с помощью Power Query)]],Таблица3[],4,0),0))),0) -> 0 | W33: Супер МТС. Область | X33: =IF(выгрузка__22[[#This Row],[Дата активации]]<>0,IF(выгрузка__22[[#This Row],[Дата блокировки]]<>"",CEILING((выгрузка__22[[#This Row],[Дата блокировки]]-выгрузка__22[[#This Row],[Дата активации]])/30,1),0),0) -> 0 | Y33: =IF(выгрузка__22[[#This Row],[Дата блокировки]]<>"",1,0) -> 0
A34: 41593.504 | B34: 985210 | C34: 1755038 | D34: 41587.486 | E34: =IF(выгрузка__22[[#This Row],[Дата активации]]<>"",MONTH(выгрузка__22[[#This Row],[Дата активации]]),0) -> 11 | F34: 41591.843 | G34: 64626 | H34: Непрофильный | I34: Тверь | J34: - МТС Коннект-4 (МАСС) (SCP) | K34: 30 | L34: 92.01 | M34: 122.01 | N34: Активен | P34: МТС Коннект-4 (МАСС) (SCP) | Q34: =IF(AND(DAY(выгрузка__22[[#This Row],[Дата отправки смс]])>=1,DAY(выгрузка__22[[#This Row],[Дата отправки смс]])<=14,MONTH(выгрузка__22[[#This Row],[Дата отправки смс]])=10),1,0) -> 0 | R34: =IF(выгрузка__22[[#This Row],[Дата регистрации]]="",0,1) -> 1 | S34: =IF(ISNA(VLOOKUP(выгрузка__22[[#This Row],[ЛС дилера]],'дилеры участники'!A:A,1,0)),0,1) -> 0 | T34: =IF(ISNA(VLOOKUP(выгрузка__22[[#This Row],[ТП комплекта текущий без города (столбец создан с помощью Power Query)]],Таблица3[Название ТП комплекта],1,0)),0,1) -> 1 | U34: =IF(ISNA(IF(выгрузка__22[[#This Row],[Канал продажи]]="Непрофильный",VLOOKUP(выгрузка__22[[#This Row],[ТП комплекта текущий без города (столбец создан с помощью Power Query)]],Таблица3[[Название ТП комплекта]:[Непрофильный]],3,0),VLOOKUP(выгрузка__22[[#This Row],[ТП комплекта текущий без города (столбец создан с помощью Power Query)]],Таблица3[[Название ТП комплекта]:[Непрофильный]],2,0)))=FALSE,1,0) -> 1 | V34: =IF(T34=1,IF(выгрузка__22[[#This Row],[Сумма дополнительного платежа и стартового баланса]]>300,VLOOKUP(выгрузка__22[[#This Row],[ТП комплекта текущий без города (столбец создан с помощью Power Query)]],Таблица3[],6,0),IF(выгрузка__22[[#This Row],[Сумма дополнительного платежа и стартового баланса]]>200,VLOOKUP(выгрузка__22[[#This Row],[ТП комплекта текущий без города (столбец создан с помощью Power Query)]],Таблица3[],5,0),IF(выгрузка__22[[#This Row],[Сумма дополнительного платежа и стартового баланса]]>100,VLOOKUP(выгрузка__22[[#This Row],[ТП комплекта текущий без города (столбец создан с помощью Power Query)]],Таблица3[],4,0),0))),0) -> 0 | W34: МТС Коннект-4 | X34: =IF(выгрузка__22[[#This Row],[Дата активации]]<>0,IF(выгрузка__22[[#This Row],[Дата блокировки]]<>"",CEILING((выгрузка__22[[#This Row],[Дата блокировки]]-выгрузка__22[[#This Row],[Дата активации]])/30,1),0),0) -> 0 | Y34: =IF(выгрузка__22[[#This Row],[Дата блокировки]]<>"",1,0) -> 0
A35: 41593.596 | B35: 916888 | C35: 1698671 | D35: 41587.486 | E35: =IF(выгрузка__22[[#This Row],[Дата активации]]<>"",MONTH(выгрузка__22[[#This Row],[Дата активации]]),0) -> 11 | F35: 41591.938 | G35: 64626 | H35: Непрофильный | I35: Тверь | J35: - Супер МТС. Область (МАСС) (SCP) | K35: 30 | L35: 0 | M35: 30 | N35: Активен | P35: Супер МТС. Область (МАСС) (SCP) | Q35: =IF(AND(DAY(выгрузка__22[[#This Row],[Дата отправки смс]])>=1,DAY(выгрузка__22[[#This Row],[Дата отправки смс]])<=14,MONTH(выгрузка__22[[#This Row],[Дата отправки смс]])=10),1,0) -> 0 | R35: =IF(выгрузка__22[[#This Row],[Дата регистрации]]="",0,1) -> 1 | S35: =IF(ISNA(VLOOKUP(выгрузка__22[[#This Row],[ЛС дилера]],'дилеры участники'!A:A,1,0)),0,1) -> 0 | T35: =IF(ISNA(VLOOKUP(выгрузка__22[[#This Row],[ТП комплекта текущий без города (столбец создан с помощью Power Query)]],Таблица3[Название ТП комплекта],1,0)),0,1) -> 1 | U35: =IF(ISNA(IF(выгрузка__22[[#This Row],[Канал продажи]]="Непрофильный",VLOOKUP(выгрузка__22[[#This Row],[ТП комплекта текущий без города (столбец создан с помощью Power Query)]],Таблица3[[Название ТП комплекта]:[Непрофильный]],3,0),VLOOKUP(выгрузка__22[[#This Row],[ТП комплекта текущий без города (столбец создан с помощью Power Query)]],Таблица3[[Название ТП комплекта]:[Непрофильный]],2,0)))=FALSE,1,0) -> 1 | V35: =IF(T35=1,IF(выгрузка__22[[#This Row],[Сумма дополнительного платежа и стартового баланса]]>300,VLOOKUP(выгрузка__22[[#This Row],[ТП комплекта текущий без города (столбец создан с помощью Power Query)]],Таблица3[],6,0),IF(выгрузка__22[[#This Row],[Сумма дополнительного платежа и стартового баланса]]>200,VLOOKUP(выгрузка__22[[#This Row],[ТП комплекта текущий без города (столбец создан с помощью Power Query)]],Таблица3[],5,0),IF(выгрузка__22[[#This Row],[Сумма дополнительного платежа и стартового баланса]]>100,VLOOKUP(выгрузка__22[[#This Row],[ТП комплекта текущий без города (столбец создан с помощью Power Query)]],Таблица3[],4,0),0))),0) -> 0 | W35: Супер МТС. Область | X35: =IF(выгрузка__22[[#This Row],[Дата активации]]<>0,IF(выгрузка__22[[#This Row],[Дата блокировки]]<>"",CEILING((выгрузка__22[[#This Row],[Дата блокировки]]-выгрузка__22[[#This Row],[Дата активации]])/30,1),0),0) -> 0 | Y35: =IF(выгрузка__22[[#This Row],[Дата блокировки]]<>"",1,0) -> 0
A36: 41588.392 | B36: 917535 | C36: 8524943 | D36: 41586.85 | E36: =IF(выгрузка__22[[#This Row],[Дата активации]]<>"",MONTH(выгрузка__22[[#This Row],[Дата активации]]),0) -> 11 | F36: 41587.8 | G36: 64626 | H36: Непрофильный | I36: Тверь | J36: - МТС Коннект-4 (МАСС) (SCP) | K36: 401 | L36: 0 | M36: 401 | N36: Активен | P36: МТС Коннект-4 (МАСС) (SCP) | Q36: =IF(AND(DAY(выгрузка__22[[#This Row],[Дата отправки смс]])>=1,DAY(выгрузка__22[[#This Row],[Дата отправки смс]])<=14,MONTH(выгрузка__22[[#This Row],[Дата отправки смс]])=10),1,0) -> 0 | R36: =IF(выгрузка__22[[#This Row],[Дата регистрации]]="",0,1) -> 1 | S36: =IF(ISNA(VLOOKUP(выгрузка__22[[#This Row],[ЛС дилера]],'дилеры участники'!A:A,1,0)),0,1) -> 0 | T36: =IF(ISNA(VLOOKUP(выгрузка__22[[#This Row],[ТП комплекта текущий без города (столбец создан с помощью Power Query)]],Таблица3[Название ТП комплекта],1,0)),0,1) -> 1 | U36: =IF(ISNA(IF(выгрузка__22[[#This Row],[Канал продажи]]="Непрофильный",VLOOKUP(выгрузка__22[[#This Row],[ТП комплекта текущий без города (столбец создан с помощью Power Query)]],Таблица3[[Название ТП комплекта]:[Непрофильный]],3,0),VLOOKUP(выгрузка__22[[#This Row],[ТП комплекта текущий без города (столбец создан с помощью Power Query)]],Таблица3[[Название ТП комплекта]:[Непрофильный]],2,0)))=FALSE,1,0) -> 1 | V36: =IF(T36=1,IF(выгрузка__22[[#This Row],[Сумма дополнительного платежа и стартового баланса]]>300,VLOOKUP(выгрузка__22[[#This Row],[ТП комплекта текущий без города (столбец создан с помощью Power Query)]],Таблица3[],6,0),IF(выгрузка__22[[#This Row],[Сумма дополнительного платежа и стартового баланса]]>200,VLOOKUP(выгрузка__22[[#This Row],[ТП комплекта текущий без города (столбец создан с помощью Power Query)]],Таблица3[],5,0),IF(выгрузка__22[[#This Row],[Сумма дополнительного платежа и стартового баланса]]>100,VLOOKUP(выгрузка__22[[#This Row],[ТП комплекта текущий без города (столбец создан с помощью Power Query)]],Таблица3[],4,0),0))),0) -> 170 | W36: МТС Коннект-4 | X36: =IF(выгрузка__22[[#This Row],[Дата активации]]<>0,IF(выгрузка__22[[#This Row],[Дата блокировки]]<>"",CEILING((выгрузка__22[[#This Row],[Дата блокировки]]-выгрузка__22[[#This Row],[Дата активации]])/30,1),0),0) -> 0 | Y36: =IF(выгрузка__22[[#This Row],[Дата блокировки]]<>"",1,0) -> 0
A37: 41593.589 | B37: 916512 | C37: 1698253 | D37: 41586.802 | E37: =IF(выгрузка__22[[#This Row],[Дата активации]]<>"",MONTH(выгрузка__22[[#This Row],[Дата активации]]),0) -> 11 | F37: 41591.999 | G37: 64626 | H37: Непрофильный | I37: Ярославль | J37: - Супер МТС. Область (МАСС) (SCP) | K37: 30 | L37: 0 | M37: 30 | N37: Активен | P37: Супер МТС. Область (МАСС) (SCP) | Q37: =IF(AND(DAY(выгрузка__22[[#This Row],[Дата отправки смс]])>=1,DAY(выгрузка__22[[#This Row],[Дата отправки смс]])<=14,MONTH(выгрузка__22[[#This Row],[Дата отправки смс]])=10),1,0) -> 0 | R37: =IF(выгрузка__22[[#This Row],[Дата регистрации]]="",0,1) -> 1 | S37: =IF(ISNA(VLOOKUP(выгрузка__22[[#This Row],[ЛС дилера]],'дилеры участники'!A:A,1,0)),0,1) -> 0 | T37: =IF(ISNA(VLOOKUP(выгрузка__22[[#This Row],[ТП комплекта текущий без города (столбец создан с помощью Power Query)]],Таблица3[Название ТП комплекта],1,0)),0,1) -> 1 | U37: =IF(ISNA(IF(выгрузка__22[[#This Row],[Канал продажи]]="Непрофильный",VLOOKUP(выгрузка__22[[#This Row],[ТП комплекта текущий без города (столбец создан с помощью Power Query)]],Таблица3[[Название ТП комплекта]:[Непрофильный]],3,0),VLOOKUP(выгрузка__22[[#This Row],[ТП комплекта текущий без города (столбец создан с помощью Power Query)]],Таблица3[[Название ТП комплекта]:[Непрофильный]],2,0)))=FALSE,1,0) -> 1 | V37: =IF(T37=1,IF(выгрузка__22[[#This Row],[Сумма дополнительного платежа и стартового баланса]]>300,VLOOKUP(выгрузка__22[[#This Row],[ТП комплекта текущий без города (столбец создан с помощью Power Query)]],Таблица3[],6,0),IF(выгрузка__22[[#This Row],[Сумма дополнительного платежа и стартового баланса]]>200,VLOOKUP(выгрузка__22[[#This Row],[ТП комплекта текущий без города (столбец создан с помощью Power Query)]],Таблица3[],5,0),IF(выгрузка__22[[#This Row],[Сумма дополнительного платежа и стартового баланса]]>100,VLOOKUP(выгрузка__22[[#This Row],[ТП комплекта текущий без города (столбец создан с помощью Power Query)]],Таблица3[],4,0),0))),0) -> 0 | W37: Супер МТС. Область | X37: =IF(выгрузка__22[[#This Row],[Дата активации]]<>0,IF(выгрузка__22[[#This Row],[Дата блокировки]]<>"",CEILING((выгрузка__22[[#This Row],[Дата блокировки]]-выгрузка__22[[#This Row],[Дата активации]])/30,1),0),0) -> 0 | Y37: =IF(выгрузка__22[[#This Row],[Дата блокировки]]<>"",1,0) -> 0
A38: 41593.505 | B38: 916513 | C38: 1755130 | D38: 41586.743 | E38: =IF(выгрузка__22[[#This Row],[Дата активации]]<>"",MONTH(выгрузка__22[[#This Row],[Дата активации]]),0) -> 11 | F38: 41591.842 | G38: 64626 | H38: Непрофильный | I38: Ярославль | J38: - МТС Коннект-4 (МАСС) (SCP) | K38: 30 | L38: 0 | M38: 30 | N38: Активен | P38: МТС Коннект-4 (МАСС) (SCP) | Q38: =IF(AND(DAY(выгрузка__22[[#This Row],[Дата отправки смс]])>=1,DAY(выгрузка__22[[#This Row],[Дата отправки смс]])<=14,MONTH(выгрузка__22[[#This Row],[Дата отправки смс]])=10),1,0) -> 0 | R38: =IF(выгрузка__22[[#This Row],[Дата регистрации]]="",0,1) -> 1 | S38: =IF(ISNA(VLOOKUP(выгрузка__22[[#This Row],[ЛС дилера]],'дилеры участники'!A:A,1,0)),0,1) -> 0 | T38: =IF(ISNA(VLOOKUP(выгрузка__22[[#This Row],[ТП комплекта текущий без города (столбец создан с помощью Power Query)]],Таблица3[Название ТП комплекта],1,0)),0,1) -> 1 | U38: =IF(ISNA(IF(выгрузка__22[[#This Row],[Канал продажи]]="Непрофильный",VLOOKUP(выгрузка__22[[#This Row],[ТП комплекта текущий без города (столбец создан с помощью Power Query)]],Таблица3[[Название ТП комплекта]:[Непрофильный]],3,0),VLOOKUP(выгрузка__22[[#This Row],[ТП комплекта текущий без города (столбец создан с помощью Power Query)]],Таблица3[[Название ТП комплекта]:[Непрофильный]],2,0)))=FALSE,1,0) -> 1 | V38: =IF(T38=1,IF(выгрузка__22[[#This Row],[Сумма дополнительного платежа и стартового баланса]]>300,VLOOKUP(выгрузка__22[[#This Row],[ТП комплекта текущий без города (столбец создан с помощью Power Query)]],Таблица3[],6,0),IF(выгрузка__22[[#This Row],[Сумма дополнительного платежа и стартового баланса]]>200,VLOOKUP(выгрузка__22[[#This Row],[ТП комплекта текущий без города (столбец создан с помощью Power Query)]],Таблица3[],5,0),IF(выгрузка__22[[#This Row],[Сумма дополнительного платежа и стартового баланса]]>100,VLOOKUP(выгрузка__22[[#This Row],[ТП комплекта текущий без города (столбец создан с помощью Power Query)]],Таблица3[],4,0),0))),0) -> 0 | W38: МТС Коннект-4 | X38: =IF(выгрузка__22[[#This Row],[Дата активации]]<>0,IF(выгрузка__22[[#This Row],[Дата блокировки]]<>"",CEILING((выгрузка__22[[#This Row],[Дата блокировки]]-выгрузка__22[[#This Row],[Дата активации]])/30,1),0),0) -> 0 | Y38: =IF(выгрузка__22[[#This Row],[Дата блокировки]]<>"",1,0) -> 0
... A41: 41593.589 | B41: 916512 | C41: 1698229 | D41: 41586.385 | E41: =IF(выгрузка__22[[#This Row],[Дата активации]]<>"",MONTH(выгрузка__22[[#This Row],[Дата активации]]),0) -> 11 | F41: 41587.462 | G41: 64626 | H41: Непрофильный | I41: Ярославль | J41: - Супер МТС. Область (МАСС) (SCP) | K41: 30 | L41: 0 | M41: 30 | N41: Активен | P41: Супер МТС. Область (МАСС) (SCP) | Q41: =IF(AND(DAY(выгрузка__22[[#This Row],[Дата отправки смс]])>=1,DAY(выгрузка__22[[#This Row],[Дата отправки смс]])<=14,MONTH(выгрузка__22[[#This Row],[Дата отправки смс]])=10),1,0) -> 0 | R41: =IF(выгрузка__22[[#This Row],[Дата регистрации]]="",0,1) -> 1 | S41: =IF(ISNA(VLOOKUP(выгрузка__22[[#This Row],[ЛС дилера]],'дилеры участники'!A:A,1,0)),0,1) -> 0 | T41: =IF(ISNA(VLOOKUP(выгрузка__22[[#This Row],[ТП комплекта текущий без города (столбец создан с помощью Power Query)]],Таблица3[Название ТП комплекта],1,0)),0,1) -> 1 | U41: =IF(ISNA(IF(выгрузка__22[[#This Row],[Канал продажи]]="Непрофильный",VLOOKUP(выгрузка__22[[#This Row],[ТП комплекта текущий без города (столбец создан с помощью Power Query)]],Таблица3[[Название ТП комплекта]:[Непрофильный]],3,0),VLOOKUP(выгрузка__22[[#This Row],[ТП комплекта текущий без города (столбец создан с помощью Power Query)]],Таблица3[[Название ТП комплекта]:[Непрофильный]],2,0)))=FALSE,1,0) -> 1 | V41: =IF(T41=1,IF(выгрузка__22[[#This Row],[Сумма дополнительного платежа и стартового баланса]]>300,VLOOKUP(выгрузка__22[[#This Row],[ТП комплекта текущий без города (столбец создан с помощью Power Query)]],Таблица3[],6,0),IF(выгрузка__22[[#This Row],[Сумма дополнительного платежа и стартового баланса]]>200,VLOOKUP(выгрузка__22[[#This Row],[ТП комплекта текущий без города (столбец создан с помощью Power Query)]],Таблица3[],5,0),IF(выгрузка__22[[#This Row],[Сумма дополнительного платежа и стартового баланса]]>100,VLOOKUP(выгрузка__22[[#This Row],[ТП комплекта текущий без города (столбец создан с помощью Power Query)]],Таблица3[],4,0),0))),0) -> 0 | W41: Супер МТС. Область | X41: =IF(выгрузка__22[[#This Row],[Дата активации]]<>0,IF(выгрузка__22[[#This Row],[Дата блокировки]]<>"",CEILING((выгрузка__22[[#This Row],[Дата блокировки]]-выгрузка__22[[#This Row],[Дата активации]])/30,1),0),0) -> 0 | Y41: =IF(выгрузка__22[[#This Row],[Дата блокировки]]<>"",1,0) -> 0
A42: 41588.508 | B42: 985648 | C42: 8524580 | D42: 41586.03 | E42: =IF(выгрузка__22[[#This Row],[Дата активации]]<>"",MONTH(выгрузка__22[[#This Row],[Дата активации]]),0) -> 11 | G42: 73902 | H42: Непрофильный | I42: Тверь | J42: - МТС Коннект-4 (МАСС) (SCP) | K42: 949 | L42: 0 | M42: 949 | N42: Активен | P42: МТС Коннект-4 (МАСС) (SCP) | Q42: =IF(AND(DAY(выгрузка__22[[#This Row],[Дата отправки смс]])>=1,DAY(выгрузка__22[[#This Row],[Дата отправки смс]])<=14,MONTH(выгрузка__22[[#This Row],[Дата отправки смс]])=10),1,0) -> 0 | R42: =IF(выгрузка__22[[#This Row],[Дата регистрации]]="",0,1) -> 0 | S42: =IF(ISNA(VLOOKUP(выгрузка__22[[#This Row],[ЛС дилера]],'дилеры участники'!A:A,1,0)),0,1) -> 0 | T42: =IF(ISNA(VLOOKUP(выгрузка__22[[#This Row],[ТП комплекта текущий без города (столбец создан с помощью Power Query)]],Таблица3[Название ТП комплекта],1,0)),0,1) -> 1 | U42: =IF(ISNA(IF(выгрузка__22[[#This Row],[Канал продажи]]="Непрофильный",VLOOKUP(выгрузка__22[[#This Row],[ТП комплекта текущий без города (столбец создан с помощью Power Query)]],Таблица3[[Название ТП комплекта]:[Непрофильный]],3,0),VLOOKUP(выгрузка__22[[#This Row],[ТП комплекта текущий без города (столбец создан с помощью Power Query)]],Таблица3[[Название ТП комплекта]:[Непрофильный]],2,0)))=FALSE,1,0) -> 1 | V42: =IF(T42=1,IF(выгрузка__22[[#This Row],[Сумма дополнительного платежа и стартового баланса]]>300,VLOOKUP(выгрузка__22[[#This Row],[ТП комплекта текущий без города (столбец создан с помощью Power Query)]],Таблица3[],6,0),IF(выгрузка__22[[#This Row],[Сумма дополнительного платежа и стартового баланса]]>200,VLOOKUP(выгрузка__22[[#This Row],[ТП комплекта текущий без города (столбец создан с помощью Power Query)]],Таблица3[],5,0),IF(выгрузка__22[[#This Row],[Сумма дополнительного платежа и стартового баланса]]>100,VLOOKUP(выгрузка__22[[#This Row],[ТП комплекта текущий без города (столбец создан с помощью Power Query)]],Таблица3[],4,0),0))),0) -> 170 | W42: МТС Коннект-4 | X42: =IF(выгрузка__22[[#This Row],[Дата активации]]<>0,IF(выгрузка__22[[#This Row],[Дата блокировки]]<>"",CEILING((выгрузка__22[[#This Row],[Дата блокировки]]-выгрузка__22[[#This Row],[Дата активации]])/30,1),0),0) -> 0 | Y42: =IF(выгрузка__22[[#This Row],[Дата блокировки]]<>"",1,0) -> 0
A43: 41588.945 | B43: 910483 | C43: 1698748 | D43: 41585.98 | E43: =IF(выгрузка__22[[#This Row],[Дата активации]]<>"",MONTH(выгрузка__22[[#This Row],[Дата активации]]),0) -> 11 | G43: 64626 | H43: Непрофильный | I43: Тверь | J43: - Супер МТС (МАСС) (SCP) | K43: 1 | L43: 0 | M43: 1 | N43: Активен | P43: Супер МТС (МАСС) (SCP) | Q43: =IF(AND(DAY(выгрузка__22[[#This Row],[Дата отправки смс]])>=1,DAY(выгрузка__22[[#This Row],[Дата отправки смс]])<=14,MONTH(выгрузка__22[[#This Row],[Дата отправки смс]])=10),1,0) -> 0 | R43: =IF(выгрузка__22[[#This Row],[Дата регистрации]]="",0,1) -> 0 | S43: =IF(ISNA(VLOOKUP(выгрузка__22[[#This Row],[ЛС дилера]],'дилеры участники'!A:A,1,0)),0,1) -> 0 | T43: =IF(ISNA(VLOOKUP(выгрузка__22[[#This Row],[ТП комплекта текущий без города (столбец создан с помощью Power Query)]],Таблица3[Название ТП комплекта],1,0)),0,1) -> 1 | U43: =IF(ISNA(IF(выгрузка__22[[#This Row],[Канал продажи]]="Непрофильный",VLOOKUP(выгрузка__22[[#This Row],[ТП комплекта текущий без города (столбец создан с помощью Power Query)]],Таблица3[[Название ТП комплекта]:[Непрофильный]],3,0),VLOOKUP(выгрузка__22[[#This Row],[ТП комплекта текущий без города (столбец создан с помощью Power Query)]],Таблица3[[Название ТП комплекта]:[Непрофильный]],2,0)))=FALSE,1,0) -> 1 | V43: =IF(T43=1,IF(выгрузка__22[[#This Row],[Сумма дополнительного платежа и стартового баланса]]>300,VLOOKUP(выгрузка__22[[#This Row],[ТП комплекта текущий без города (столбец создан с помощью Power Query)]],Таблица3[],6,0),IF(выгрузка__22[[#This Row],[Сумма дополнительного платежа и стартового баланса]]>200,VLOOKUP(выгрузка__22[[#This Row],[ТП комплекта текущий без города (столбец создан с помощью Power Query)]],Таблица3[],5,0),IF(выгрузка__22[[#This Row],[Сумма дополнительного платежа и стартового баланса]]>100,VLOOKUP(выгрузка__22[[#This Row],[ТП комплекта текущий без города (столбец создан с помощью Power Query)]],Таблица3[],4,0),0))),0) -> 0 | W43: Супер МТС | X43: =IF(выгрузка__22[[#This Row],[Дата активации]]<>0,IF(выгрузка__22[[#This Row],[Дата блокировки]]<>"",CEILING((выгрузка__22[[#This Row],[Дата блокировки]]-выгрузка__22[[#This Row],[Дата активации]])/30,1),0),0) -> 0 | Y43: =IF(выгрузка__22[[#This Row],[Дата блокировки]]<>"",1,0) -> 0
A44: 41593.6 | B44: 916888 | C44: 1753349 | D44: 41585.923 | E44: =IF(выгрузка__22[[#This Row],[Дата активации]]<>"",MONTH(выгрузка__22[[#This Row],[Дата активации]]),0) -> 11 | F44: 41586.974 | G44: 64626 | H44: Непрофильный | I44: Ярославль | J44: - Супер МТС. Область (МАСС) (SCP) | K44: 30 | L44: 0 | M44: 30 | N44: Активен | P44: Супер МТС. Область (МАСС) (SCP) | Q44: =IF(AND(DAY(выгрузка__22[[#This Row],[Дата отправки смс]])>=1,DAY(выгрузка__22[[#This Row],[Дата отправки смс]])<=14,MONTH(выгрузка__22[[#This Row],[Дата отправки смс]])=10),1,0) -> 0 | R44: =IF(выгрузка__22[[#This Row],[Дата регистрации]]="",0,1) -> 1 | S44: =IF(ISNA(VLOOKUP(выгрузка__22[[#This Row],[ЛС дилера]],'дилеры участники'!A:A,1,0)),0,1) -> 0 | T44: =IF(ISNA(VLOOKUP(выгрузка__22[[#This Row],[ТП комплекта текущий без города (столбец создан с помощью Power Query)]],Таблица3[Название ТП комплекта],1,0)),0,1) -> 1 | U44: =IF(ISNA(IF(выгрузка__22[[#This Row],[Канал продажи]]="Непрофильный",VLOOKUP(выгрузка__22[[#This Row],[ТП комплекта текущий без города (столбец создан с помощью Power Query)]],Таблица3[[Название ТП комплекта]:[Непрофильный]],3,0),VLOOKUP(выгрузка__22[[#This Row],[ТП комплекта текущий без города (столбец создан с помощью Power Query)]],Таблица3[[Название ТП комплекта]:[Непрофильный]],2,0)))=FALSE,1,0) -> 1 | V44: =IF(T44=1,IF(выгрузка__22[[#This Row],[Сумма дополнительного платежа и стартового баланса]]>300,VLOOKUP(выгрузка__22[[#This Row],[ТП комплекта текущий без города (столбец создан с помощью Power Query)]],Таблица3[],6,0),IF(выгрузка__22[[#This Row],[Сумма дополнительного платежа и стартового баланса]]>200,VLOOKUP(выгрузка__22[[#This Row],[ТП комплекта текущий без города (столбец создан с помощью Power Query)]],Таблица3[],5,0),IF(выгрузка__22[[#This Row],[Сумма дополнительного платежа и стартового баланса]]>100,VLOOKUP(выгрузка__22[[#This Row],[ТП комплекта текущий без города (столбец создан с помощью Power Query)]],Таблица3[],4,0),0))),0) -> 0 | W44: Супер МТС. Область | X44: =IF(выгрузка__22[[#This Row],[Дата активации]]<>0,IF(выгрузка__22[[#This Row],[Дата блокировки]]<>"",CEILING((выгрузка__22[[#This Row],[Дата блокировки]]-выгрузка__22[[#This Row],[Дата активации]])/30,1),0),0) -> 0 | Y44: =IF(выгрузка__22[[#This Row],[Дата блокировки]]<>"",1,0) -> 0
A45: 41593.596 | B45: 916888 | C45: 1698642 | D45: 41585.911 | E45: =IF(выгрузка__22[[#This Row],[Дата активации]]<>"",MONTH(выгрузка__22[[#This Row],[Дата активации]]),0) -> 11 | F45: 41587.131 | G45: 64626 | H45: Непрофильный | I45: Ярославль | J45: - Супер МТС. Область (МАСС) (SCP) | K45: 30 | L45: 0 | M45: 30 | N45: Активен | P45: Супер МТС. Область (МАСС) (SCP) | Q45: =IF(AND(DAY(выгрузка__22[[#This Row],[Дата отправки смс]])>=1,DAY(выгрузка__22[[#This Row],[Дата отправки смс]])<=14,MONTH(выгрузка__22[[#This Row],[Дата отправки смс]])=10),1,0) -> 0 | R45: =IF(выгрузка__22[[#This Row],[Дата регистрации]]="",0,1) -> 1 | S45: =IF(ISNA(VLOOKUP(выгрузка__22[[#This Row],[ЛС дилера]],'дилеры участники'!A:A,1,0)),0,1) -> 0 | T45: =IF(ISNA(VLOOKUP(выгрузка__22[[#This Row],[ТП комплекта текущий без города (столбец создан с помощью Power Query)]],Таблица3[Название ТП комплекта],1,0)),0,1) -> 1 | U45: =IF(ISNA(IF(выгрузка__22[[#This Row],[Канал продажи]]="Непрофильный",VLOOKUP(выгрузка__22[[#This Row],[ТП комплекта текущий без города (столбец создан с помощью Power Query)]],Таблица3[[Название ТП комплекта]:[Непрофильный]],3,0),VLOOKUP(выгрузка__22[[#This Row],[ТП комплекта текущий без города (столбец создан с помощью Power Query)]],Таблица3[[Название ТП комплекта]:[Непрофильный]],2,0)))=FALSE,1,0) -> 1 | V45: =IF(T45=1,IF(выгрузка__22[[#This Row],[Сумма дополнительного платежа и стартового баланса]]>300,VLOOKUP(выгрузка__22[[#This Row],[ТП комплекта текущий без города (столбец создан с помощью Power Query)]],Таблица3[],6,0),IF(выгрузка__22[[#This Row],[Сумма дополнительного платежа и стартового баланса]]>200,VLOOKUP(выгрузка__22[[#This Row],[ТП комплекта текущий без города (столбец создан с помощью Power Query)]],Таблица3[],5,0),IF(выгрузка__22[[#This Row],[Сумма дополнительного платежа и стартового баланса]]>100,VLOOKUP(выгрузка__22[[#This Row],[ТП комплекта текущий без города (столбец создан с помощью Power Query)]],Таблица3[],4,0),0))),0) -> 0 | W45: Супер МТС. Область | X45: =IF(выгрузка__22[[#This Row],[Дата активации]]<>0,IF(выгрузка__22[[#This Row],[Дата блокировки]]<>"",CEILING((выгрузка__22[[#This Row],[Дата блокировки]]-выгрузка__22[[#This Row],[Дата активации]])/30,1),0),0) -> 0 | Y45: =IF(выгрузка__22[[#This Row],[Дата блокировки]]<>"",1,0) -> 0
A46: 41593.59 | B46: 916512 | C46: 1698561 | D46: 41585.884 | E46: =IF(выгрузка__22[[#This Row],[Дата активации]]<>"",MONTH(выгрузка__22[[#This Row],[Дата активации]]),0) -> 11 | F46: 41587.13 | G46: 64626 | H46: Непрофильный | I46: Ярославль | J46: - Супер МТС. Область (МАСС) (SCP) | K46: 30 | L46: 0 | M46: 30 | N46: Активен | P46: Супер МТС. Область (МАСС) (SCP) | Q46: =IF(AND(DAY(выгрузка__22[[#This Row],[Дата отправки смс]])>=1,DAY(выгрузка__22[[#This Row],[Дата отправки смс]])<=14,MONTH(выгрузка__22[[#This Row],[Дата отправки смс]])=10),1,0) -> 0 | R46: =IF(выгрузка__22[[#This Row],[Дата регистрации]]="",0,1) -> 1 | S46: =IF(ISNA(VLOOKUP(выгрузка__22[[#This Row],[ЛС дилера]],'дилеры участники'!A:A,1,0)),0,1) -> 0 | T46: =IF(ISNA(VLOOKUP(выгрузка__22[[#This Row],[ТП комплекта текущий без города (столбец создан с помощью Power Query)]],Таблица3[Название ТП комплекта],1,0)),0,1) -> 1 | U46: =IF(ISNA(IF(выгрузка__22[[#This Row],[Канал продажи]]="Непрофильный",VLOOKUP(выгрузка__22[[#This Row],[ТП комплекта текущий без города (столбец создан с помощью Power Query)]],Таблица3[[Название ТП комплекта]:[Непрофильный]],3,0),VLOOKUP(выгрузка__22[[#This Row],[ТП комплекта текущий без города (столбец создан с помощью Power Query)]],Таблица3[[Название ТП комплекта]:[Непрофильный]],2,0)))=FALSE,1,0) -> 1 | V46: =IF(T46=1,IF(выгрузка__22[[#This Row],[Сумма дополнительного платежа и стартового баланса]]>300,VLOOKUP(выгрузка__22[[#This Row],[ТП комплекта текущий без города (столбец создан с помощью Power Query)]],Таблица3[],6,0),IF(выгрузка__22[[#This Row],[Сумма дополнительного платежа и стартового баланса]]>200,VLOOKUP(выгрузка__22[[#This Row],[ТП комплекта текущий без города (столбец создан с помощью Power Query)]],Таблица3[],5,0),IF(выгрузка__22[[#This Row],[Сумма дополнительного платежа и стартового баланса]]>100,VLOOKUP(выгрузка__22[[#This Row],[ТП комплекта текущий без города (столбец создан с помощью Power Query)]],Таблица3[],4,0),0))),0) -> 0 | W46: Супер МТС. Область | X46: =IF(выгрузка__22[[#This Row],[Дата активации]]<>0,IF(выгрузка__22[[#This Row],[Дата блокировки]]<>"",CEILING((выгрузка__22[[#This Row],[Дата блокировки]]-выгрузка__22[[#This Row],[Дата активации]])/30,1),0),0) -> 0 | Y46: =IF(выгрузка__22[[#This Row],[Дата блокировки]]<>"",1,0) -> 0
A47: 41593.592 | B47: 916512 | C47: 1698606 | D47: 41585.861 | E47: =IF(выгрузка__22[[#This Row],[Дата активации]]<>"",MONTH(выгрузка__22[[#This Row],[Дата активации]]),0) -> 11 | F47: 41587.317 | G47: 64626 | H47: Непрофильный | I47: Ярославль | J47: - Супер МТС. Область (МАСС) (SCP) | K47: 30 | L47: 0 | M47: 30 | N47: Активен | P47: Супер МТС. Область (МАСС) (SCP) | Q47: =IF(AND(DAY(выгрузка__22[[#This Row],[Дата отправки смс]])>=1,DAY(выгрузка__22[[#This Row],[Дата отправки смс]])<=14,MONTH(выгрузка__22[[#This Row],[Дата отправки смс]])=10),1,0) -> 0 | R47: =IF(выгрузка__22[[#This Row],[Дата регистрации]]="",0,1) -> 1 | S47: =IF(ISNA(VLOOKUP(выгрузка__22[[#This Row],[ЛС дилера]],'дилеры участники'!A:A,1,0)),0,1) -> 0 | T47: =IF(ISNA(VLOOKUP(выгрузка__22[[#This Row],[ТП комплекта текущий без города (столбец создан с помощью Power Query)]],Таблица3[Название ТП комплекта],1,0)),0,1) -> 1 | U47: =IF(ISNA(IF(выгрузка__22[[#This Row],[Канал продажи]]="Непрофильный",VLOOKUP(выгрузка__22[[#This Row],[ТП комплекта текущий без города (столбец создан с помощью Power Query)]],Таблица3[[Название ТП комплекта]:[Непрофильный]],3,0),VLOOKUP(выгрузка__22[[#This Row],[ТП комплекта текущий без города (столбец создан с помощью Power Query)]],Таблица3[[Название ТП комплекта]:[Непрофильный]],2,0)))=FALSE,1,0) -> 1 | V47: =IF(T47=1,IF(выгрузка__22[[#This Row],[Сумма дополнительного платежа и стартового баланса]]>300,VLOOKUP(выгрузка__22[[#This Row],[ТП комплекта текущий без города (столбец создан с помощью Power Query)]],Таблица3[],6,0),IF(выгрузка__22[[#This Row],[Сумма дополнительного платежа и стартового баланса]]>200,VLOOKUP(выгрузка__22[[#This Row],[ТП комплекта текущий без города (столбец создан с помощью Power Query)]],Таблица3[],5,0),IF(выгрузка__22[[#This Row],[Сумма дополнительного платежа и стартового баланса]]>100,VLOOKUP(выгрузка__22[[#This Row],[ТП комплекта текущий без города (столбец создан с помощью Power Query)]],Таблица3[],4,0),0))),0) -> 0 | W47: Супер МТС. Область | X47: =IF(выгрузка__22[[#This Row],[Дата активации]]<>0,IF(выгрузка__22[[#This Row],[Дата блокировки]]<>"",CEILING((выгрузка__22[[#This Row],[Дата блокировки]]-выгрузка__22[[#This Row],[Дата активации]])/30,1),0),0) -> 0 | Y47: =IF(выгрузка__22[[#This Row],[Дата блокировки]]<>"",1,0) -> 0
A48: 41588.487 | B48: 916527 | C48: 1754812 | D48: 41585.826 | E48: =IF(выгрузка__22[[#This Row],[Дата активации]]<>"",MONTH(выгрузка__22[[#This Row],[Дата активации]]),0) -> 11 | G48: 64626 | H48: Непрофильный | I48: Тверь | J48: - Супер МТС (МАСС) (SCP) | K48: 30 | L48: 0 | M48: 30 | N48: Активен | P48: Супер МТС (МАСС) (SCP) | Q48: =IF(AND(DAY(выгрузка__22[[#This Row],[Дата отправки смс]])>=1,DAY(выгрузка__22[[#This Row],[Дата отправки смс]])<=14,MONTH(выгрузка__22[[#This Row],[Дата отправки смс]])=10),1,0) -> 0 | R48: =IF(выгрузка__22[[#This Row],[Дата регистрации]]="",0,1) -> 0 | S48: =IF(ISNA(VLOOKUP(выгрузка__22[[#This Row],[ЛС дилера]],'дилеры участники'!A:A,1,0)),0,1) -> 0 | T48: =IF(ISNA(VLOOKUP(выгрузка__22[[#This Row],[ТП комплекта текущий без города (столбец создан с помощью Power Query)]],Таблица3[Название ТП комплекта],1,0)),0,1) -> 1 | U48: =IF(ISNA(IF(выгрузка__22[[#This Row],[Канал продажи]]="Непрофильный",VLOOKUP(выгрузка__22[[#This Row],[ТП комплекта текущий без города (столбец создан с помощью Power Query)]],Таблица3[[Название ТП комплекта]:[Непрофильный]],3,0),VLOOKUP(выгрузка__22[[#This Row],[ТП комплекта текущий без города (столбец создан с помощью Power Query)]],Таблица3[[Название ТП комплекта]:[Непрофильный]],2,0)))=FALSE,1,0) -> 1 | V48: =IF(T48=1,IF(выгрузка__22[[#This Row],[Сумма дополнительного платежа и стартового баланса]]>300,VLOOKUP(выгрузка__22[[#This Row],[ТП комплекта текущий без города (столбец создан с помощью Power Query)]],Таблица3[],6,0),IF(выгрузка__22[[#This Row],[Сумма дополнительного платежа и стартового баланса]]>200,VLOOKUP(выгрузка__22[[#This Row],[ТП комплекта текущий без города (столбец создан с помощью Power Query)]],Таблица3[],5,0),IF(выгрузка__22[[#This Row],[Сумма дополнительного платежа и стартового баланса]]>100,VLOOKUP(выгрузка__22[[#This Row],[ТП комплекта текущий без города (столбец создан с помощью Power Query)]],Таблица3[],4,0),0))),0) -> 0 | W48: Супер МТС | X48: =IF(выгрузка__22[[#This Row],[Дата активации]]<>0,IF(выгрузка__22[[#This Row],[Дата блокировки]]<>"",CEILING((выгрузка__22[[#This Row],[Дата блокировки]]-выгрузка__22[[#This Row],[Дата активации]])/30,1),0),0) -> 0 | Y48: =IF(выгрузка__22[[#This Row],[Дата блокировки]]<>"",1,0) -> 0
A49: 41593.599 | B49: 916888 | C49: 1699529 | D49: 41585.724 | E49: =IF(выгрузка__22[[#This Row],[Дата активации]]<>"",MONTH(выгрузка__22[[#This Row],[Дата активации]]),0) -> 11 | F49: 41586.973 | G49: 64626 | H49: Непрофильный | I49: Ярославль | J49: - Супер МТС (МАСС) (SCP) | K49: 30 | L49: 210 | M49: 240 | N49: Активен | P49: Супер МТС (МАСС) (SCP) | Q49: =IF(AND(DAY(выгрузка__22[[#This Row],[Дата отправки смс]])>=1,DAY(выгрузка__22[[#This Row],[Дата отправки смс]])<=14,MONTH(выгрузка__22[[#This Row],[Дата отправки смс]])=10),1,0) -> 0 | R49: =IF(выгрузка__22[[#This Row],[Дата регистрации]]="",0,1) -> 1 | S49: =IF(ISNA(VLOOKUP(выгрузка__22[[#This Row],[ЛС дилера]],'дилеры участники'!A:A,1,0)),0,1) -> 0 | T49: =IF(ISNA(VLOOKUP(выгрузка__22[[#This Row],[ТП комплекта текущий без города (столбец создан с помощью Power Query)]],Таблица3[Название ТП комплекта],1,0)),0,1) -> 1 | U49: =IF(ISNA(IF(выгрузка__22[[#This Row],[Канал продажи]]="Непрофильный",VLOOKUP(выгрузка__22[[#This Row],[ТП комплекта текущий без города (столбец создан с помощью Power Query)]],Таблица3[[Название ТП комплекта]:[Непрофильный]],3,0),VLOOKUP(выгрузка__22[[#This Row],[ТП комплекта текущий без города (столбец создан с помощью Power Query)]],Таблица3[[Название ТП комплекта]:[Непрофильный]],2,0)))=FALSE,1,0) -> 1 | V49: =IF(T49=1,IF(выгрузка__22[[#This Row],[Сумма дополнительного платежа и стартового баланса]]>300,VLOOKUP(выгрузка__22[[#This Row],[ТП комплекта текущий без города (столбец создан с помощью Power Query)]],Таблица3[],6,0),IF(выгрузка__22[[#This Row],[Сумма дополнительного платежа и стартового баланса]]>200,VLOOKUP(выгрузка__22[[#This Row],[ТП комплекта текущий без города (столбец создан с помощью Power Query)]],Таблица3[],5,0),IF(выгрузка__22[[#This Row],[Сумма дополнительного платежа и стартового баланса]]>100,VLOOKUP(выгрузка__22[[#This Row],[ТП комплекта текущий без города (столбец создан с помощью Power Query)]],Таблица3[],4,0),0))),0) -> 70 | W49: Супер МТС | X49: =IF(выгрузка__22[[#This Row],[Дата активации]]<>0,IF(выгрузка__22[[#This Row],[Дата блокировки]]<>"",CEILING((выгрузка__22[[#This Row],[Дата блокировки]]-выгрузка__22[[#This Row],[Дата активации]])/30,1),0),0) -> 0 | Y49: =IF(выгрузка__22[[#This Row],[Дата блокировки]]<>"",1,0) -> 0
A50: 41593.749 | B50: 915322 | C50: 8526222 | D50: 41585.717 | E50: =IF(выгрузка__22[[#This Row],[Дата активации]]<>"",MONTH(выгрузка__22[[#This Row],[Дата активации]]),0) -> 11 | F50: 41588.722 | G50: 57078 | H50: Локальный | I50: Ярославль | J50: - Супер МТС. Область (МАСС) (SCP) | K50: 90 | L50: 0 | M50: 90 | N50: Активен | P50: Супер МТС. Область (МАСС) (SCP) | Q50: =IF(AND(DAY(выгрузка__22[[#This Row],[Дата отправки смс]])>=1,DAY(выгрузка__22[[#This Row],[Дата отправки смс]])<=14,MONTH(выгрузка__22[[#This Row],[Дата отправки смс]])=10),1,0) -> 0 | R50: =IF(выгрузка__22[[#This Row],[Дата регистрации]]="",0,1) -> 1 | S50: =IF(ISNA(VLOOKUP(выгрузка__22[[#This Row],[ЛС дилера]],'дилеры участники'!A:A,1,0)),0,1) -> 1 | T50: =IF(ISNA(VLOOKUP(выгрузка__22[[#This Row],[ТП комплекта текущий без города (столбец создан с помощью Power Query)]],Таблица3[Название ТП комплекта],1,0)),0,1) -> 1 | U50: =IF(ISNA(IF(выгрузка__22[[#This Row],[Канал продажи]]="Непрофильный",VLOOKUP(выгрузка__22[[#This Row],[ТП комплекта текущий без города (столбец создан с помощью Power Query)]],Таблица3[[Название ТП комплекта]:[Непрофильный]],3,0),VLOOKUP(выгрузка__22[[#This Row],[ТП комплекта текущий без города (столбец создан с помощью Power Query)]],Таблица3[[Название ТП комплекта]:[Непрофильный]],2,0)))=FALSE,1,0) -> 1 | V50: =IF(T50=1,IF(выгрузка__22[[#This Row],[Сумма дополнительного платежа и стартового баланса]]>300,VLOOKUP(выгрузка__22[[#This Row],[ТП комплекта текущий без города (столбец создан с помощью Power Query)]],Таблица3[],6,0),IF(выгрузка__22[[#This Row],[Сумма дополнительного платежа и стартового баланса]]>200,VLOOKUP(выгрузка__22[[#This Row],[ТП комплекта текущий без города (столбец создан с помощью Power Query)]],Таблица3[],5,0),IF(выгрузка__22[[#This Row],[Сумма дополнительного платежа и стартового баланса]]>100,VLOOKUP(выгрузка__22[[#This Row],[ТП комплекта текущий без города (столбец создан с помощью Power Query)]],Таблица3[],4,0),0))),0) -> 0 | W50: Супер МТС. Область | X50: =IF(выгрузка__22[[#This Row],[Дата активации]]<>0,IF(выгрузка__22[[#This Row],[Дата блокировки]]<>"",CEILING((выгрузка__22[[#This Row],[Дата блокировки]]-выгрузка__22[[#This Row],[Дата активации]])/30,1),0),0) -> 0 | Y50: =IF(выгрузка__22[[#This Row],[Дата блокировки]]<>"",1,0) -> 0
A51: 41593.499 | B51: 985210 | C51: 8524672 | D51: 41585.563 | E51: =IF(выгрузка__22[[#This Row],[Дата активации]]<>"",MONTH(выгрузка__22[[#This Row],[Дата активации]]),0) -> 11 | F51: 41587.536 | G51: 64626 | H51: Непрофильный | I51: Ярославль | J51: - МТС Коннект-4 (МАСС) (SCP) | K51: 401 | L51: 0 | M51: 401 | N51: Активен | P51: МТС Коннект-4 (МАСС) (SCP) | Q51: =IF(AND(DAY(выгрузка__22[[#This Row],[Дата отправки смс]])>=1,DAY(выгрузка__22[[#This Row],[Дата отправки смс]])<=14,MONTH(выгрузка__22[[#This Row],[Дата отправки смс]])=10),1,0) -> 0 | R51: =IF(выгрузка__22[[#This Row],[Дата регистрации]]="",0,1) -> 1 | S51: =IF(ISNA(VLOOKUP(выгрузка__22[[#This Row],[ЛС дилера]],'дилеры участники'!A:A,1,0)),0,1) -> 0 | T51: =IF(ISNA(VLOOKUP(выгрузка__22[[#This Row],[ТП комплекта текущий без города (столбец создан с помощью Power Query)]],Таблица3[Название ТП комплекта],1,0)),0,1) -> 1 | U51: =IF(ISNA(IF(выгрузка__22[[#This Row],[Канал продажи]]="Непрофильный",VLOOKUP(выгрузка__22[[#This Row],[ТП комплекта текущий без города (столбец создан с помощью Power Query)]],Таблица3[[Название ТП комплекта]:[Непрофильный]],3,0),VLOOKUP(выгрузка__22[[#This Row],[ТП комплекта текущий без города (столбец создан с помощью Power Query)]],Таблица3[[Название ТП комплекта]:[Непрофильный]],2,0)))=FALSE,1,0) -> 1 | V51: =IF(T51=1,IF(выгрузка__22[[#This Row],[Сумма дополнительного платежа и стартового баланса]]>300,VLOOKUP(выгрузка__22[[#This Row],[ТП комплекта текущий без города (столбец создан с помощью Power Query)]],Таблица3[],6,0),IF(выгрузка__22[[#This Row],[Сумма дополнительного платежа и стартового баланса]]>200,VLOOKUP(выгрузка__22[[#This Row],[ТП комплекта текущий без города (столбец создан с помощью Power Query)]],Таблица3[],5,0),IF(выгрузка__22[[#This Row],[Сумма дополнительного платежа и стартового баланса]]>100,VLOOKUP(выгрузка__22[[#This Row],[ТП комплекта текущий без города (столбец создан с помощью Power Query)]],Таблица3[],4,0),0))),0) -> 170 | W51: МТС Коннект-4 | X51: =IF(выгрузка__22[[#This Row],[Дата активации]]<>0,IF(выгрузка__22[[#This Row],[Дата блокировки]]<>"",CEILING((выгрузка__22[[#This Row],[Дата блокировки]]-выгрузка__22[[#This Row],[Дата активации]])/30,1),0),0) -> 0 | Y51: =IF(выгрузка__22[[#This Row],[Дата блокировки]]<>"",1,0) -> 0
A52: 41588.617 | B52: 916361 | C52: 8523495 | D52: 41585.555 | E52: =IF(выгрузка__22[[#This Row],[Дата активации]]<>"",MONTH(выгрузка__22[[#This Row],[Дата активации]]),0) -> 11 | G52: 79956 | H52: Непрофильный | I52: Тверь | J52: - RED Energy (МАСС) (SCP) | K52: 30 | L52: 0 | M52: 30 | N52: Активен | P52: RED Energy (МАСС) (SCP) | Q52: =IF(AND(DAY(выгрузка__22[[#This Row],[Дата отправки смс]])>=1,DAY(выгрузка__22[[#This Row],[Дата отправки смс]])<=14,MONTH(выгрузка__22[[#This Row],[Дата отправки смс]])=10),1,0) -> 0 | R52: =IF(выгрузка__22[[#This Row],[Дата регистрации]]="",0,1) -> 0 | S52: =IF(ISNA(VLOOKUP(выгрузка__22[[#This Row],[ЛС дилера]],'дилеры участники'!A:A,1,0)),0,1) -> 1 | T52: =IF(ISNA(VLOOKUP(выгрузка__22[[#This Row],[ТП комплекта текущий без города (столбец создан с помощью Power Query)]],Таблица3[Название ТП комплекта],1,0)),0,1) -> 0 | U52: =IF(ISNA(IF(выгрузка__22[[#This Row],[Канал продажи]]="Непрофильный",VLOOKUP(выгрузка__22[[#This Row],[ТП комплекта текущий без города (столбец создан с помощью Power Query)]],Таблица3[[Название ТП комплекта]:[Непрофильный]],3,0),VLOOKUP(выгрузка__22[[#This Row],[ТП комплекта текущий без города (столбец создан с помощью Power Query)]],Таблица3[[Название ТП комплекта]:[Непрофильный]],2,0)))=FALSE,1,0) -> 0 | V52: =IF(T52=1,IF(выгрузка__22[[#This Row],[Сумма дополнительного платежа и стартового баланса]]>300,VLOOKUP(выгрузка__22[[#This Row],[ТП комплекта текущий без города (столбец создан с помощью Power Query)]],Таблица3[],6,0),IF(выгрузка__22[[#This Row],[Сумма дополнительного платежа и стартового баланса]]>200,VLOOKUP(выгрузка__22[[#This Row],[ТП комплекта текущий без города (столбец создан с помощью Power Query)]],Таблица3[],5,0),IF(выгрузка__22[[#This Row],[Сумма дополнительного платежа и стартового баланса]]>100,VLOOKUP(выгрузка__22[[#This Row],[ТП комплекта текущий без города (столбец создан с помощью Power Query)]],Таблица3[],4,0),0))),0) -> 0 | W52: RED Energy | X52: =IF(выгрузка__22[[#This Row],[Дата активации]]<>0,IF(выгрузка__22[[#This Row],[Дата блокировки]]<>"",CEILING((выгрузка__22[[#This Row],[Дата блокировки]]-выгрузка__22[[#This Row],[Дата активации]])/30,1),0),0) -> 0 | Y52: =IF(выгрузка__22[[#This Row],[Дата блокировки]]<>"",1,0) -> 0
A53: 41593.505 | B53: 916513 | C53: 1755043 | D53: 41585.423 | E53: =IF(выгрузка__22[[#This Row],[Дата активации]]<>"",MONTH(выгрузка__22[[#This Row],[Дата активации]]),0) -> 11 | F53: 41586.868 | G53: 64626 | H53: Непрофильный | I53: Ярославль | J53: - Smart mini (МАСС) (SCP) | K53: 30 | L53: 291 | M53: 321 | N53: Активен | P53: Smart mini (МАСС) (SCP) | Q53: =IF(AND(DAY(выгрузка__22[[#This Row],[Дата отправки смс]])>=1,DAY(выгрузка__22[[#This Row],[Дата отправки смс]])<=14,MONTH(выгрузка__22[[#This Row],[Дата отправки смс]])=10),1,0) -> 0 | R53: =IF(выгрузка__22[[#This Row],[Дата регистрации]]="",0,1) -> 1 | S53: =IF(ISNA(VLOOKUP(выгрузка__22[[#This Row],[ЛС дилера]],'дилеры участники'!A:A,1,0)),0,1) -> 0 | T53: =IF(ISNA(VLOOKUP(выгрузка__22[[#This Row],[ТП комплекта текущий без города (столбец создан с помощью Power Query)]],Таблица3[Название ТП комплекта],1,0)),0,1) -> 1 | U53: =IF(ISNA(IF(выгрузка__22[[#This Row],[Канал продажи]]="Непрофильный",VLOOKUP(выгрузка__22[[#This Row],[ТП комплекта текущий без города (столбец создан с помощью Power Query)]],Таблица3[[Название ТП комплекта]:[Непрофильный]],3,0),VLOOKUP(выгрузка__22[[#This Row],[ТП комплекта текущий без города (столбец создан с помощью Power Query)]],Таблица3[[Название ТП комплекта]:[Непрофильный]],2,0)))=FALSE,1,0) -> 1 | V53: =IF(T53=1,IF(выгрузка__22[[#This Row],[Сумма дополнительного платежа и стартового баланса]]>300,VLOOKUP(выгрузка__22[[#This Row],[ТП комплекта текущий без города (столбец создан с помощью Power Query)]],Таблица3[],6,0),IF(выгрузка__22[[#This Row],[Сумма дополнительного платежа и стартового баланса]]>200,VLOOKUP(выгрузка__22[[#This Row],[ТП комплекта текущий без города (столбец создан с помощью Power Query)]],Таблица3[],5,0),IF(выгрузка__22[[#This Row],[Сумма дополнительного платежа и стартового баланса]]>100,VLOOKUP(выгрузка__22[[#This Row],[ТП комплекта текущий без города (столбец создан с помощью Power Query)]],Таблица3[],4,0),0))),0) -> 110 | W53: Smart mini | X53: =IF(выгрузка__22[[#This Row],[Дата активации]]<>0,IF(выгрузка__22[[#This Row],[Дата блокировки]]<>"",CEILING((выгрузка__22[[#This Row],[Дата блокировки]]-выгрузка__22[[#This Row],[Дата активации]])/30,1),0),0) -> 0 | Y53: =IF(выгрузка__22[[#This Row],[Дата блокировки]]<>"",1,0) -> 0
A54: 41588.627 | B54: 916527 | C54: 1755197 | D54: 41585.314 | E54: =IF(выгрузка__22[[#This Row],[Дата активации]]<>"",MONTH(выгрузка__22[[#This Row],[Дата активации]]),0) -> 11 | G54: 64626 | H54: Непрофильный | I54: Тверь | J54: - Супер МТС (МАСС) (SCP) | K54: 30 | L54: 0 | M54: 30 | N54: Активен | P54: Супер МТС (МАСС) (SCP) | Q54: =IF(AND(DAY(выгрузка__22[[#This Row],[Дата отправки смс]])>=1,DAY(выгрузка__22[[#This Row],[Дата отправки смс]])<=14,MONTH(выгрузка__22[[#This Row],[Дата отправки смс]])=10),1,0) -> 0 | R54: =IF(выгрузка__22[[#This Row],[Дата регистрации]]="",0,1) -> 0 | S54: =IF(ISNA(VLOOKUP(выгрузка__22[[#This Row],[ЛС дилера]],'дилеры участники'!A:A,1,0)),0,1) -> 0 | T54: =IF(ISNA(VLOOKUP(выгрузка__22[[#This Row],[ТП комплекта текущий без города (столбец создан с помощью Power Query)]],Таблица3[Название ТП комплекта],1,0)),0,1) -> 1 | U54: =IF(ISNA(IF(выгрузка__22[[#This Row],[Канал продажи]]="Непрофильный",VLOOKUP(выгрузка__22[[#This Row],[ТП комплекта текущий без города (столбец создан с помощью Power Query)]],Таблица3[[Название ТП комплекта]:[Непрофильный]],3,0),VLOOKUP(выгрузка__22[[#This Row],[ТП комплекта текущий без города (столбец создан с помощью Power Query)]],Таблица3[[Название ТП комплекта]:[Непрофильный]],2,0)))=FALSE,1,0) -> 1 | V54: =IF(T54=1,IF(выгрузка__22[[#This Row],[Сумма дополнительного платежа и стартового баланса]]>300,VLOOKUP(выгрузка__22[[#This Row],[ТП комплекта текущий без города (столбец создан с помощью Power Query)]],Таблица3[],6,0),IF(выгрузка__22[[#This Row],[Сумма дополнительного платежа и стартового баланса]]>200,VLOOKUP(выгрузка__22[[#This Row],[ТП комплекта текущий без города (столбец создан с помощью Power Query)]],Таблица3[],5,0),IF(выгрузка__22[[#This Row],[Сумма дополнительного платежа и стартового баланса]]>100,VLOOKUP(выгрузка__22[[#This Row],[ТП комплекта текущий без города (столбец создан с помощью Power Query)]],Таблица3[],4,0),0))),0) -> 0 | W54: Супер МТС | X54: =IF(выгрузка__22[[#This Row],[Дата активации]]<>0,IF(выгрузка__22[[#This Row],[Дата блокировки]]<>"",CEILING((выгрузка__22[[#This Row],[Дата блокировки]]-выгрузка__22[[#This Row],[Дата активации]])/30,1),0),0) -> 0 | Y54: =IF(выгрузка__22[[#This Row],[Дата блокировки]]<>"",1,0) -> 0
A55: 41593.595 | B55: 916888 | C55: 1698618 | D55: 41584.97 | E55: =IF(выгрузка__22[[#This Row],[Дата активации]]<>"",MONTH(выгрузка__22[[#This Row],[Дата активации]]),0) -> 11 | F55: 41587.317 | G55: 64626 | H55: Непрофильный | I55: Ярославль | J55: - Супер МТС. Область (МАСС) (SCP) | K55: 30 | L55: 0 | M55: 30 | N55: Активен | P55: Супер МТС. Область (МАСС) (SCP) | Q55: =IF(AND(DAY(выгрузка__22[[#This Row],[Дата отправки смс]])>=1,DAY(выгрузка__22[[#This Row],[Дата отправки смс]])<=14,MONTH(выгрузка__22[[#This Row],[Дата отправки смс]])=10),1,0) -> 0 | R55: =IF(выгрузка__22[[#This Row],[Дата регистрации]]="",0,1) -> 1 | S55: =IF(ISNA(VLOOKUP(выгрузка__22[[#This Row],[ЛС дилера]],'дилеры участники'!A:A,1,0)),0,1) -> 0 | T55: =IF(ISNA(VLOOKUP(выгрузка__22[[#This Row],[ТП комплекта текущий без города (столбец создан с помощью Power Query)]],Таблица3[Название ТП комплекта],1,0)),0,1) -> 1 | U55: =IF(ISNA(IF(выгрузка__22[[#This Row],[Канал продажи]]="Непрофильный",VLOOKUP(выгрузка__22[[#This Row],[ТП комплекта текущий без города (столбец создан с помощью Power Query)]],Таблица3[[Название ТП комплекта]:[Непрофильный]],3,0),VLOOKUP(выгрузка__22[[#This Row],[ТП комплекта текущий без города (столбец создан с помощью Power Query)]],Таблица3[[Название ТП комплекта]:[Непрофильный]],2,0)))=FALSE,1,0) -> 1 | V55: =IF(T55=1,IF(выгрузка__22[[#This Row],[Сумма дополнительного платежа и стартового баланса]]>300,VLOOKUP(выгрузка__22[[#This Row],[ТП комплекта текущий без города (столбец создан с помощью Power Query)]],Таблица3[],6,0),IF(выгрузка__22[[#This Row],[Сумма дополнительного платежа и стартового баланса]]>200,VLOOKUP(выгрузка__22[[#This Row],[ТП комплекта текущий без города (столбец создан с помощью Power Query)]],Таблица3[],5,0),IF(выгрузка__22[[#This Row],[Сумма дополнительного платежа и стартового баланса]]>100,VLOOKUP(выгрузка__22[[#This Row],[ТП комплекта текущий без города (столбец создан с помощью Power Query)]],Таблица3[],4,0),0))),0) -> 0 | W55: Супер МТС. Область | X55: =IF(выгрузка__22[[#This Row],[Дата активации]]<>0,IF(выгрузка__22[[#This Row],[Дата блокировки]]<>"",CEILING((выгрузка__22[[#This Row],[Дата блокировки]]-выгрузка__22[[#This Row],[Дата активации]])/30,1),0),0) -> 0 | Y55: =IF(выгрузка__22[[#This Row],[Дата блокировки]]<>"",1,0) -> 0
A56: 41593.597 | B56: 916888 | C56: 1698695 | D56: 41584.958 | E56: =IF(выгрузка__22[[#This Row],[Дата активации]]<>"",MONTH(выгрузка__22[[#This Row],[Дата активации]]),0) -> 11 | F56: 41587.503 | G56: 64626 | H56: Непрофильный | I56: Ярославль | J56: - Супер МТС. Область (МАСС) (SCP) | K56: 30 | L56: 0 | M56: 30 | N56: Активен | P56: Супер МТС. Область (МАСС) (SCP) | Q56: =IF(AND(DAY(выгрузка__22[[#This Row],[Дата отправки смс]])>=1,DAY(выгрузка__22[[#This Row],[Дата отправки смс]])<=14,MONTH(выгрузка__22[[#This Row],[Дата отправки смс]])=10),1,0) -> 0 | R56: =IF(выгрузка__22[[#This Row],[Дата регистрации]]="",0,1) -> 1 | S56: =IF(ISNA(VLOOKUP(выгрузка__22[[#This Row],[ЛС дилера]],'дилеры участники'!A:A,1,0)),0,1) -> 0 | T56: =IF(ISNA(VLOOKUP(выгрузка__22[[#This Row],[ТП комплекта текущий без города (столбец создан с помощью Power Query)]],Таблица3[Название ТП комплекта],1,0)),0,1) -> 1 | U56: =IF(ISNA(IF(выгрузка__22[[#This Row],[Канал продажи]]="Непрофильный",VLOOKUP(выгрузка__22[[#This Row],[ТП комплекта текущий без города (столбец создан с помощью Power Query)]],Таблица3[[Название ТП комплекта]:[Непрофильный]],3,0),VLOOKUP(выгрузка__22[[#This Row],[ТП комплекта текущий без города (столбец создан с помощью Power Query)]],Таблица3[[Название ТП комплекта]:[Непрофильный]],2,0)))=FALSE,1,0) -> 1 | V56: =IF(T56=1,IF(выгрузка__22[[#This Row],[Сумма дополнительного платежа и стартового баланса]]>300,VLOOKUP(выгрузка__22[[#This Row],[ТП комплекта текущий без города (столбец создан с помощью Power Query)]],Таблица3[],6,0),IF(выгрузка__22[[#This Row],[Сумма дополнительного платежа и стартового баланса]]>200,VLOOKUP(выгрузка__22[[#This Row],[ТП комплекта текущий без города (столбец создан с помощью Power Query)]],Таблица3[],5,0),IF(выгрузка__22[[#This Row],[Сумма дополнительного платежа и стартового баланса]]>100,VLOOKUP(выгрузка__22[[#This Row],[ТП комплекта текущий без города (столбец создан с помощью Power Query)]],Таблица3[],4,0),0))),0) -> 0 | W56: Супер МТС. Область | X56: =IF(выгрузка__22[[#This Row],[Дата активации]]<>0,IF(выгрузка__22[[#This Row],[Дата блокировки]]<>"",CEILING((выгрузка__22[[#This Row],[Дата блокировки]]-выгрузка__22[[#This Row],[Дата активации]])/30,1),0),0) -> 0 | Y56: =IF(выгрузка__22[[#This Row],[Дата блокировки]]<>"",1,0) -> 0
A57: 41593.597 | B57: 916888 | C57: 1698685 | D57: 41584.861 | E57: =IF(выгрузка__22[[#This Row],[Дата активации]]<>"",MONTH(выгрузка__22[[#This Row],[Дата активации]]),0) -> 11 | F57: 41587.13 | G57: 64626 | H57: Непрофильный | I57: Ярославль | J57: - Супер МТС. Область (МАСС) (SCP) | K57: 30 | L57: 75 | M57: 105 | N57: Активен | P57: Супер МТС. Область (МАСС) (SCP) | Q57: =IF(AND(DAY(выгрузка__22[[#This Row],[Дата отправки смс]])>=1,DAY(выгрузка__22[[#This Row],[Дата отправки смс]])<=14,MONTH(выгрузка__22[[#This Row],[Дата отправки смс]])=10),1,0) -> 0 | R57: =IF(выгрузка__22[[#This Row],[Дата регистрации]]="",0,1) -> 1 | S57: =IF(ISNA(VLOOKUP(выгрузка__22[[#This Row],[ЛС дилера]],'дилеры участники'!A:A,1,0)),0,1) -> 0 | T57: =IF(ISNA(VLOOKUP(выгрузка__22[[#This Row],[ТП комплекта текущий без города (столбец создан с помощью Power Query)]],Таблица3[Название ТП комплекта],1,0)),0,1) -> 1 | U57: =IF(ISNA(IF(выгрузка__22[[#This Row],[Канал продажи]]="Непрофильный",VLOOKUP(выгрузка__22[[#This Row],[ТП комплекта текущий без города (столбец создан с помощью Power Query)]],Таблица3[[Название ТП комплекта]:[Непрофильный]],3,0),VLOOKUP(выгрузка__22[[#This Row],[ТП комплекта текущий без города (столбец создан с помощью Power Query)]],Таблица3[[Название ТП комплекта]:[Непрофильный]],2,0)))=FALSE,1,0) -> 1 | V57: =IF(T57=1,IF(выгрузка__22[[#This Row],[Сумма дополнительного платежа и стартового баланса]]>300,VLOOKUP(выгрузка__22[[#This Row],[ТП комплекта текущий без города (столбец создан с помощью Power Query)]],Таблица3[],6,0),IF(выгрузка__22[[#This Row],[Сумма дополнительного платежа и стартового баланса]]>200,VLOOKUP(выгрузка__22[[#This Row],[ТП комплекта текущий без города (столбец создан с помощью Power Query)]],Таблица3[],5,0),IF(выгрузка__22[[#This Row],[Сумма дополнительного платежа и стартового баланса]]>100,VLOOKUP(выгрузка__22[[#This Row],[ТП комплекта текущий без города (столбец создан с помощью Power Query)]],Таблица3[],4,0),0))),0) -> 70 | W57: Супер МТС. Область | X57: =IF(выгрузка__22[[#This Row],[Дата активации]]<>0,IF(выгрузка__22[[#This Row],[Дата блокировки]]<>"",CEILING((выгрузка__22[[#This Row],[Дата блокировки]]-выгрузка__22[[#This Row],[Дата активации]])/30,1),0),0) -> 0 | Y57: =IF(выгрузка__22[[#This Row],[Дата блокировки]]<>"",1,0) -> 0
A58: 41593.579 | B58: 916939 | C58: 1698370 | D58: 41584.779 | E58: =IF(выгрузка__22[[#This Row],[Дата активации]]<>"",MONTH(выгрузка__22[[#This Row],[Дата активации]]),0) -> 11 | F58: 41453.808 | G58: 64626 | H58: Непрофильный | I58: Ярославль | J58: - Супер МТС 092014 (МАСС) (SCP) | K58: 30 | L58: 0 | M58: 30 | N58: Активен | P58: Супер МТС 092014 (МАСС) (SCP) | Q58: =IF(AND(DAY(выгрузка__22[[#This Row],[Дата отправки смс]])>=1,DAY(выгрузка__22[[#This Row],[Дата отправки смс]])<=14,MONTH(выгрузка__22[[#This Row],[Дата отправки смс]])=10),1,0) -> 0 | R58: =IF(выгрузка__22[[#This Row],[Дата регистрации]]="",0,1) -> 1 | S58: =IF(ISNA(VLOOKUP(выгрузка__22[[#This Row],[ЛС дилера]],'дилеры участники'!A:A,1,0)),0,1) -> 0 | T58: =IF(ISNA(VLOOKUP(выгрузка__22[[#This Row],[ТП комплекта текущий без города (столбец создан с помощью Power Query)]],Таблица3[Название ТП комплекта],1,0)),0,1) -> 1 | U58: =IF(ISNA(IF(выгрузка__22[[#This Row],[Канал продажи]]="Непрофильный",VLOOKUP(выгрузка__22[[#This Row],[ТП комплекта текущий без города (столбец создан с помощью Power Query)]],Таблица3[[Название ТП комплекта]:[Непрофильный]],3,0),VLOOKUP(выгрузка__22[[#This Row],[ТП комплекта текущий без города (столбец создан с помощью Power Query)]],Таблица3[[Название ТП комплекта]:[Непрофильный]],2,0)))=FALSE,1,0) -> 1 | V58: =IF(T58=1,IF(выгрузка__22[[#This Row],[Сумма дополнительного платежа и стартового баланса]]>300,VLOOKUP(выгрузка__22[[#This Row],[ТП комплекта текущий без города (столбец создан с помощью Power Query)]],Таблица3[],6,0),IF(выгрузка__22[[#This Row],[Сумма дополнительного платежа и стартового баланса]]>200,VLOOKUP(выгрузка__22[[#This Row],[ТП комплекта текущий без города (столбец создан с помощью Power Query)]],Таблица3[],5,0),IF(выгрузка__22[[#This Row],[Сумма дополнительного платежа и стартового баланса]]>100,VLOOKUP(выгрузка__22[[#This Row],[ТП комплекта текущий без города (столбец создан с помощью Power Query)]],Таблица3[],4,0),0))),0) -> 0 | W58: Супер МТС 092014 | X58: =IF(выгрузка__22[[#This Row],[Дата активации]]<>0,IF(выгрузка__22[[#This Row],[Дата блокировки]]<>"",CEILING((выгрузка__22[[#This Row],[Дата блокировки]]-выгрузка__22[[#This Row],[Дата активации]])/30,1),0),0) -> 0 | Y58: =IF(выгрузка__22[[#This Row],[Дата блокировки]]<>"",1,0) -> 0
A59: 41593.596 | B59: 916888 | C59: 1698650 | D59: 41584.766 | E59: =IF(выгрузка__22[[#This Row],[Дата активации]]<>"",MONTH(выгрузка__22[[#This Row],[Дата активации]]),0) -> 11 | F59: 41587.13 | G59: 64626 | H59: Непрофильный | I59: Ярославль | J59: - Супер МТС. Область (МАСС) (SCP) | K59: 30 | L59: 0 | M59: 30 | N59: Активен | P59: Супер МТС. Область (МАСС) (SCP) | Q59: =IF(AND(DAY(выгрузка__22[[#This Row],[Дата отправки смс]])>=1,DAY(выгрузка__22[[#This Row],[Дата отправки смс]])<=14,MONTH(выгрузка__22[[#This Row],[Дата отправки смс]])=10),1,0) -> 0 | R59: =IF(выгрузка__22[[#This Row],[Дата регистрации]]="",0,1) -> 1 | S59: =IF(ISNA(VLOOKUP(выгрузка__22[[#This Row],[ЛС дилера]],'дилеры участники'!A:A,1,0)),0,1) -> 0 | T59: =IF(ISNA(VLOOKUP(выгрузка__22[[#This Row],[ТП комплекта текущий без города (столбец создан с помощью Power Query)]],Таблица3[Название ТП комплекта],1,0)),0,1) -> 1 | U59: =IF(ISNA(IF(выгрузка__22[[#This Row],[Канал продажи]]="Непрофильный",VLOOKUP(выгрузка__22[[#This Row],[ТП комплекта текущий без города (столбец создан с помощью Power Query)]],Таблица3[[Название ТП комплекта]:[Непрофильный]],3,0),VLOOKUP(выгрузка__22[[#This Row],[ТП комплекта текущий без города (столбец создан с помощью Power Query)]],Таблица3[[Название ТП комплекта]:[Непрофильный]],2,0)))=FALSE,1,0) -> 1 | V59: =IF(T59=1,IF(выгрузка__22[[#This Row],[Сумма дополнительного платежа и стартового баланса]]>300,VLOOKUP(выгрузка__22[[#This Row],[ТП комплекта текущий без города (столбец создан с помощью Power Query)]],Таблица3[],6,0),IF(выгрузка__22[[#This Row],[Сумма дополнительного платежа и стартового баланса]]>200,VLOOKUP(выгрузка__22[[#This Row],[ТП комплекта текущий без города (столбец создан с помощью Power Query)]],Таблица3[],5,0),IF(выгрузка__22[[#This Row],[Сумма дополнительного платежа и стартового баланса]]>100,VLOOKUP(выгрузка__22[[#This Row],[ТП комплекта текущий без города (столбец создан с помощью Power Query)]],Таблица3[],4,0),0))),0) -> 0 | W59: Супер МТС. Область | X59: =IF(выгрузка__22[[#This Row],[Дата активации]]<>0,IF(выгрузка__22[[#This Row],[Дата блокировки]]<>"",CEILING((выгрузка__22[[#This Row],[Дата блокировки]]-выгрузка__22[[#This Row],[Дата активации]])/30,1),0),0) -> 0 | Y59: =IF(выгрузка__22[[#This Row],[Дата блокировки]]<>"",1,0) -> 0
A60: 41593.591 | B60: 916512 | C60: 1698583 | D60: 41584.756 | E60: =IF(выгрузка__22[[#This Row],[Дата активации]]<>"",MONTH(выгрузка__22[[#This Row],[Дата активации]]),0) -> 11 | F60: 41587.317 | G60: 64626 | H60: Непрофильный | I60: Ярославль | J60: - Супер МТС. Область (МАСС) (SCP) | K60: 30 | L60: 0 | M60: 30 | N60: Активен | P60: Супер МТС. Область (МАСС) (SCP) | Q60: =IF(AND(DAY(выгрузка__22[[#This Row],[Дата отправки смс]])>=1,DAY(выгрузка__22[[#This Row],[Дата отправки смс]])<=14,MONTH(выгрузка__22[[#This Row],[Дата отправки смс]])=10),1,0) -> 0 | R60: =IF(выгрузка__22[[#This Row],[Дата регистрации]]="",0,1) -> 1 | S60: =IF(ISNA(VLOOKUP(выгрузка__22[[#This Row],[ЛС дилера]],'дилеры участники'!A:A,1,0)),0,1) -> 0 | T60: =IF(ISNA(VLOOKUP(выгрузка__22[[#This Row],[ТП комплекта текущий без города (столбец создан с помощью Power Query)]],Таблица3[Название ТП комплекта],1,0)),0,1) -> 1 | U60: =IF(ISNA(IF(выгрузка__22[[#This Row],[Канал продажи]]="Непрофильный",VLOOKUP(выгрузка__22[[#This Row],[ТП комплекта текущий без города (столбец создан с помощью Power Query)]],Таблица3[[Название ТП комплекта]:[Непрофильный]],3,0),VLOOKUP(выгрузка__22[[#This Row],[ТП комплекта текущий без города (столбец создан с помощью Power Query)]],Таблица3[[Название ТП комплекта]:[Непрофильный]],2,0)))=FALSE,1,0) -> 1 | V60: =IF(T60=1,IF(выгрузка__22[[#This Row],[Сумма дополнительного платежа и стартового баланса]]>300,VLOOKUP(выгрузка__22[[#This Row],[ТП комплекта текущий без города (столбец создан с помощью Power Query)]],Таблица3[],6,0),IF(выгрузка__22[[#This Row],[Сумма дополнительного платежа и стартового баланса]]>200,VLOOKUP(выгрузка__22[[#This Row],[ТП комплекта текущий без города (столбец создан с помощью Power Query)]],Таблица3[],5,0),IF(выгрузка__22[[#This Row],[Сумма дополнительного платежа и стартового баланса]]>100,VLOOKUP(выгрузка__22[[#This Row],[ТП комплекта текущий без города (столбец создан с помощью Power Query)]],Таблица3[],4,0),0))),0) -> 0 | W60: Супер МТС. Область | X60: =IF(выгрузка__22[[#This Row],[Дата активации]]<>0,IF(выгрузка__22[[#This Row],[Дата блокировки]]<>"",CEILING((выгрузка__22[[#This Row],[Дата блокировки]]-выгрузка__22[[#This Row],[Дата активации]])/30,1),0),0) -> 0 | Y60: =IF(выгрузка__22[[#This Row],[Дата блокировки]]<>"",1,0) -> 0
A61: 41593.591 | B61: 916512 | C61: 1698568 | D61: 41584.756 | E61: =IF(выгрузка__22[[#This Row],[Дата активации]]<>"",MONTH(выгрузка__22[[#This Row],[Дата активации]]),0) -> 11 | F61: 41587.13 | G61: 64626 | H61: Непрофильный | I61: Ярославль | J61: - Супер МТС. Область (МАСС) (SCP) | K61: 30 | L61: 0 | M61: 30 | N61: Активен | P61: Супер МТС. Область (МАСС) (SCP) | Q61: =IF(AND(DAY(выгрузка__22[[#This Row],[Дата отправки смс]])>=1,DAY(выгрузка__22[[#This Row],[Дата отправки смс]])<=14,MONTH(выгрузка__22[[#This Row],[Дата отправки смс]])=10),1,0) -> 0 | R61: =IF(выгрузка__22[[#This Row],[Дата регистрации]]="",0,1) -> 1 | S61: =IF(ISNA(VLOOKUP(выгрузка__22[[#This Row],[ЛС дилера]],'дилеры участники'!A:A,1,0)),0,1) -> 0 | T61: =IF(ISNA(VLOOKUP(выгрузка__22[[#This Row],[ТП комплекта текущий без города (столбец создан с помощью Power Query)]],Таблица3[Название ТП комплекта],1,0)),0,1) -> 1 | U61: =IF(ISNA(IF(выгрузка__22[[#This Row],[Канал продажи]]="Непрофильный",VLOOKUP(выгрузка__22[[#This Row],[ТП комплекта текущий без города (столбец создан с помощью Power Query)]],Таблица3[[Название ТП комплекта]:[Непрофильный]],3,0),VLOOKUP(выгрузка__22[[#This Row],[ТП комплекта текущий без города (столбец создан с помощью Power Query)]],Таблица3[[Название ТП комплекта]:[Непрофильный]],2,0)))=FALSE,1,0) -> 1 | V61: =IF(T61=1,IF(выгрузка__22[[#This Row],[Сумма дополнительного платежа и стартового баланса]]>300,VLOOKUP(выгрузка__22[[#This Row],[ТП комплекта текущий без города (столбец создан с помощью Power Query)]],Таблица3[],6,0),IF(выгрузка__22[[#This Row],[Сумма дополнительного платежа и стартового баланса]]>200,VLOOKUP(выгрузка__22[[#This Row],[ТП комплекта текущий без города (столбец создан с помощью Power Query)]],Таблица3[],5,0),IF(выгрузка__22[[#This Row],[Сумма дополнительного платежа и стартового баланса]]>100,VLOOKUP(выгрузка__22[[#This Row],[ТП комплекта текущий без города (столбец создан с помощью Power Query)]],Таблица3[],4,0),0))),0) -> 0 | W61: Супер МТС. Область | X61: =IF(выгрузка__22[[#This Row],[Дата активации]]<>0,IF(выгрузка__22[[#This Row],[Дата блокировки]]<>"",CEILING((выгрузка__22[[#This Row],[Дата блокировки]]-выгрузка__22[[#This Row],[Дата активации]])/30,1),0),0) -> 0 | Y61: =IF(выгрузка__22[[#This Row],[Дата блокировки]]<>"",1,0) -> 0
A62: 41593.589 | B62: 916512 | C62: 1698242 | D62: 41584.724 | E62: =IF(выгрузка__22[[#This Row],[Дата активации]]<>"",MONTH(выгрузка__22[[#This Row],[Дата активации]]),0) -> 11 | F62: 41587.462 | G62: 64626 | H62: Непрофильный | I62: Ярославль | J62: - Супер МТС. Область (МАСС) (SCP) | K62: 30 | L62: 0 | M62: 30 | N62: Активен | P62: Супер МТС. Область (МАСС) (SCP) | Q62: =IF(AND(DAY(выгрузка__22[[#This Row],[Дата отправки смс]])>=1,DAY(выгрузка__22[[#This Row],[Дата отправки смс]])<=14,MONTH(выгрузка__22[[#This Row],[Дата отправки смс]])=10),1,0) -> 0 | R62: =IF(выгрузка__22[[#This Row],[Дата регистрации]]="",0,1) -> 1 | S62: =IF(ISNA(VLOOKUP(выгрузка__22[[#This Row],[ЛС дилера]],'дилеры участники'!A:A,1,0)),0,1) -> 0 | T62: =IF(ISNA(VLOOKUP(выгрузка__22[[#This Row],[ТП комплекта текущий без города (столбец создан с помощью Power Query)]],Таблица3[Название ТП комплекта],1,0)),0,1) -> 1 | U62: =IF(ISNA(IF(выгрузка__22[[#This Row],[Канал продажи]]="Непрофильный",VLOOKUP(выгрузка__22[[#This Row],[ТП комплекта текущий без города (столбец создан с помощью Power Query)]],Таблица3[[Название ТП комплекта]:[Непрофильный]],3,0),VLOOKUP(выгрузка__22[[#This Row],[ТП комплекта текущий без города (столбец создан с помощью Power Query)]],Таблица3[[Название ТП комплекта]:[Непрофильный]],2,0)))=FALSE,1,0) -> 1 | V62: =IF(T62=1,IF(выгрузка__22[[#This Row],[Сумма дополнительного платежа и стартового баланса]]>300,VLOOKUP(выгрузка__22[[#This Row],[ТП комплекта текущий без города (столбец создан с помощью Power Query)]],Таблица3[],6,0),IF(выгрузка__22[[#This Row],[Сумма дополнительного платежа и стартового баланса]]>200,VLOOKUP(выгрузка__22[[#This Row],[ТП комплекта текущий без города (столбец создан с помощью Power Query)]],Таблица3[],5,0),IF(выгрузка__22[[#This Row],[Сумма дополнительного платежа и стартового баланса]]>100,VLOOKUP(выгрузка__22[[#This Row],[ТП комплекта текущий без города (столбец создан с помощью Power Query)]],Таблица3[],4,0),0))),0) -> 0 | W62: Супер МТС. Область | X62: =IF(выгрузка__22[[#This Row],[Дата активации]]<>0,IF(выгрузка__22[[#This Row],[Дата блокировки]]<>"",CEILING((выгрузка__22[[#This Row],[Дата блокировки]]-выгрузка__22[[#This Row],[Дата активации]])/30,1),0),0) -> 0 | Y62: =IF(выгрузка__22[[#This Row],[Дата блокировки]]<>"",1,0) -> 0
A63: 41593.572 | B63: 916513 | C63: 1751787 | D63: 41584.598 | E63: =IF(выгрузка__22[[#This Row],[Дата активации]]<>"",MONTH(выгрузка__22[[#This Row],[Дата активации]]),0) -> 11 | F63: 41587.535 | G63: 64626 | H63: Непрофильный | I63: Ярославль | J63: - Супер МТС (МАСС) (SCP) | K63: 50 | L63: 0 | M63: 50 | N63: Активен | P63: Супер МТС (МАСС) (SCP) | Q63: =IF(AND(DAY(выгрузка__22[[#This Row],[Дата отправки смс]])>=1,DAY(выгрузка__22[[#This Row],[Дата отправки смс]])<=14,MONTH(выгрузка__22[[#This Row],[Дата отправки смс]])=10),1,0) -> 0 | R63: =IF(выгрузка__22[[#This Row],[Дата регистрации]]="",0,1) -> 1 | S63: =IF(ISNA(VLOOKUP(выгрузка__22[[#This Row],[ЛС дилера]],'дилеры участники'!A:A,1,0)),0,1) -> 0 | T63: =IF(ISNA(VLOOKUP(выгрузка__22[[#This Row],[ТП комплекта текущий без города (столбец создан с помощью Power Query)]],Таблица3[Название ТП комплекта],1,0)),0,1) -> 1 | U63: =IF(ISNA(IF(выгрузка__22[[#This Row],[Канал продажи]]="Непрофильный",VLOOKUP(выгрузка__22[[#This Row],[ТП комплекта текущий без города (столбец создан с помощью Power Query)]],Таблица3[[Название ТП комплекта]:[Непрофильный]],3,0),VLOOKUP(выгрузка__22[[#This Row],[ТП комплекта текущий без города (столбец создан с помощью Power Query)]],Таблица3[[Название ТП комплекта]:[Непрофильный]],2,0)))=FALSE,1,0) -> 1 | V63: =IF(T63=1,IF(выгрузка__22[[#This Row],[Сумма дополнительного платежа и стартового баланса]]>300,VLOOKUP(выгрузка__22[[#This Row],[ТП комплекта текущий без города (столбец создан с помощью Power Query)]],Таблица3[],6,0),IF(выгрузка__22[[#This Row],[Сумма дополнительного платежа и стартового баланса]]>200,VLOOKUP(выгрузка__22[[#This Row],[ТП комплекта текущий без города (столбец создан с помощью Power Query)]],Таблица3[],5,0),IF(выгрузка__22[[#This Row],[Сумма дополнительного платежа и стартового баланса]]>100,VLOOKUP(выгрузка__22[[#This Row],[ТП комплекта текущий без города (столбец создан с помощью Power Query)]],Таблица3[],4,0),0))),0) -> 0 | W63: Супер МТС | X63: =IF(выгрузка__22[[#This Row],[Дата активации]]<>0,IF(выгрузка__22[[#This Row],[Дата блокировки]]<>"",CEILING((выгрузка__22[[#This Row],[Дата блокировки]]-выгрузка__22[[#This Row],[Дата активации]])/30,1),0),0) -> 0 | Y63: =IF(выгрузка__22[[#This Row],[Дата блокировки]]<>"",1,0) -> 0
A64: 41593.572 | B64: 916513 | C64: 1751767 | D64: 41584.598 | E64: =IF(выгрузка__22[[#This Row],[Дата активации]]<>"",MONTH(выгрузка__22[[#This Row],[Дата активации]]),0) -> 11 | F64: 41587.535 | G64: 64626 | H64: Непрофильный | I64: Ярославль | J64: - Супер МТС (МАСС) (SCP) | K64: 50 | L64: 0 | M64: 50 | N64: Активен | P64: Супер МТС (МАСС) (SCP) | Q64: =IF(AND(DAY(выгрузка__22[[#This Row],[Дата отправки смс]])>=1,DAY(выгрузка__22[[#This Row],[Дата отправки смс]])<=14,MONTH(выгрузка__22[[#This Row],[Дата отправки смс]])=10),1,0) -> 0 | R64: =IF(выгрузка__22[[#This Row],[Дата регистрации]]="",0,1) -> 1 | S64: =IF(ISNA(VLOOKUP(выгрузка__22[[#This Row],[ЛС дилера]],'дилеры участники'!A:A,1,0)),0,1) -> 0 | T64: =IF(ISNA(VLOOKUP(выгрузка__22[[#This Row],[ТП комплекта текущий без города (столбец создан с помощью Power Query)]],Таблица3[Название ТП комплекта],1,0)),0,1) -> 1 | U64: =IF(ISNA(IF(выгрузка__22[[#This Row],[Канал продажи]]="Непрофильный",VLOOKUP(выгрузка__22[[#This Row],[ТП комплекта текущий без города (столбец создан с помощью Power Query)]],Таблица3[[Название ТП комплекта]:[Непрофильный]],3,0),VLOOKUP(выгрузка__22[[#This Row],[ТП комплекта текущий без города (столбец создан с помощью Power Query)]],Таблица3[[Название ТП комплекта]:[Непрофильный]],2,0)))=FALSE,1,0) -> 1 | V64: =IF(T64=1,IF(выгрузка__22[[#This Row],[Сумма дополнительного платежа и стартового баланса]]>300,VLOOKUP(выгрузка__22[[#This Row],[ТП комплекта текущий без города (столбец создан с помощью Power Query)]],Таблица3[],6,0),IF(выгрузка__22[[#This Row],[Сумма дополнительного платежа и стартового баланса]]>200,VLOOKUP(выгрузка__22[[#This Row],[ТП комплекта текущий без города (столбец создан с помощью Power Query)]],Таблица3[],5,0),IF(выгрузка__22[[#This Row],[Сумма дополнительного платежа и стартового баланса]]>100,VLOOKUP(выгрузка__22[[#This Row],[ТП комплекта текущий без города (столбец создан с помощью Power Query)]],Таблица3[],4,0),0))),0) -> 0 | W64: Супер МТС | X64: =IF(выгрузка__22[[#This Row],[Дата активации]]<>0,IF(выгрузка__22[[#This Row],[Дата блокировки]]<>"",CEILING((выгрузка__22[[#This Row],[Дата блокировки]]-выгрузка__22[[#This Row],[Дата активации]])/30,1),0),0) -> 0 | Y64: =IF(выгрузка__22[[#This Row],[Дата блокировки]]<>"",1,0) -> 0
A65: 41593.506 | B65: 916513 | C65: 1755175 | D65: 41584.527 | E65: =IF(выгрузка__22[[#This Row],[Дата активации]]<>"",MONTH(выгрузка__22[[#This Row],[Дата активации]]),0) -> 11 | F65: 41586.867 | G65: 64626 | H65: Непрофильный | I65: Ярославль | J65: - Супер МТС (МАСС) (SCP) | K65: 30 | L65: 78.12 | M65: 108.12 | N65: Активен | P65: Супер МТС (МАСС) (SCP) | Q65: =IF(AND(DAY(выгрузка__22[[#This Row],[Дата отправки смс]])>=1,DAY(выгрузка__22[[#This Row],[Дата отправки смс]])<=14,MONTH(выгрузка__22[[#This Row],[Дата отправки смс]])=10),1,0) -> 0 | R65: =IF(выгрузка__22[[#This Row],[Дата регистрации]]="",0,1) -> 1 | S65: =IF(ISNA(VLOOKUP(выгрузка__22[[#This Row],[ЛС дилера]],'дилеры участники'!A:A,1,0)),0,1) -> 0 | T65: =IF(ISNA(VLOOKUP(выгрузка__22[[#This Row],[ТП комплекта текущий без города (столбец создан с помощью Power Query)]],Таблица3[Название ТП комплекта],1,0)),0,1) -> 1 | U65: =IF(ISNA(IF(выгрузка__22[[#This Row],[Канал продажи]]="Непрофильный",VLOOKUP(выгрузка__22[[#This Row],[ТП комплекта текущий без города (столбец создан с помощью Power Query)]],Таблица3[[Название ТП комплекта]:[Непрофильный]],3,0),VLOOKUP(выгрузка__22[[#This Row],[ТП комплекта текущий без города (столбец создан с помощью Power Query)]],Таблица3[[Название ТП комплекта]:[Непрофильный]],2,0)))=FALSE,1,0) -> 1 | V65: =IF(T65=1,IF(выгрузка__22[[#This Row],[Сумма дополнительного платежа и стартового баланса]]>300,VLOOKUP(выгрузка__22[[#This Row],[ТП комплекта текущий без города (столбец создан с помощью Power Query)]],Таблица3[],6,0),IF(выгрузка__22[[#This Row],[Сумма дополнительного платежа и стартового баланса]]>200,VLOOKUP(выгрузка__22[[#This Row],[ТП комплекта текущий без города (столбец создан с помощью Power Query)]],Таблица3[],5,0),IF(выгрузка__22[[#This Row],[Сумма дополнительного платежа и стартового баланса]]>100,VLOOKUP(выгрузка__22[[#This Row],[ТП комплекта текущий без города (столбец создан с помощью Power Query)]],Таблица3[],4,0),0))),0) -> 70 | W65: Супер МТС | X65: =IF(выгрузка__22[[#This Row],[Дата активации]]<>0,IF(выгрузка__22[[#This Row],[Дата блокировки]]<>"",CEILING((выгрузка__22[[#This Row],[Дата блокировки]]-выгрузка__22[[#This Row],[Дата активации]])/30,1),0),0) -> 0 | Y65: =IF(выгрузка__22[[#This Row],[Дата блокировки]]<>"",1,0) -> 0
A66: 41593.588 | B66: 916512 | C66: 1697827 | D66: 41584.501 | E66: =IF(выгрузка__22[[#This Row],[Дата активации]]<>"",MONTH(выгрузка__22[[#This Row],[Дата активации]]),0) -> 11 | F66: 41586.911 | G66: 64626 | H66: Непрофильный | I66: Ярославль | J66: - Супер МТС. Область (МАСС) (SCP) | K66: 30 | L66: 0 | M66: 30 | N66: Активен | P66: Супер МТС. Область (МАСС) (SCP) | Q66: =IF(AND(DAY(выгрузка__22[[#This Row],[Дата отправки смс]])>=1,DAY(выгрузка__22[[#This Row],[Дата отправки смс]])<=14,MONTH(выгрузка__22[[#This Row],[Дата отправки смс]])=10),1,0) -> 0 | R66: =IF(выгрузка__22[[#This Row],[Дата регистрации]]="",0,1) -> 1 | S66: =IF(ISNA(VLOOKUP(выгрузка__22[[#This Row],[ЛС дилера]],'дилеры участники'!A:A,1,0)),0,1) -> 0 | T66: =IF(ISNA(VLOOKUP(выгрузка__22[[#This Row],[ТП комплекта текущий без города (столбец создан с помощью Power Query)]],Таблица3[Название ТП комплекта],1,0)),0,1) -> 1 | U66: =IF(ISNA(IF(выгрузка__22[[#This Row],[Канал продажи]]="Непрофильный",VLOOKUP(выгрузка__22[[#This Row],[ТП комплекта текущий без города (столбец создан с помощью Power Query)]],Таблица3[[Название ТП комплекта]:[Непрофильный]],3,0),VLOOKUP(выгрузка__22[[#This Row],[ТП комплекта текущий без города (столбец создан с помощью Power Query)]],Таблица3[[Название ТП комплекта]:[Непрофильный]],2,0)))=FALSE,1,0) -> 1 | V66: =IF(T66=1,IF(выгрузка__22[[#This Row],[Сумма дополнительного платежа и стартового баланса]]>300,VLOOKUP(выгрузка__22[[#This Row],[ТП комплекта текущий без города (столбец создан с помощью Power Query)]],Таблица3[],6,0),IF(выгрузка__22[[#This Row],[Сумма дополнительного платежа и стартового баланса]]>200,VLOOKUP(выгрузка__22[[#This Row],[ТП комплекта текущий без города (столбец создан с помощью Power Query)]],Таблица3[],5,0),IF(выгрузка__22[[#This Row],[Сумма дополнительного платежа и стартового баланса]]>100,VLOOKUP(выгрузка__22[[#This Row],[ТП комплекта текущий без города (столбец создан с помощью Power Query)]],Таблица3[],4,0),0))),0) -> 0 | W66: Супер МТС. Область | X66: =IF(выгрузка__22[[#This Row],[Дата активации]]<>0,IF(выгрузка__22[[#This Row],[Дата блокировки]]<>"",CEILING((выгрузка__22[[#This Row],[Дата блокировки]]-выгрузка__22[[#This Row],[Дата активации]])/30,1),0),0) -> 0 | Y66: =IF(выгрузка__22[[#This Row],[Дата блокировки]]<>"",1,0) -> 0
... A70: 41593.567 | B70: 916513 | C70: 1698791 | D70: 41584.002 | E70: =IF(выгрузка__22[[#This Row],[Дата активации]]<>"",MONTH(выгрузка__22[[#This Row],[Дата активации]]),0) -> 11 | F70: 41587.161 | G70: 64626 | H70: Непрофильный | I70: Ярославль | J70: - Супер МТС (МАСС) (SCP) | K70: 30 | L70: 0 | M70: 30 | N70: Активен | P70: Супер МТС (МАСС) (SCP) | Q70: =IF(AND(DAY(выгрузка__22[[#This Row],[Дата отправки смс]])>=1,DAY(выгрузка__22[[#This Row],[Дата отправки смс]])<=14,MONTH(выгрузка__22[[#This Row],[Дата отправки смс]])=10),1,0) -> 0 | R70: =IF(выгрузка__22[[#This Row],[Дата регистрации]]="",0,1) -> 1 | S70: =IF(ISNA(VLOOKUP(выгрузка__22[[#This Row],[ЛС дилера]],'дилеры участники'!A:A,1,0)),0,1) -> 0 | T70: =IF(ISNA(VLOOKUP(выгрузка__22[[#This Row],[ТП комплекта текущий без города (столбец создан с помощью Power Query)]],Таблица3[Название ТП комплекта],1,0)),0,1) -> 1 | U70: =IF(ISNA(IF(выгрузка__22[[#This Row],[Канал продажи]]="Непрофильный",VLOOKUP(выгрузка__22[[#This Row],[ТП комплекта текущий без города (столбец создан с помощью Power Query)]],Таблица3[[Название ТП комплекта]:[Непрофильный]],3,0),VLOOKUP(выгрузка__22[[#This Row],[ТП комплекта текущий без города (столбец создан с помощью Power Query)]],Таблица3[[Название ТП комплекта]:[Непрофильный]],2,0)))=FALSE,1,0) -> 1 | V70: =IF(T70=1,IF(выгрузка__22[[#This Row],[Сумма дополнительного платежа и стартового баланса]]>300,VLOOKUP(выгрузка__22[[#This Row],[ТП комплекта текущий без города (столбец создан с помощью Power Query)]],Таблица3[],6,0),IF(выгрузка__22[[#This Row],[Сумма дополнительного платежа и стартового баланса]]>200,VLOOKUP(выгрузка__22[[#This Row],[ТП комплекта текущий без города (столбец создан с помощью Power Query)]],Таблица3[],5,0),IF(выгрузка__22[[#This Row],[Сумма дополнительного платежа и стартового баланса]]>100,VLOOKUP(выгрузка__22[[#This Row],[ТП комплекта текущий без города (столбец создан с помощью Power Query)]],Таблица3[],4,0),0))),0) -> 0 | W70: Супер МТС | X70: =IF(выгрузка__22[[#This Row],[Дата активации]]<>0,IF(выгрузка__22[[#This Row],[Дата блокировки]]<>"",CEILING((выгрузка__22[[#This Row],[Дата блокировки]]-выгрузка__22[[#This Row],[Дата активации]])/30,1),0),0) -> 0 | Y70: =IF(выгрузка__22[[#This Row],[Дата блокировки]]<>"",1,0) -> 0
A71: 41583.875 | B71: 915001 | C71: 8542631 | D71: 41583.921 | E71: =IF(выгрузка__22[[#This Row],[Дата активации]]<>"",MONTH(выгрузка__22[[#This Row],[Дата активации]]),0) -> 11 | G71: 79956 | H71: Непрофильный | I71: Тверь | J71: - МТС Коннект-4 (МАСС) (SCP) | K71: 401 | L71: 0 | M71: 401 | N71: Активен | P71: МТС Коннект-4 (МАСС) (SCP) | Q71: =IF(AND(DAY(выгрузка__22[[#This Row],[Дата отправки смс]])>=1,DAY(выгрузка__22[[#This Row],[Дата отправки смс]])<=14,MONTH(выгрузка__22[[#This Row],[Дата отправки смс]])=10),1,0) -> 0 | R71: =IF(выгрузка__22[[#This Row],[Дата регистрации]]="",0,1) -> 0 | S71: =IF(ISNA(VLOOKUP(выгрузка__22[[#This Row],[ЛС дилера]],'дилеры участники'!A:A,1,0)),0,1) -> 1 | T71: =IF(ISNA(VLOOKUP(выгрузка__22[[#This Row],[ТП комплекта текущий без города (столбец создан с помощью Power Query)]],Таблица3[Название ТП комплекта],1,0)),0,1) -> 1 | U71: =IF(ISNA(IF(выгрузка__22[[#This Row],[Канал продажи]]="Непрофильный",VLOOKUP(выгрузка__22[[#This Row],[ТП комплекта текущий без города (столбец создан с помощью Power Query)]],Таблица3[[Название ТП комплекта]:[Непрофильный]],3,0),VLOOKUP(выгрузка__22[[#This Row],[ТП комплекта текущий без города (столбец создан с помощью Power Query)]],Таблица3[[Название ТП комплекта]:[Непрофильный]],2,0)))=FALSE,1,0) -> 1 | V71: =IF(T71=1,IF(выгрузка__22[[#This Row],[Сумма дополнительного платежа и стартового баланса]]>300,VLOOKUP(выгрузка__22[[#This Row],[ТП комплекта текущий без города (столбец создан с помощью Power Query)]],Таблица3[],6,0),IF(выгрузка__22[[#This Row],[Сумма дополнительного платежа и стартового баланса]]>200,VLOOKUP(выгрузка__22[[#This Row],[ТП комплекта текущий без города (столбец создан с помощью Power Query)]],Таблица3[],5,0),IF(выгрузка__22[[#This Row],[Сумма дополнительного платежа и стартового баланса]]>100,VLOOKUP(выгрузка__22[[#This Row],[ТП комплекта текущий без города (столбец создан с помощью Power Query)]],Таблица3[],4,0),0))),0) -> 170 | W71: МТС Коннект-4 | X71: =IF(выгрузка__22[[#This Row],[Дата активации]]<>0,IF(выгрузка__22[[#This Row],[Дата блокировки]]<>"",CEILING((выгрузка__22[[#This Row],[Дата блокировки]]-выгрузка__22[[#This Row],[Дата активации]])/30,1),0),0) -> 0 | Y71: =IF(выгрузка__22[[#This Row],[Дата блокировки]]<>"",1,0) -> 0
A72: 41593.599 | B72: 916888 | C72: 1752152 | D72: 41583.889 | E72: =IF(выгрузка__22[[#This Row],[Дата активации]]<>"",MONTH(выгрузка__22[[#This Row],[Дата активации]]),0) -> 11 | F72: 41587.349 | G72: 64626 | H72: Непрофильный | I72: Ярославль | J72: - Супер МТС. Область (МАСС) (SCP) | K72: 30 | L72: 0 | M72: 30 | N72: Активен | P72: Супер МТС. Область (МАСС) (SCP) | Q72: =IF(AND(DAY(выгрузка__22[[#This Row],[Дата отправки смс]])>=1,DAY(выгрузка__22[[#This Row],[Дата отправки смс]])<=14,MONTH(выгрузка__22[[#This Row],[Дата отправки смс]])=10),1,0) -> 0 | R72: =IF(выгрузка__22[[#This Row],[Дата регистрации]]="",0,1) -> 1 | S72: =IF(ISNA(VLOOKUP(выгрузка__22[[#This Row],[ЛС дилера]],'дилеры участники'!A:A,1,0)),0,1) -> 0 | T72: =IF(ISNA(VLOOKUP(выгрузка__22[[#This Row],[ТП комплекта текущий без города (столбец создан с помощью Power Query)]],Таблица3[Название ТП комплекта],1,0)),0,1) -> 1 | U72: =IF(ISNA(IF(выгрузка__22[[#This Row],[Канал продажи]]="Непрофильный",VLOOKUP(выгрузка__22[[#This Row],[ТП комплекта текущий без города (столбец создан с помощью Power Query)]],Таблица3[[Название ТП комплекта]:[Непрофильный]],3,0),VLOOKUP(выгрузка__22[[#This Row],[ТП комплекта текущий без города (столбец создан с помощью Power Query)]],Таблица3[[Название ТП комплекта]:[Непрофильный]],2,0)))=FALSE,1,0) -> 1 | V72: =IF(T72=1,IF(выгрузка__22[[#This Row],[Сумма дополнительного платежа и стартового баланса]]>300,VLOOKUP(выгрузка__22[[#This Row],[ТП комплекта текущий без города (столбец создан с помощью Power Query)]],Таблица3[],6,0),IF(выгрузка__22[[#This Row],[Сумма дополнительного платежа и стартового баланса]]>200,VLOOKUP(выгрузка__22[[#This Row],[ТП комплекта текущий без города (столбец создан с помощью Power Query)]],Таблица3[],5,0),IF(выгрузка__22[[#This Row],[Сумма дополнительного платежа и стартового баланса]]>100,VLOOKUP(выгрузка__22[[#This Row],[ТП комплекта текущий без города (столбец создан с помощью Power Query)]],Таблица3[],4,0),0))),0) -> 0 | W72: Супер МТС. Область | X72: =IF(выгрузка__22[[#This Row],[Дата активации]]<>0,IF(выгрузка__22[[#This Row],[Дата блокировки]]<>"",CEILING((выгрузка__22[[#This Row],[Дата блокировки]]-выгрузка__22[[#This Row],[Дата активации]])/30,1),0),0) -> 0 | Y72: =IF(выгрузка__22[[#This Row],[Дата блокировки]]<>"",1,0) -> 0
A73: 41583.834 | B73: 910486 | C73: 8527896 | D73: 41583.83 | E73: =IF(выгрузка__22[[#This Row],[Дата активации]]<>"",MONTH(выгрузка__22[[#This Row],[Дата активации]]),0) -> 11 | F73: 41585.695 | G73: 79956 | H73: Непрофильный | I73: Тверь | J73: - МТС Коннект-4 (МАСС) (SCP) | K73: 30 | L73: 752 | M73: 782 | N73: Активен | P73: МТС Коннект-4 (МАСС) (SCP) | Q73: =IF(AND(DAY(выгрузка__22[[#This Row],[Дата отправки смс]])>=1,DAY(выгрузка__22[[#This Row],[Дата отправки смс]])<=14,MONTH(выгрузка__22[[#This Row],[Дата отправки смс]])=10),1,0) -> 0 | R73: =IF(выгрузка__22[[#This Row],[Дата регистрации]]="",0,1) -> 1 | S73: =IF(ISNA(VLOOKUP(выгрузка__22[[#This Row],[ЛС дилера]],'дилеры участники'!A:A,1,0)),0,1) -> 1 | T73: =IF(ISNA(VLOOKUP(выгрузка__22[[#This Row],[ТП комплекта текущий без города (столбец создан с помощью Power Query)]],Таблица3[Название ТП комплекта],1,0)),0,1) -> 1 | U73: =IF(ISNA(IF(выгрузка__22[[#This Row],[Канал продажи]]="Непрофильный",VLOOKUP(выгрузка__22[[#This Row],[ТП комплекта текущий без города (столбец создан с помощью Power Query)]],Таблица3[[Название ТП комплекта]:[Непрофильный]],3,0),VLOOKUP(выгрузка__22[[#This Row],[ТП комплекта текущий без города (столбец создан с помощью Power Query)]],Таблица3[[Название ТП комплекта]:[Непрофильный]],2,0)))=FALSE,1,0) -> 1 | V73: =IF(T73=1,IF(выгрузка__22[[#This Row],[Сумма дополнительного платежа и стартового баланса]]>300,VLOOKUP(выгрузка__22[[#This Row],[ТП комплекта текущий без города (столбец создан с помощью Power Query)]],Таблица3[],6,0),IF(выгрузка__22[[#This Row],[Сумма дополнительного платежа и стартового баланса]]>200,VLOOKUP(выгрузка__22[[#This Row],[ТП комплекта текущий без города (столбец создан с помощью Power Query)]],Таблица3[],5,0),IF(выгрузка__22[[#This Row],[Сумма дополнительного платежа и стартового баланса]]>100,VLOOKUP(выгрузка__22[[#This Row],[ТП комплекта текущий без города (столбец создан с помощью Power Query)]],Таблица3[],4,0),0))),0) -> 170 | W73: МТС Коннект-4 | X73: =IF(выгрузка__22[[#This Row],[Дата активации]]<>0,IF(выгрузка__22[[#This Row],[Дата блокировки]]<>"",CEILING((выгрузка__22[[#This Row],[Дата блокировки]]-выгрузка__22[[#This Row],[Дата активации]])/30,1),0),0) -> 0 | Y73: =IF(выгрузка__22[[#This Row],[Дата блокировки]]<>"",1,0) -> 0
A74: 41593.596 | B74: 916888 | C74: 1698680 | D74: 41583.782 | E74: =IF(выгрузка__22[[#This Row],[Дата активации]]<>"",MONTH(выгрузка__22[[#This Row],[Дата активации]]),0) -> 11 | F74: 41587.129 | G74: 64626 | H74: Непрофильный | I74: Ярославль | J74: - Супер МТС. Область (МАСС) (SCP) | K74: 30 | L74: 0 | M74: 30 | N74: Активен | P74: Супер МТС. Область (МАСС) (SCP) | Q74: =IF(AND(DAY(выгрузка__22[[#This Row],[Дата отправки смс]])>=1,DAY(выгрузка__22[[#This Row],[Дата отправки смс]])<=14,MONTH(выгрузка__22[[#This Row],[Дата отправки смс]])=10),1,0) -> 0 | R74: =IF(выгрузка__22[[#This Row],[Дата регистрации]]="",0,1) -> 1 | S74: =IF(ISNA(VLOOKUP(выгрузка__22[[#This Row],[ЛС дилера]],'дилеры участники'!A:A,1,0)),0,1) -> 0 | T74: =IF(ISNA(VLOOKUP(выгрузка__22[[#This Row],[ТП комплекта текущий без города (столбец создан с помощью Power Query)]],Таблица3[Название ТП комплекта],1,0)),0,1) -> 1 | U74: =IF(ISNA(IF(выгрузка__22[[#This Row],[Канал продажи]]="Непрофильный",VLOOKUP(выгрузка__22[[#This Row],[ТП комплекта текущий без города (столбец создан с помощью Power Query)]],Таблица3[[Название ТП комплекта]:[Непрофильный]],3,0),VLOOKUP(выгрузка__22[[#This Row],[ТП комплекта текущий без города (столбец создан с помощью Power Query)]],Таблица3[[Название ТП комплекта]:[Непрофильный]],2,0)))=FALSE,1,0) -> 1 | V74: =IF(T74=1,IF(выгрузка__22[[#This Row],[Сумма дополнительного платежа и стартового баланса]]>300,VLOOKUP(выгрузка__22[[#This Row],[ТП комплекта текущий без города (столбец создан с помощью Power Query)]],Таблица3[],6,0),IF(выгрузка__22[[#This Row],[Сумма дополнительного платежа и стартового баланса]]>200,VLOOKUP(выгрузка__22[[#This Row],[ТП комплекта текущий без города (столбец создан с помощью Power Query)]],Таблица3[],5,0),IF(выгрузка__22[[#This Row],[Сумма дополнительного платежа и стартового баланса]]>100,VLOOKUP(выгрузка__22[[#This Row],[ТП комплекта текущий без города (столбец создан с помощью Power Query)]],Таблица3[],4,0),0))),0) -> 0 | W74: Супер МТС. Область | X74: =IF(выгрузка__22[[#This Row],[Дата активации]]<>0,IF(выгрузка__22[[#This Row],[Дата блокировки]]<>"",CEILING((выгрузка__22[[#This Row],[Дата блокировки]]-выгрузка__22[[#This Row],[Дата активации]])/30,1),0),0) -> 0 | Y74: =IF(выгрузка__22[[#This Row],[Дата блокировки]]<>"",1,0) -> 0
A75: 41593.502 | B75: 985210 | C75: 1754805 | D75: 41583.772 | E75: =IF(выгрузка__22[[#This Row],[Дата активации]]<>"",MONTH(выгрузка__22[[#This Row],[Дата активации]]),0) -> 11 | F75: 41586.867 | G75: 64626 | H75: Непрофильный | I75: Ярославль | J75: - МТС Коннект-4 (МАСС) (SCP) | K75: 30 | L75: 0 | M75: 30 | N75: Активен | P75: МТС Коннект-4 (МАСС) (SCP) | Q75: =IF(AND(DAY(выгрузка__22[[#This Row],[Дата отправки смс]])>=1,DAY(выгрузка__22[[#This Row],[Дата отправки смс]])<=14,MONTH(выгрузка__22[[#This Row],[Дата отправки смс]])=10),1,0) -> 0 | R75: =IF(выгрузка__22[[#This Row],[Дата регистрации]]="",0,1) -> 1 | S75: =IF(ISNA(VLOOKUP(выгрузка__22[[#This Row],[ЛС дилера]],'дилеры участники'!A:A,1,0)),0,1) -> 0 | T75: =IF(ISNA(VLOOKUP(выгрузка__22[[#This Row],[ТП комплекта текущий без города (столбец создан с помощью Power Query)]],Таблица3[Название ТП комплекта],1,0)),0,1) -> 1 | U75: =IF(ISNA(IF(выгрузка__22[[#This Row],[Канал продажи]]="Непрофильный",VLOOKUP(выгрузка__22[[#This Row],[ТП комплекта текущий без города (столбец создан с помощью Power Query)]],Таблица3[[Название ТП комплекта]:[Непрофильный]],3,0),VLOOKUP(выгрузка__22[[#This Row],[ТП комплекта текущий без города (столбец создан с помощью Power Query)]],Таблица3[[Название ТП комплекта]:[Непрофильный]],2,0)))=FALSE,1,0) -> 1 | V75: =IF(T75=1,IF(выгрузка__22[[#This Row],[Сумма дополнительного платежа и стартового баланса]]>300,VLOOKUP(выгрузка__22[[#This Row],[ТП комплекта текущий без города (столбец создан с помощью Power Query)]],Таблица3[],6,0),IF(выгрузка__22[[#This Row],[Сумма дополнительного платежа и стартового баланса]]>200,VLOOKUP(выгрузка__22[[#This Row],[ТП комплекта текущий без города (столбец создан с помощью Power Query)]],Таблица3[],5,0),IF(выгрузка__22[[#This Row],[Сумма дополнительного платежа и стартового баланса]]>100,VLOOKUP(выгрузка__22[[#This Row],[ТП комплекта текущий без города (столбец создан с помощью Power Query)]],Таблица3[],4,0),0))),0) -> 0 | W75: МТС Коннект-4 | X75: =IF(выгрузка__22[[#This Row],[Дата активации]]<>0,IF(выгрузка__22[[#This Row],[Дата блокировки]]<>"",CEILING((выгрузка__22[[#This Row],[Дата блокировки]]-выгрузка__22[[#This Row],[Дата активации]])/30,1),0),0) -> 0 | Y75: =IF(выгрузка__22[[#This Row],[Дата блокировки]]<>"",1,0) -> 0
A76: 41593.5 | B76: 985210 | C76: 8524829 | D76: 41583.555 | E76: =IF(выгрузка__22[[#This Row],[Дата активации]]<>"",MONTH(выгрузка__22[[#This Row],[Дата активации]]),0) -> 11 | F76: 41584.621 | G76: 64626 | H76: Непрофильный | I76: Ярославль | J76: - МТС Коннект-4 (МАСС) (SCP) | K76: 401 | L76: 0 | M76: 401 | N76: Активен | P76: МТС Коннект-4 (МАСС) (SCP) | Q76: =IF(AND(DAY(выгрузка__22[[#This Row],[Дата отправки смс]])>=1,DAY(выгрузка__22[[#This Row],[Дата отправки смс]])<=14,MONTH(выгрузка__22[[#This Row],[Дата отправки смс]])=10),1,0) -> 0 | R76: =IF(выгрузка__22[[#This Row],[Дата регистрации]]="",0,1) -> 1 | S76: =IF(ISNA(VLOOKUP(выгрузка__22[[#This Row],[ЛС дилера]],'дилеры участники'!A:A,1,0)),0,1) -> 0 | T76: =IF(ISNA(VLOOKUP(выгрузка__22[[#This Row],[ТП комплекта текущий без города (столбец создан с помощью Power Query)]],Таблица3[Название ТП комплекта],1,0)),0,1) -> 1 | U76: =IF(ISNA(IF(выгрузка__22[[#This Row],[Канал продажи]]="Непрофильный",VLOOKUP(выгрузка__22[[#This Row],[ТП комплекта текущий без города (столбец создан с помощью Power Query)]],Таблица3[[Название ТП комплекта]:[Непрофильный]],3,0),VLOOKUP(выгрузка__22[[#This Row],[ТП комплекта текущий без города (столбец создан с помощью Power Query)]],Таблица3[[Название ТП комплекта]:[Непрофильный]],2,0)))=FALSE,1,0) -> 1 | V76: =IF(T76=1,IF(выгрузка__22[[#This Row],[Сумма дополнительного платежа и стартового баланса]]>300,VLOOKUP(выгрузка__22[[#This Row],[ТП комплекта текущий без города (столбец создан с помощью Power Query)]],Таблица3[],6,0),IF(выгрузка__22[[#This Row],[Сумма дополнительного платежа и стартового баланса]]>200,VLOOKUP(выгрузка__22[[#This Row],[ТП комплекта текущий без города (столбец создан с помощью Power Query)]],Таблица3[],5,0),IF(выгрузка__22[[#This Row],[Сумма дополнительного платежа и стартового баланса]]>100,VLOOKUP(выгрузка__22[[#This Row],[ТП комплекта текущий без города (столбец создан с помощью Power Query)]],Таблица3[],4,0),0))),0) -> 170 | W76: МТС Коннект-4 | X76: =IF(выгрузка__22[[#This Row],[Дата активации]]<>0,IF(выгрузка__22[[#This Row],[Дата блокировки]]<>"",CEILING((выгрузка__22[[#This Row],[Дата блокировки]]-выгрузка__22[[#This Row],[Дата активации]])/30,1),0),0) -> 0 | Y76: =IF(выгрузка__22[[#This Row],[Дата блокировки]]<>"",1,0) -> 0
A77: 41593.597 | B77: 916888 | C77: 1698723 | D77: 41583.531 | E77: =IF(выгрузка__22[[#This Row],[Дата активации]]<>"",MONTH(выгрузка__22[[#This Row],[Дата активации]]),0) -> 11 | F77: 41587.129 | G77: 64626 | H77: Непрофильный | I77: Ярославль | J77: - Супер МТС. Область (МАСС) (SCP) | K77: 30 | L77: 0 | M77: 30 | N77: Активен | P77: Супер МТС. Область (МАСС) (SCP) | Q77: =IF(AND(DAY(выгрузка__22[[#This Row],[Дата отправки смс]])>=1,DAY(выгрузка__22[[#This Row],[Дата отправки смс]])<=14,MONTH(выгрузка__22[[#This Row],[Дата отправки смс]])=10),1,0) -> 0 | R77: =IF(выгрузка__22[[#This Row],[Дата регистрации]]="",0,1) -> 1 | S77: =IF(ISNA(VLOOKUP(выгрузка__22[[#This Row],[ЛС дилера]],'дилеры участники'!A:A,1,0)),0,1) -> 0 | T77: =IF(ISNA(VLOOKUP(выгрузка__22[[#This Row],[ТП комплекта текущий без города (столбец создан с помощью Power Query)]],Таблица3[Название ТП комплекта],1,0)),0,1) -> 1 | U77: =IF(ISNA(IF(выгрузка__22[[#This Row],[Канал продажи]]="Непрофильный",VLOOKUP(выгрузка__22[[#This Row],[ТП комплекта текущий без города (столбец создан с помощью Power Query)]],Таблица3[[Название ТП комплекта]:[Непрофильный]],3,0),VLOOKUP(выгрузка__22[[#This Row],[ТП комплекта текущий без города (столбец создан с помощью Power Query)]],Таблица3[[Название ТП комплекта]:[Непрофильный]],2,0)))=FALSE,1,0) -> 1 | V77: =IF(T77=1,IF(выгрузка__22[[#This Row],[Сумма дополнительного платежа и стартового баланса]]>300,VLOOKUP(выгрузка__22[[#This Row],[ТП комплекта текущий без города (столбец создан с помощью Power Query)]],Таблица3[],6,0),IF(выгрузка__22[[#This Row],[Сумма дополнительного платежа и стартового баланса]]>200,VLOOKUP(выгрузка__22[[#This Row],[ТП комплекта текущий без города (столбец создан с помощью Power Query)]],Таблица3[],5,0),IF(выгрузка__22[[#This Row],[Сумма дополнительного платежа и стартового баланса]]>100,VLOOKUP(выгрузка__22[[#This Row],[ТП комплекта текущий без города (столбец создан с помощью Power Query)]],Таблица3[],4,0),0))),0) -> 0 | W77: Супер МТС. Область | X77: =IF(выгрузка__22[[#This Row],[Дата активации]]<>0,IF(выгрузка__22[[#This Row],[Дата блокировки]]<>"",CEILING((выгрузка__22[[#This Row],[Дата блокировки]]-выгрузка__22[[#This Row],[Дата активации]])/30,1),0),0) -> 0 | Y77: =IF(выгрузка__22[[#This Row],[Дата блокировки]]<>"",1,0) -> 0
A78: 41593.568 | B78: 916513 | C78: 8538212 | D78: 41583.527 | E78: =IF(выгрузка__22[[#This Row],[Дата активации]]<>"",MONTH(выгрузка__22[[#This Row],[Дата активации]]),0) -> 11 | G78: 64626 | H78: Непрофильный | I78: Ярославль | J78: - Супер МТС (МАСС) (SCP) | K78: 1 | L78: 0 | M78: 1 | N78: Активен | P78: Супер МТС (МАСС) (SCP) | Q78: =IF(AND(DAY(выгрузка__22[[#This Row],[Дата отправки смс]])>=1,DAY(выгрузка__22[[#This Row],[Дата отправки смс]])<=14,MONTH(выгрузка__22[[#This Row],[Дата отправки смс]])=10),1,0) -> 0 | R78: =IF(выгрузка__22[[#This Row],[Дата регистрации]]="",0,1) -> 0 | S78: =IF(ISNA(VLOOKUP(выгрузка__22[[#This Row],[ЛС дилера]],'дилеры участники'!A:A,1,0)),0,1) -> 0 | T78: =IF(ISNA(VLOOKUP(выгрузка__22[[#This Row],[ТП комплекта текущий без города (столбец создан с помощью Power Query)]],Таблица3[Название ТП комплекта],1,0)),0,1) -> 1 | U78: =IF(ISNA(IF(выгрузка__22[[#This Row],[Канал продажи]]="Непрофильный",VLOOKUP(выгрузка__22[[#This Row],[ТП комплекта текущий без города (столбец создан с помощью Power Query)]],Таблица3[[Название ТП комплекта]:[Непрофильный]],3,0),VLOOKUP(выгрузка__22[[#This Row],[ТП комплекта текущий без города (столбец создан с помощью Power Query)]],Таблица3[[Название ТП комплекта]:[Непрофильный]],2,0)))=FALSE,1,0) -> 1 | V78: =IF(T78=1,IF(выгрузка__22[[#This Row],[Сумма дополнительного платежа и стартового баланса]]>300,VLOOKUP(выгрузка__22[[#This Row],[ТП комплекта текущий без города (столбец создан с помощью Power Query)]],Таблица3[],6,0),IF(выгрузка__22[[#This Row],[Сумма дополнительного платежа и стартового баланса]]>200,VLOOKUP(выгрузка__22[[#This Row],[ТП комплекта текущий без города (столбец создан с помощью Power Query)]],Таблица3[],5,0),IF(выгрузка__22[[#This Row],[Сумма дополнительного платежа и стартового баланса]]>100,VLOOKUP(выгрузка__22[[#This Row],[ТП комплекта текущий без города (столбец создан с помощью Power Query)]],Таблица3[],4,0),0))),0) -> 0 | W78: Супер МТС | X78: =IF(выгрузка__22[[#This Row],[Дата активации]]<>0,IF(выгрузка__22[[#This Row],[Дата блокировки]]<>"",CEILING((выгрузка__22[[#This Row],[Дата блокировки]]-выгрузка__22[[#This Row],[Дата активации]])/30,1),0),0) -> 0 | Y78: =IF(выгрузка__22[[#This Row],[Дата блокировки]]<>"",1,0) -> 0
A79: 41593.504 | B79: 985210 | C79: 1754981 | D79: 41583.508 | E79: =IF(выгрузка__22[[#This Row],[Дата активации]]<>"",MONTH(выгрузка__22[[#This Row],[Дата активации]]),0) -> 11 | F79: 41586.866 | G79: 64626 | H79: Непрофильный | I79: Ярославль | J79: - МТС Коннект-4 (МАСС) (SCP) | K79: 30 | L79: 800 | M79: 830 | N79: Активен | P79: МТС Коннект-4 (МАСС) (SCP) | Q79: =IF(AND(DAY(выгрузка__22[[#This Row],[Дата отправки смс]])>=1,DAY(выгрузка__22[[#This Row],[Дата отправки смс]])<=14,MONTH(выгрузка__22[[#This Row],[Дата отправки смс]])=10),1,0) -> 0 | R79: =IF(выгрузка__22[[#This Row],[Дата регистрации]]="",0,1) -> 1 | S79: =IF(ISNA(VLOOKUP(выгрузка__22[[#This Row],[ЛС дилера]],'дилеры участники'!A:A,1,0)),0,1) -> 0 | T79: =IF(ISNA(VLOOKUP(выгрузка__22[[#This Row],[ТП комплекта текущий без города (столбец создан с помощью Power Query)]],Таблица3[Название ТП комплекта],1,0)),0,1) -> 1 | U79: =IF(ISNA(IF(выгрузка__22[[#This Row],[Канал продажи]]="Непрофильный",VLOOKUP(выгрузка__22[[#This Row],[ТП комплекта текущий без города (столбец создан с помощью Power Query)]],Таблица3[[Название ТП комплекта]:[Непрофильный]],3,0),VLOOKUP(выгрузка__22[[#This Row],[ТП комплекта текущий без города (столбец создан с помощью Power Query)]],Таблица3[[Название ТП комплекта]:[Непрофильный]],2,0)))=FALSE,1,0) -> 1 | V79: =IF(T79=1,IF(выгрузка__22[[#This Row],[Сумма дополнительного платежа и стартового баланса]]>300,VLOOKUP(выгрузка__22[[#This Row],[ТП комплекта текущий без города (столбец создан с помощью Power Query)]],Таблица3[],6,0),IF(выгрузка__22[[#This Row],[Сумма дополнительного платежа и стартового баланса]]>200,VLOOKUP(выгрузка__22[[#This Row],[ТП комплекта текущий без города (столбец создан с помощью Power Query)]],Таблица3[],5,0),IF(выгрузка__22[[#This Row],[Сумма дополнительного платежа и стартового баланса]]>100,VLOOKUP(выгрузка__22[[#This Row],[ТП комплекта текущий без города (столбец создан с помощью Power Query)]],Таблица3[],4,0),0))),0) -> 170 | W79: МТС Коннект-4 | X79: =IF(выгрузка__22[[#This Row],[Дата активации]]<>0,IF(выгрузка__22[[#This Row],[Дата блокировки]]<>"",CEILING((выгрузка__22[[#This Row],[Дата блокировки]]-выгрузка__22[[#This Row],[Дата активации]])/30,1),0),0) -> 0 | Y79: =IF(выгрузка__22[[#This Row],[Дата блокировки]]<>"",1,0) -> 0
A80: 41593.572 | B80: 916513 | C80: 1698613 | D80: 41583.43 | E80: =IF(выгрузка__22[[#This Row],[Дата активации]]<>"",MONTH(выгрузка__22[[#This Row],[Дата активации]]),0) -> 11 | F80: 41534.59 | G80: 64626 | H80: Непрофильный | I80: Ярославль | J80: - Супер МТС (МАСС) (SCP) | K80: 50 | L80: 0 | M80: 50 | N80: Активен | P80: Супер МТС (МАСС) (SCP) | Q80: =IF(AND(DAY(выгрузка__22[[#This Row],[Дата отправки смс]])>=1,DAY(выгрузка__22[[#This Row],[Дата отправки смс]])<=14,MONTH(выгрузка__22[[#This Row],[Дата отправки смс]])=10),1,0) -> 0 | R80: =IF(выгрузка__22[[#This Row],[Дата регистрации]]="",0,1) -> 1 | S80: =IF(ISNA(VLOOKUP(выгрузка__22[[#This Row],[ЛС дилера]],'дилеры участники'!A:A,1,0)),0,1) -> 0 | T80: =IF(ISNA(VLOOKUP(выгрузка__22[[#This Row],[ТП комплекта текущий без города (столбец создан с помощью Power Query)]],Таблица3[Название ТП комплекта],1,0)),0,1) -> 1 | U80: =IF(ISNA(IF(выгрузка__22[[#This Row],[Канал продажи]]="Непрофильный",VLOOKUP(выгрузка__22[[#This Row],[ТП комплекта текущий без города (столбец создан с помощью Power Query)]],Таблица3[[Название ТП комплекта]:[Непрофильный]],3,0),VLOOKUP(выгрузка__22[[#This Row],[ТП комплекта текущий без города (столбец создан с помощью Power Query)]],Таблица3[[Название ТП комплекта]:[Непрофильный]],2,0)))=FALSE,1,0) -> 1 | V80: =IF(T80=1,IF(выгрузка__22[[#This Row],[Сумма дополнительного платежа и стартового баланса]]>300,VLOOKUP(выгрузка__22[[#This Row],[ТП комплекта текущий без города (столбец создан с помощью Power Query)]],Таблица3[],6,0),IF(выгрузка__22[[#This Row],[Сумма дополнительного платежа и стартового баланса]]>200,VLOOKUP(выгрузка__22[[#This Row],[ТП комплекта текущий без города (столбец создан с помощью Power Query)]],Таблица3[],5,0),IF(выгрузка__22[[#This Row],[Сумма дополнительного платежа и стартового баланса]]>100,VLOOKUP(выгрузка__22[[#This Row],[ТП комплекта текущий без города (столбец создан с помощью Power Query)]],Таблица3[],4,0),0))),0) -> 0 | W80: Супер МТС | X80: =IF(выгрузка__22[[#This Row],[Дата активации]]<>0,IF(выгрузка__22[[#This Row],[Дата блокировки]]<>"",CEILING((выгрузка__22[[#This Row],[Дата блокировки]]-выгрузка__22[[#This Row],[Дата активации]])/30,1),0),0) -> 0 | Y80: =IF(выгрузка__22[[#This Row],[Дата блокировки]]<>"",1,0) -> 0
